Workbook

Sheet Planilla Global  - Cumplim (%)
D2: Lista de Verificación de Cumplimiento Requisitos Legales y Otros Aplicable a Seguridad, Salud Ocupacional, Medioambiente y Comunidad Contrato 4600029025 - SKIC CC-101 | H2: Código | I2: MTRSE-00002
H3: Revisión | I3: 3
H4: Fecha | I4: 46288
B6: N° | C6: Cuerpo Legal | D6: Organismo | E6: Materia | F6: Nombre del Cuerpo Legal | G6: % Cumplimiento | H6: Link | I6: Columna1
B7: 1 | C7: Ley 16.744 | D7: MINISTERIO DEL TRABAJO Y PREVISION SOCIAL. | E7: Seguridad y Salud | F7: Establece Normas sobre Accidentes del Trabajo y Enfermedades Profesionales | G7: 1 | H7: https://www.leychile.cl/Navegar?idNorma=28650&idVersion=2019-01-01 | I7: Vigente / Modificado
B8: 2 | C8: Ley 18.290 | D8: MINISTERIO DE JUSTICIA | E8: Seguridad | F8: Ley de Transito | G8: 1 | H8: https://www.leychile.cl/Navegar?idNorma=29708 | I8: Vigente
B9: 3 | C9: Ley 19.303 | D9: MINISTERIO DEL INTERIOR | E9: Seguridad | F9: Establece Obligaciones a Entidades que indica, en Materia de Seguridad de las Personas | G9: 1 | H9: https://www.leychile.cl/Navegar?idNorma=30670 | I9: Vigente
B10: 4 | C10: LEY 19.404 | D10: MINISTERIO DE SALUD | E10: RRHH | F10: Introduce modificación al Decreto Ley Nº 3.500, de 1980, Texto Original del 01-03-2009 y dicta normas relativas a pensiones de vejez, considerando el desempeño de trabajos pesados. | G10: N/A | H10: https://www.bcn.cl/leychile/navegar?idNorma=30771 | I10: Vigente
B11: 5 | C11: Ley 19.419 | D11: MINISTERIO DE SALUD | E11: Medio Ambiente | F11: Regula Actividades que indica Relacionadas con el Tabaco | G11: 1 | H11: https://www.leychile.cl/Navegar?idNorma=30786 | I11: Vigente / Modificado
B12: 6 | C12: Ley 19.518 | D12: MINISTERIO DEL TRABAJO Y PREVISIÓN | E12: RRHH | F12: Fija nuevo estatuto de capacitación y empleo | G12: 0 | H12: https://www.bcn.cl/leychile/navegar?idNorma=76201 | I12: Vigente
B13: 7 | C13: Ley 19.628 | D13: MINISTERIO SECRETARIA GENERAL DE LA PRESIDENCIA | E13: RRLL | F13: Derecho a la Privacidad | G13: 1 | H13: https://www.leychile.cl/Navegar?idNorma=141599 | I13: Vigente / Modificado
B14: 8 | C14: Ley 19.728 | D14: MINISTERIO DEL TRABAJO Y PREVISION SOCIAL. | E14: RRLL | F14: Establece un Seguro de desempleo | G14: 1 | H14: https://www.leychile.cl/Navegar?idNorma=184979 | I14: Vigente
B15: 9 | C15: LEY 20.000 | D15: MINISTERIO DEL INTERIOR | E15: RRHH | F15: Sustituye la ley Nº 19.366, que sanciona el trafico ilícito de estupefacientes y sustancias psicotrópicas | G15: 1 | H15: https://www.bcn.cl/leychile/navegar?idNorma=235507 | I15: Vigente
B16: 10 | C16: Ley 20.001 | D16: MINISTERIO DEL TRABAJO Y PREVISION SOCIAL. | E16: Seguridad | F16: Regula el Peso Máximo de Carga Humana | G16: 1 | H16: https://www.leychile.cl/Navegar?idNorma=235279 | I16: Modificada 20949
B17: 11 | C17: Ley 20.005 | D17: MINISTERIO DEL TRABAJO Y PREVISION SOCIAL. | E17: RRLL | F17: Tipifica y Sanciona el Acoso Sexual | G17: 1 | H17: https://www.leychile.cl/Navegar?idNorma=236425 | I17: Vigente / Modificado
B18: 12 | C18: Ley 20.047 | D18: MINISTERIO DEL TRABAJO Y PREVISION SOCIAL. | E18: RRLL | F18: Establece un Permiso Paternal en el Código del Trabajo | G18: 1 | H18: https://www.leychile.cl/Navegar?idNorma=241556 | I18: Vigente
B19: 13 | C19: LEY 20.068 | D19: MINISTERIO DE TRANSPORTE Y TELECOMUNICACIONES | E19: HSEC | F19: Actualización Ley de transito Introduce diversas modificaciones a la ley Nº 18.290, en materia de tránsito terrestre | G19: 1 | H19: https://www.bcn.cl/leychile/navegar?idNorma=244868 | I19: Vigente
B20: 14 | C20: Ley 20.096 | D20: MINISTERIO SECRETARIA GENERAL DE LA PRESIDENCIA | E20: Medio Ambiente | F20: Establece Mecanismos de Control Aplicables a la Sustancias Agotadoras de la Capa de Ozono | G20: 1 | H20: https://www.leychile.cl/Navegar?idNorma=248323 | I20: Vigente
B21: 15 | C21: Ley 20.101 | D21: MINISTERIO DEL TRABAJO Y PREVISION SOCIAL. | E21: Seguridad | F21: Amplia el concepto de accidente de Trabajo contemplado en la ley Nº 16.744, sobre Accidente del Trabajo y Enfermedades Profesionales | G21: 1 | H21: https://www.leychile.cl/Navegar?idNorma=249199 | I21: Vigente
B22: 16 | C22: LEY 20.105 | D22: Ministerio de Salud, Subsecretaria de Salud Pública | E22: RRLL | F22: Modifica la ley Nº 19.419, en materias relativas a la publicidad y el consumo del tabaco | G22: 1 | H22: https://www.bcn.cl/leychile/navegar?idNorma=249682&idVersion=2006-05-16 | I22: Vigente
... B71: 66 | C71: Decreto 48 | D71: MINISTERIO DEL TRABAJO Y PREVISIÓN SOCIAL | E71: Salud | F71: Introduce modificaciones en el reglamento para la aplicación de la ley N° 20.001 que regula el peso máximo de carga humana, contenido en el decreto supremo N°63 | G71: 1 | H71: Decreto-48 17-ENE-2018 MINISTERIO DEL TRABAJO Y PREVISIÓN SOCIAL - Ley Chile - Biblioteca del Congreso Nacional (bcn.cl) | I71: Vigente
B72: 67 | C72: Decreto 49 | D72: MINISTERIO DEL TRABAJO | E72: RRHH | F72: Modifica decreto supremo 71, de 1996, que aprueba reglamento para la aplicación de la ley 19.404, que introduce modificaciones al dl 3.500, y dicta normas relativas a pensiones de vejez | G72: N/A | H72: https://www.bcn.cl/leychile/navegar?i=1115974&f=2018-03-09&p=9893266 | I72: Vigente
B73: 68 | C73: Decreto 55 | D73: MINISTERIO DEL TRANSPORTE Y TELECOMUNICACIONES | E73: Medio Ambiente | F73: Establece Normas de Emisión Aplicables a Vehículos Motorizados Pesados Que Indica | G73: 1 | H73: https://www.leychile.cl/Navegar?idNorma=8364 | I73: Vigente
B74: 69 | C74: Decreto 63 | D74: MINISTERIO DEL TRABAJO Y PREVISION SOCIAL. | E74: Seguridad y Salud | F74: Aprueba reglamento para la aplicación de la Ley 20.001, que regula el peso máximo de carga humana | G74: 1 | H74: https://www.leychile.cl/Navegar?idNorma=241855 | I74: Vigente / Modificado
B75: 70 | C75: Decreto 67 | D75: MINISTERIO DEL TRABAJO Y PREVISION SOCIAL. | E75: Seguridad | F75: Aprueba Reglamento para Aplicación de Artículos 15 y 16 de Ley N°16.744, sobre exenciones, rebajas y recargos de la cotización adicional diferenciada. | G75: 1 | H75: https://www.leychile.cl/Navegar?idNorma=159800 | I75: Vigente / Modificado
B76: 71 | C76: Decreto 73 | D76: MINISTERIO DEL TRABAJO Y PREVISIÓN SOCIAL | E76: HSEC | F76: Introduce modificaciones en el reglamento para la aplicación de la ley nº16.744, que establece normas sobre accidentes del trabajo y enfermedades profesionales, contenido en el decreto supremo Nº 101, de 1968, del ministerio del trabajo y previsión social, y en el reglamento para la calificación y evaluación de los accidentes del trabajo y enfermedades profesionales, contenido en el decreto supremo Nº 109, de 1968, del ministerio del trabajo y previsión social | G76: 1 | H76: https://www.bcn.cl/leychile/navegar?idNorma=247787 | I76: Vigente
B77: 72 | C77: Decreto 76 | D77: MINISTERIO DEL TRABAJO Y PREVISION SOCIAL. | E77: Seguridad y Salud | F77: Aprueba Reglamento para la aplicación del artículo 66 bis de la Ley N° 16.744 sobre la gestión de la seguridad y salud en el trabajo en obras, faenas o servicios que indica | G77: 1 | H77: https://www.leychile.cl/Navegar?idNorma=257601 | I77: Vigente
B78: 73 | C78: Decreto 97 | D78: MINISTERIO SECRETARIA GENERAL DE LA PRESIDENCIA | E78: Seguridad y Salud | F78: Modifica Decreto N°594 de 1999, sobre condiciones básicas en los lugares de trabajo | G78: 1 | H78: https://www.bcn.cl/leychile/navegar?idNorma=1021867&idParte=9094939&idVersion=2011-03-08 | I78: Vigente
B79: 74 | C79: Decreto 100 | D79: MINISTERIO SECRETARIA GENERAL DE LA PRESIDENCIA | E79: Medio Ambiente | F79: Fija el Texto Refundido Coordinado y Sistematizado de la Constitución Política de la Republica de Chile | G79: 1 | H79: https://www.leychile.cl/Navegar?idNorma=242302 | I79: Vigente
B80: 75 | C80: Decreto 101 | D80: MINISTERIO DEL TRABAJO Y PREVISION SOCIAL. | E80: Seguridad y Salud | F80: Reglamento para la aplicación de la Ley N°16.744, que establece normas sobre Accidentes del Trabajo y Enfermedades Profesionales | G80: 1 | H80: https://www.leychile.cl/Navegar?idNorma=9231 | I80: Vigente / Modificado
B81: 76 | C81: Decreto 109 | D81: MINISTERIO DEL TRABAJO Y PREVISION SOCIAL. | E81: Seguridad y Salud | F81: Reglamento para la Calificación y Evaluación de los Accidentes del Trabajo y Enfermedades Profesionales | G81: 1 | H81: https://www.leychile.cl/Navegar?idNorma=9391 | I81: Cumplimiento O.A.L.
B82: 77 | C82: Decreto 110 | D82: MINISTERIO DEL TRABAJO Y PREVISION SOCIAL. | E82: Seguridad y Salud | F82: Escala para la determinación de la cotización adicional diferenciada | G82: 1 | H82: https://www.leychile.cl/Navegar?idNorma=179501 | I82: Vigente
B83: 78 | C83: Decreto 132 | D83: MINISTERIO DE MINERÍA | E83: Seguridad | F83: Aprueba Reglamento de Seguridad Minera | G83: 1 | H83: https://www.leychile.cl/Navegar?idNorma=221064 | I83: Vigente
B84: 79 | C84: Decreto 144 | D84: MINISTERIO DE SALUD | E84: Medio Ambiente | F84: Establece Normas Para Evitar Emanaciones o Contaminantes Atmosféricos de Cualquiera Naturaleza | G84: 1 | H84: https://www.leychile.cl/Navegar?idNorma=9981 | I84: Vigente / Modificado
... B92: 88 | C92: Decreto 1.052 Exento | D92: MINISTERIO DE SALUD | E92: Salud | F92: Aprueba Norma Técnica N°156 denominada "Protocolo sobre normas mínimas para el desarrollo de programas de vigilancia de la perdida auditiva por exposición a ruido en los lugares de trabajo" | G92: 1 | H92: https://www.leychile.cl/Navegar?idNorma=1069385 | I92: Vigente
B93: 89 | C93: Decreto 1159 Exento | D93: MINISTERIO DE SALUD | E93: Seguridad | F93: Declara normas oficiales de la Republica de Chile | G93: 1 | H93: https://www.bcn.cl/leychile/navegar?idNorma=247502&idVersion=2006-02-23
B94: 90 | C94: Resolución 19 Exenta | D94: MINISTERIO DE SALUD | E94: Seguridad | F94: Aprueba guía para la selección y control de cascos de protección uso industrial | G94: 1 | H94: https://www.leychile.cl/Navegar?idNorma=1048391 | I94: Vigente / Modificado
B95: 91 | C95: Resolución 22 Exenta | D95: MINISTERIO DE SALUD | E95: Salud | F95: Actualiza guía técnica de evaluación y control de riesgos asociados al manejo o manipulación manual de carga | G95: 1 | H95: Resolución-22 EXENTA 10-FEB-2018 MINISTERIO DEL TRABAJO Y PREVISIÓN SOCIAL - Ley Chile - Biblioteca del Congreso Nacional (bcn.cl) | I95: Vigente
B96: 92 | C96: Resolución 129 Exenta | D96: MINISTERIO DEL TRABAJO Y PREVISIÓN SOCIAL | E96: Seguridad | F96: Dicta "guía para la elaboración de mapas de riesgos laborales al interior de las entidades empleadoras" | G96: 1 | H96: Ley Chile - Resolución 129 EXENTA 18-FEB-2025 MINISTERIO DEL TRABAJO Y PREVISIÓN SOCIAL, SUBSECRETARÍA DE PREVISIÓN SOCIAL - Biblioteca del Congreso Nacional | I96: Vigente
B97: 93 | C97: Resolución 156 Exenta | D97: MINISTERIO DEL TRABAJO Y PREVISION SOCIAL. | E97: Seguridad y Salud | F97: Aprueba Compendio de Normas del Seguro Social de Accidentes del Trabajo y Enfermedades Profesionales de la Ley 16.744, Deroga y Declara Inaplicables Circulares que indica | G97: 1 | H97: https://www.leychile.cl/Navegar?idNorma=1116045 | I97: Vigente / Modificado
B98: 94 | C98: Resolución 172 Exenta | D98: MINISTERIO DE SALUD | E98: Salud | F98: Aprueba Protocolo para la Toma de Muestra de Sílice Libre Cristalizada en su fracción respirable y de polvo no clasificado total y fracción respirable. | G98: 1 | H98: https://www.leychile.cl/Navegar?idNorma=1048619 | I98: Vigente / Modificado
B99: 95 | C99: Resolución 268 Exenta | D99: MINISTERIO DE SALUD | E99: Salud | F99: Aprueba protocolo de vigilancia del ambiente y de la salud de los trabajadores con exposición a la sílice | G99: 1 | H99: https://www.leychile.cl/Navegar?idNorma=1083722 | I99: Vigente
B100: 96 | C100: Resolución 606 Exenta | D100: MINISTERIO DE SALUD | E100: Salud | F100: Aprueba Protocolo de Vigilancia Ocupacional por Exposición a Metales y Metaloides | G100: 1 | H100: https://www.bcn.cl/leychile/navegar?i=1193025 | I100: Vigente
B101: 97 | C101: Resolución 909 Exenta | D101: MINISTERIO DE SALUD | E101: HSEC | F101: Aprueba el documento "Guía para la selección y control de equipos de protección respiratoria" | G101: 1 | H101: https://www.bcn.cl/leychile/navegar?idNorma=1130908 | I101: Vigente
B102: 98 | C102: Resolución 971 Exenta | D102: MINISTERIO DE SALUD | E102: Seguridad | F102: Establece criterios técnicos de calificación de la idoneidad de los elementos de protección personal comercializados en el país para uso en los lugares de trabajo | G102: 1 | H102: https://www.leychile.cl/Navegar/index_html?idNorma=1043130 | I102: Vigente
B103: 99 | C103: Resolución 1.031 Exenta | D103: MINISTERIO DE SALUD | E103: Seguridad | F103: Aprueba guía que contiene recomendaciones para la selección, uso, mantención, limpieza, almacenamiento y control para trabajos con riesgos de caída | G103: 1 | H103: https://www.leychile.cl/Navegar?idNorma=1003227 | I103: Vigente / Modificado
B104: 100 | C104: Resolución 1059 Exenta | D104: MINISTERIO DE SALUD | E104: Salud | F104: Modifica "protocolo de vigilancia del ambiente de trabajo y de la salud de los trabajadores expuestos a sílice" aprobado por resolución exenta n°268, de 2015, del ministerio de salud | G104: 1 | H104: https://www.minsal.cl/sites/default/files/files/ResExt1059_2016ModificaProtocoloVigilanciadeSilice.pdf | I104: Vigente
B105: 101 | C105: Resolución 1391 Exenta | D105: MINISTERIO DE SALUD | E105: Salud | F105: Aprueba guía que contiene recomendaciones para la selección, uso, mantención y almacenamiento de equipos de protección respiratoria | G105: 1 | H105: https://www.leychile.cl/Navegar?idNorma=268976 | I105: Vigente / Modificado
... B108: 104 | C108: Resolución 1538 Exenta | D108: MINISTERIO DE SALUD | E108: Seguridad y Salud | F108: Aprueba Guía para la gestión de elementos de protección personal en entidades empleadoras, elaborada por el Departamento de Salud Ocupacional del ISP de Chile. | G108: 1 | H108: http://www.ispch.cl/sites/default/files/resolucion/2010/10/Res%201924%202010.pdf | I108: Vigente
B109: 105 | C109: Resolución 1660 Exenta | D109: MINISTERIO DE SALUD | E109: Salud | F109: Protocolo TMERT V2 - DEROGADO; sustituido por Res. Ex. N° 1.697/2026 (TMERT V3) | G109: N/A | H109: https://www.bcn.cl/leychile/navegar?i=1209799&f=2026-02-25 | I109: DEROGADO 25-02-2026
B110: 106 | C110: Resolución 2863 Exenta | D110: MINISTERIO DE SALUD | E110: Salud | F110: Modifica la Resolución Exenta N° 909, del 12 de abril de 2019 que Aprueba Guía para la selección y control de equipos de Protección Respiratoria. | G110: 1 | H110: https://www.bcn.cl/leychile/navegar?idNorma=1139426&idVersion=2019-12-03 | I110: Vigente
B111: 107 | C111: Resolución 3457 Exenta | D111: MINISTERIO DE SALUD | E111: Seguridad | F111: Aprueba guía para la selección y control de protección ocular y facial, elaborada por el departamento de salud ocupacional | G111: 1 | H111: https://www.leychile.cl/Navegar?idNorma=1047962 | I111: Vigente / Modificado
B112: 108 | C112: Resolución 5921 Exenta | D112: MINISTERIO DE SALUD | E112: Salud | F112: Aprueba "Protocolo para la Evaluación de la Exposición a Ruido en los puestos de Trabajo" y deja sin efecto resoluciones que indica | G112: 1 | H112: https://www.ispch.gob.cl/wp-content/uploads/resoluciones/35569_5921-2025.pdf | I112: Vigente
B113: 109 | C113: CIRCULAR 148 | D113: MINISTERIO DEL TRABAJO Y PREVISION SOCIAL. | E113: RRLL | F113: Establece procedimiento para solicitar y emitir Certificado de Cumplimiento de Obligaciones Laborales y Previsionales y Certificado de Antecedentes Laborales y Previsionales. | G113: 1 | H113: http://www.dt.gob.cl/portal/1626/w3-article-94284.html | I113: Vigente
B114: 110 | C114: CIRCULAR 3221 | D114: SUPERINTENDENCIA DE SEGURIDAD SOCIAL | E114: Seguridad | F114: Accidente de Trayecto. Modifica, complementa y refunde instrucciones. Deroga Circular N°3154, de 2015 | G114: 1 | H114: https://www.suseso.cl/612/w3-article-7486.html | I114: Vigente
B115: 111 | C115: CIRCULAR 3298 | D115: MINISTERIO DEL TRABAJO Y PREVISIOÓN SOCIAL | E115: Seguridad | F115: Instruye a los organismos administradores del seguro de la Ley N°16.744, SOBRE EL Protocolo de normas mínimas de evaluación que deben cumplir en el proceso de calificación del origen de las enfermedades denunciadas como profesionales | G115: 1 | H115: https://www.suseso.cl/612/articles-7653_archivo_01.pdf | I115: Vigente
B116: 112 | C116: ORD. 0188 | D116: SERVICIO NACIONAL DE GEOLOGÍA Y MINERÍA | E116: Seguridad | F116: Exámenes Psicosensométrico Riguroso | G116: 1 | H116: http://copresem.cl/assets/resoluci%C3%B3n-sernageomin-nacional-2007.pdf | I116: Vigente
B117: 113 | C117: Consumo de Tabaco. ORD. Nº3029/044 | D117: DIRECCIÓN DEL TRABAJO | E117: Salud | F117: En consecuencia, sobre la base de las disposiciones legales citadas y consideraciones expuestas, cumplo con informar a Ud., que, en virtud de lo dispuesto en el numeral 9) del artículo 154 del Código del Trabajo | G117: 1 | H117: http://www.dt.gob.cl/legislacion/1624/w3-article-98156.html | I117: Vigente
B118: 114 | C118: NCh 1377 | D118: INSTITUTO NACIONAL DE NORMALIZACIÓN | E118: Medio Ambiente | F118: NCh Nº 1377 Of1990: Gases comprimidos - Cilindros de gas para uso industrial - Marcas para identificación del contenido y de los riesgos inherentes. | G118: 1 | H118: www.inn.cl | I118: Vigente
B119: 115 | C119: NCH 1411 | D119: INSTITUTO NACIONAL DE NORMALIZACIÓN | E119: HSEC | F119: Letreros de seguridad, señales de seguridad y tarjetas de seguridad | G119: 1 | H119: https://www.studocu.com/cl/document/instituto-profesional-aiep/prevencion-de-riesgos-y-tecnicas-preventivas/ncha-1411-norma-chilena/36999808 | I119: Vigente
B120: 116 | C120: NCH 1430 | D120: INSTITUTO NACIONAL DE NORMALIZACIÓN | E120: Seguridad | F120: Extintores portátiles- características y rotulación | G120: 1 | H120: http://tipbook.iapp.cl/ak/7ba2f4bd8e4ba3715cad4afabda5061914006c38/embed/view/nch1430 | I120: Vigente
B121: 117 | C121: NCH 1433 | D121: INSTITUTO NACIONAL DE NORMALIZACIÓN | E121: Seguridad | F121: Ubicación y señalización de los extintores portátiles | G121: 1 | H121: www.inn.cl | I121: Vigente / Modificado
... B124: 120 | C124: NCh 2.245 | D124: INSTITUTO NACIONAL DE NORMALIZACIÓN | E124: Medio Ambiente | F124: NCh 2.245 Hoja de Datos de Seguridad de Productos Químicos. | G124: 1 | H124: www.inn.cl | I124: Vigente / Modificado
B125: 121 | C125: NCh3262:2021 | D125: INSTITUTO NACIONAL DE NORMALIZACIÓN (INN) | E125: RRHH / Equidad | F125: Sistemas de gestión - Gestión de igualdad de género y conciliación de la vida laboral, familiar y personal - Requisitos | G125: N/A | H125: https://www.inn.cl/nch-aprobadas?page=35 | I125: Vigente como norma voluntaria; verificar exigencia contractual/corporativa
B126: 122 | C126: Dictamen 385/09 | D126: DIRECCIÓN DEL TRABAJO | E126: Seguridad y Salud | F126: Complementa Doctrina. Inicio de investigación acoso sexual, laboral y violencia en el trabajo ejercida por terceros ajenos a la relación laboral. | G126: 1 | H126: https://www.dt.gob.cl/legislacion/1624/w3-article-127874.html
B127: 123 | C127: Dictamen 1233 | D127: SUPERINTENDENCIA DE SEGURIDAD SOCIAL | E127: Seguridad y Salud | F127: Constitución y funcionamiento de los Comités Paritarios de Higiene y Seguridad del sector público, ante la contingencia provocada por el Coronavirus Covid 19. | G127: 1 | H127: https://www.suseso.cl/612/w3-article-587621.html | I127: Vigente
B128: 124 | C128: Dictamen 1389 | D128: DIRECCIÓN DEL TRABAJO | E128: Seguridad y Salud | F128: Trabajo a distancia y teletrabajo | G128: 1 | H128: https://www.dt.gob.cl/legislacion/1624/w3-article-118503.html | I128: Vigente
B129: 125 | C129: POLITICA SIGDO KOPPERS | D129: SIGDO KOPPERS SKIC | E129: SEGURIDAD, SALUD, MEDIO AMBIENTE Y COMUNIDAD | F129: Política de seguridad, salud ocupacional, medio ambiente y comunidad | G129: 1 | H129: N/A | I129: Vigente
B130: 126 | C130: SIGO | D130: CODELCO | E130: HSEC ADC | F130: Sistema de gestión para la seguridad, salud en el trabajo y riesgos operacionales | G130: 0.9 | H130: N/A | I130: Vigente
B131: 127 | C131: NOR.INT.DCH | D131: CODELCO | E131: SEGURIDAD | F131: Normativas Internas DHC | G131: 0.45 | H131: N/A | I131: Vigente
B132: 128 | C132: ECF - CODELCO | D132: CODELCO | E132: SEGURIDAD | F132: Estándares de Control de Fatalidad | G132: N/A | H132: N/A | I132: CADUCADO
B133: 129 | C133: EST - CODELCO | D133: CODELCO | E133: SALUD | F133: Estándares de salud en el trabajo | G133: 0.93 | H133: N/A | I133: Vigente
B134: 130 | C134: BOWTIE - CODELCO | D134: CODELCO | E134: SEGURIDAD | F134: Bowtie | G134: N/A | H134: N/A | I134: CADUCADO
B135: 131 | C135: PROTOCOLOS NACIONALES DE SALUD | D135: MINISTERIO DE SALUD | E135: SALUD | F135: PROTOCOLOS NACIONALES DE SALUD | G135: 0.96 | H135: N/A | I135: Vigente
B136: 132 | C136: Ley 21.797 | D136: MINISTERIO DE TRANSPORTES Y TELECOMUNICACIONES | E136: Seguridad / RRLL | F136: Modifica la Ley N°18.290 y otros cuerpos legales para exigir aptitudes para conducir y regular materias relacionadas | G136: 1 | H136: https://www.bcn.cl/leychile/Navegar?idNorma=1221210 | I136: Vigente / requisitos por verificar
B137: 133 | C137: Ley 21.828 | D137: MINISTERIO DEL TRABAJO Y PREVISIÓN SOCIAL | E137: RRHH / Equidad | F137: Promueve la transparencia y la adopción de medidas para la inclusión laboral de las mujeres en las empresas que indica | G137: 1 | H137: https://www.bcn.cl/leychile/navegar?idNorma=1226327 | I137: Vigente / implementación para reporte anual
B140: 134 | C140: Decreto 57 | D140: MINISTERIO DE SALUD; SUBSECRETARÍA DE SALUD PÚBLICA | E140: HSEC / Sustancias peligrosas | F140: Aprueba reglamento de clasificación, etiquetado y notificación de sustancias químicas y mezclas peligrosas | G140: 1 | H140: https://www.bcn.cl/leychile/Navegar?idNorma=1155752 | I140: Vigente / aplicabilidad y evidencia por verificar
B141: 135 | C141: Decreto 4/2026 - Convenio OIT 155 | D141: MINISTERIO DE RELACIONES EXTERIORES | E141: Seguridad y Salud | F141: Promulga el Convenio N°155 sobre Seguridad y Salud de los Trabajadores, 1981, de la OIT | G141: 1 | H141: https://www.bcn.cl/leychile/navegar?idNorma=1222695 | I141: Vigente en Chile desde 10-06-2026 / marco SST
B142: 136 | C142: Resolución Exenta 1.697 | D142: MINISTERIO DE SALUD | E142: Salud Ocupacional / Ergonomía | F142: Aprueba Protocolo de Vigilancia Ocupacional por Exposición a Factores de Riesgo de Trastornos Musculoesqueléticos V3 | G142: 1 | H142: https://www.bcn.cl/leychile/navegar?idNorma=1221732 | I142: Vigente / sustituye Res. 327 y Res. 1660
B143: 137 | C143: Ley 21.755 | D143: MINISTERIO DE HACIENDA | E143: RRLL / Jornada | F143: Modifica cuerpos legales en materia de simplificación regulatoria y promoción de la actividad económica; incluye ajustes al Código del Trabajo vinculados a la reducción de jornada | G143: 1 | H143: https://www.bcn.cl/leychile/navegar?idNorma=1214890 | I143: Vigente / verificar implementación en jornada
B144: 138 | C144: Resolución Exenta 1.117 | D144: MINISTERIO DEL TRABAJO Y PREVISIÓN SOCIAL; SUBSECRETARÍA DE PREVISIÓN SOCIAL | E144: Seguridad y Salud / Capacitación | F144: Guía Técnica para la capacitación de los trabajadores en prevención de los riesgos laborales | G144: 1 | H144: https://www.bcn.cl/leychile/navegar?idNorma=1226913 | I144: PUBLICADA / vigencia 01-11-2026 / en implementación
B145: 139 | C145: Ley 21.719 | D145: MINISTERIO SECRETARÍA GENERAL DE LA PRESIDENCIA | E145: RRHH / Datos personales | F145: Regula la protección y el tratamiento de los datos personales y crea la Agencia de Protección de Datos Personales | G145: 1 | H145: https://www.bcn.cl/leychile/Navegar/imprimir?idNorma=1209272 | I145: VIGENCIA FUTURA 01-12-2026 / en implementación
B146: 140 | C146: Ley 21.735 | D146: MINISTERIO DEL TRABAJO Y PREVISIÓN SOCIAL; SUBSECRETARÍA DE PREVISIÓN SOCIAL | E146: RRHH / Previsional | F146: Crea un nuevo sistema mixto de pensiones y un seguro social en el pilar contributivo y establece otras modificaciones | G146: 1 | H146: https://www.bcn.cl/leychile/Navegar?idNorma=1212060 | I146: Vigencia diferenciada / obligaciones 2026 por verificar
B147: 141 | C147: Decreto 40/2026 | D147: MINISTERIO DE SALUD | E147: Salud Ocupacional / Calor | F147: Modifica el DS N°594 incorporando obligaciones frente a altas temperaturas y temperaturas extremas | G147: 1 | H147: https://www.bcn.cl/leychile/navegar?idNorma=1220382&idParte=10578771 | I147: Vigente / contenido incorporado en DCTO 594
B148: 142 | C148: Ley 21.628 | D148: MINISTERIO DEL TRABAJO Y PREVISIÓN SOCIAL | E148: RRHH / Previsional | F148: Flexibiliza requisitos de acceso e incrementa prestaciones del Seguro de Desempleo de la Ley N°19.728 | G148: 1 | H148: https://www.bcn.cl/leychile/Navegar?idNorma=1197373 | I148: Vigente / obligaciones y evidencias por verificar
... B154: 148 | C154: NEO 53 | D154: CODELCO - DIVISIÓN CHUQUICAMATA | E154: Seguridad / Tránsito | F154: Reglamento de Tránsito y Transporte de Personas y Materiales en Áreas Administrativas, Plantas y Servicios | G154: 1 | H154: SGDOC / documento controlado DCH | I154: Vigente contractual / verificar revisión controlada y evidencia
B155: PROMEDIO | G155: =AVERAGE(G7:G154) -> 0.98742857
B157: ELABORÓ | E157: REVISÓ | G157: APROBÓ
B158: Claudio Rojas / Jefe Dpto. HSEC | E158: Mauricio Araya / Presidente CPHS | G158: José Maira / Administrador de Contrato
B159: FIRMA: FECHA: | E159: FIRMA: FECHA: | G159: FIRMA: FECHA:

Sheet Control de Cambios
D3: CONTROL DE CAMBIOS Lista de Verificación de Cumplimiento Requisitos Legales y Otros Aplicable a Seguridad, Salud Ocupacional, Medioambiente y Comunidad Contrato 4600029025 - SKIC CC-101 | G3: Código | H3: MTRSE-00002
G4: Revisión | H4: 2
G5: Fecha | H5: 46272
C7: Código Cuerpo Legal | D7: Organismo | E7: Nombre del Cuerpo Legal | F7: Fecha modificación | G7: Revisión | H7: Comentario
C8: Ley 21.797 | D8: MINISTERIO DE TRANSPORTES Y TELECOMUNICACIONES | E8: MODIFICA LA LEY N° 18.290 Y OTROS CUERPOS LEGALES QUE INDICA, PARA HACER EFECTIVA LA EXIGENCIA DE CONTAR CON APTITUDES PARA CONDUCIR VEHÍCULOS MOTORIZADOS Y REGULAR OTRAS MATERIAS RELACIONADAS | F8: 46065 | G8: 1 | H8: Se incluye nuevos requerimeinto legal
C9: Ley 19.300 | D9: MINISTERIO SECRETARIA GENERAL DE LA PRESIDENCIA | E9: Aprueba Ley sobre bases Generales del Medio Ambiente | F9: 43229 | G9: 3 | H9: Modificado
C10: Ley 19.419 | D10: MINISTERIO DE SALUD | E10: Regula Actividades que indica Relacionadas con el Tabaco | F10: 43229 | G10: 3 | H10: Modificado
C11: Ley 19.473 | D11: MINISTERIO DE AGRICULTURA | E11: Ley de Caza y su Reglamento aprobado por D.S. Nº 5, modificado este último por D.S. Nº 53. | F11: 43229 | G11: 3 | H11: Modificado
C12: Ley 19.518 | D12: MINISTERIO DEL TRABAJO Y PREVISION SOCIAL. | E12: Fija Nuevo Estatuto de Capacitacion y Empleo | F12: 43229 | G12: 3 | H12: Modificado
C13: Ley 20.005 | D13: MINISTERIO DEL TRABAJO Y PREVISION SOCIAL. | E13: Tipifica y Sanciona el Acoso Sexual | F13: 43229 | G13: 3 | H13: Modificado
C14: Ley 20.249 | D14: MINISTERIO DE PLANIFICACION | E14: Crea el espacio costero marino de los pueblos originarios | F14: 43229 | G14: 3 | H14: Modificado
C15: Ley 20.283 | D15: MINISTERIO DE AGRICULTURA | E15: Ley sobre recuperacion del bosque nativo y fomento forestal | F15: 43229 | G15: 3 | H15: Modificado
C16: Ley 20.609 | D16: MINISTERIO SECRETARIA GENERAL DE LA PRESIDENCIA | E16: Establece medidas contra la discriminación. | F16: 43229 | G16: 3 | H16: Modificado
C17: Ley 20.660 | D17: MINISTERIO DE SALUD | E17: Modifica Ley Nº 19.419, en Materia de Ambientes Librea de Humo de Tabaco | F17: 43229 | G17: 3 | H17: El contenido de la presente Ley se encuentra incluida en Ley 19419 MINSAL
C18: Ley 20.949 | D18: MINISTERIO DEL TRABAJO Y PREVISION SOCIAL. | E18: Modifica el código del trabajo para reducir el peso de las cargas de manipulación manual | F18: 43229 | G18: 3 | H18: Modificado
C19: Decreto con Fuerza de Ley 1 | D19: MINISTERIO DEL TRANSPORTE Y TELECOMUNICACIONES | E19: Ley de Tránsito | F19: 43229 | G19: 3 | H19: Modificado
... C140: Dictamen 1161 | D140: SUPERINTENDENCIA DE SEGURIDAD SOCIAL | E140: Cobertura del seguro de la Ley 16.744, ante la contingencia provocada por el Coronavirus Covid 19, Complementa Ord. N° 1124 de 16 de marzo de 2020, de esta Superintendencia. | F140: 43966 | G140: 6 | H140: Se incorpora y Complementa Ord. N° 1124 de 16 de marzo de 2020, de esta Superintendencia.
C141: ORD. 1086 | D141: MINISTERIO DE SALUD | E141: Envía recomendaciones de Actuación en los Lugares de Trabajo en el Contexto COVID-19 | F141: 16.05.2020 | G141: 6 | H141: Se incorpora
C142: Dictamen 1013 | D142: SUPERINTENDENCIA DE SEGURIDAD SOCIAL | E142: Infección por Coronavirus Covid 19. Situaciones a considerar en la calificación de su origen. | F142: 16.05.2020 | G142: 6 | H142: Se incorpora
C143: Dictamen 1233 | D143: SUPERINTENDENCIA DE SEGURIDAD SOCIAL | E143: Constitución y funcionamiento de los Comités Paritarios de Higiene y Seguridad del sector público, ante la contingencia provocada por el Coronavirus Covid 19. | F143: 43967 | G143: 6 | H143: Se incorpora
C144: Dictamen 1239 | D144: DIRECCIÓN DEL TRABAJO | E144: Salud y Seguridad en el Trabajo | F144: 43967 | G144: 6 | H144: Se incorpora
C145: Dictamen 1389 | D145: DIRECCIÓN DEL TRABAJO | E145: Trabajo a distancia y teletrabajo | F145: 43967 | G145: 6 | H145: Se incorpora
C146: PROTOCOLO DE LIMPIEZA Y DESINFECCIÓN DE AMBIENTES - COVID-19 | D146: MINSAL | E146: PROTOCOLO DE LIMPIEZA Y DESINFECCIÓN DE AMBIENTES - COVID-19 | F146: 43967 | G146: 6 | H146: Se incorpora
C147: PROTOCOLO DE CONTACTOS DE CASOS COVID-19 FASE 4. Ver.2 | D147: MINSAL | E147: PROTOCOLO DE CONTACTOS DE CASOS COVID-19 FASE 4. Ver.2 | F147: 43967 | G147: 6 | H147: Se incorpora
C148: DECRETO 18 | D148: MINISTERIO DEL TRABAJO Y PREVISION SOCIAL. | E148: "Aprueba Reglamento del artículo 152 Quáter M del Código del Trabajo, que establece condiciones específicas de seguridad y salud en el trabajo a que deberán sujetarse los trabajadores que prestan servicios en las modalidades de trabajo a distancia o teletrabajo, de acuerdo con los principios y condiciones de la Ley Nº 16.744" | F148: 44319 | G148: 7 | H148: Se incorpora
C149: LEY 21260 | D149: DIRECCIÓN DEL TRABAJO Y PREVISIÓN SOCIAL | E149: Modifica el código del trabajo para posibilitar el teletrabajo de la trabajadora embarazada, en caso de estado de excepción constitucional de catástrofe, por calamidad pública, con ocasión de una epidemia o pandemia a causa de una enfermedad contagiosa. | F149: 44319 | G149: 7 | H149: Se incorpora
C150: Dictamen 2639 | D150: DIRECCIÓN DEL TRABAJO Y PREVISIÓN SOCIAL | E150: Elección representantes cphs y celebración reuniones utilizando medios electrónicos, mientras dure la pandemia. | F150: 44319 | G150: 7 | H150: Se incorpora
C151: FORMULARIO ÚNICO DE FISCALIZACIÓN DE MEDIDAS PREVENTIVAS PARA EL COVID-19 EN LUGARES DE TRABAJO EN LUGARES DE TRABAJO | D151: DIRECCION DEL TRABAJO Y MINISTERIO DE SALUD | E151: FORMULARIO ÚNICO DE FISCALIZACIÓN DE MEDIDAS PREVENTIVAS PARA EL COVID-19 EN LUGARES DE TRABAJO | F151: 44319 | G151: 7 | H151: Se incorpora
C152: Compendio de Normas del Seguro Social de Accidentes del Trabajo y Enfermedades Profesionales | D152: SUSESO | E152: Compendio de Normas del Seguro Social de Accidentes del Trabajo y Enfermedades Profesionales | F152: 44319 | G152: 7 | H152: Se incorpora
C153: PROGRAMA EMPRESA COMPETITIVA PEC | D153: MUTUAL DE SEGURIDAD | E153: Programa PEC | F153: 44319 | G153: 7 | H153: Se incorpora
C154: Resolución N° 2358 exenta | D154: Instituto de Salud Pública | E154: Aprueba el documento nota técnica denominada “Recomendaciones sobre prevención de COVID-19 en lugares de trabajo insertos en edificios modernos”. | F154: 44560 | G154: 8 | H154: Se incorpora
... C190: NEO 53 | D190: CODELCO - DIVISIÓN CHUQUICAMATA | E190: REGLAMENTO DE TRÁNSITO Y TRANSPORTE DE PERSONAS Y MATERIALES EN ÁREAS ADMINISTRATIVAS, PLANTAS Y SERVICIOS | F190: 46288 | G190: 2 | H190: Se individualiza en Planilla Global, se crea hoja propia y se corrige su registro en NOR.INTER.DCH. Verificar revisión controlada SGDOC.

Sheet Ley 16.744
D1: Lista de Verificación de Cumplimiento Requisitos Legales y Otros Aplicable a Seguridad, Salud Ocupacional, Medioambiente y Comunidad Contrato 4600029025 - SKIC CC-101 | M1: Código | N1: ='Planilla Global - Cumplim (%)'!I2 -> MTRSE-00002
M2: Revisión | N2: 2
M3: Fecha | N3: 46272
A5: Nº Cuerpo Legal | B5: Fecha de Publicación | C5: Organismo | D5: Nombre del Cuerpo Legal | E5: Artículo | F5: Descripción del Contenido (Breve) | G5: Peligro o Aspecto | H5: Nº Contrato | I5: Modo de Cumplimiento | J5: ¿Cumple? | K5: % Cumplimiento | L5: Evidencia del Cumplimiento | M5: Responsable | N5: Fecha de cumplimiento
A6: LEY 16.744 | B6: 24869 | C6: MINISTERIO DEL TRABAJO Y PREVISION SOCIAL | D6: ESTABLECE NORMAS SOBRE ACCIDENTES DEL TRABAJO Y ENFERMEDADES PROFESIONALES | E6: Art. 1 | F6: Declárase obligatorio el Seguro Social contra Riesgos de Accidentes del Trabajo y Enfermedades Profesionales, en la forma y condiciones establecidas en la presente ley. | G6: No estar afiliado a algún organismo Administrador Contrato del seguro | H6: 4600029025 CC-101 | I6: Afiliación a organismo Administrador ley | J6: SI | K6: 1 | L6: Certificado de afiliación Mutual de Seguridad | M6: Administrador de Contrato
E7: Art.4 | F7: Para los efectos de este seguro, todos los empleadores se entenderán afiliados al Instituto de Seguridad Laboral respecto de la totalidad de sus trabajadores, salvo que se adhieran a alguna mutualidad de empleadores. Lo dispuesto en el inciso anterior también se aplicará a los trabajadores independientes afectos al seguro de esta ley. | G7: No estar afiliado a algún organismo Administrador Contrato del seguro | I7: Pago del seguro | J7: SI | K7: 1 | L7: Planilla firmada por el OAL | M7: Administrador de Contrato
E8: Art.5 | F8: Para los efectos de esta ley se entiende por accidente del trabajo toda lesión que una persona sufra a causa o con ocasión del trabajo, y que le produzca incapacidad o muerte. Son también accidentes del trabajo los ocurridos en el trayecto directo, de ida o regreso, entre la habitación y el lugar del trabajo, y aquéllos que ocurran en el trayecto directo entre dos lugares de trabajo, aunque correspondan a distintos empleadores. En este último caso, se considerará que el accidente dice relación con el trabajo al que se dirigía el trabajador al ocurrir el siniestro. Se considerarán también accidentes del trabajo los sufridos por dirigentes de instituciones sindicales a causa o con ocasión del desempeño de sus cometidos gremiales. Exceptuándose los accidentes debidos a fuerza mayor extraña que no tenga relación alguna con el trabajo y los producidos intencionalmente por la víctima. La prueba de las excepciones corresponderá al organismo administrador. | G8: No enviar al accidentado al OAL | H8: 4600029025 CC-101 | I8: Realización de DIAT empresa | J8: SI | K8: 1 | L8: DIAT Empresa presentada en Organismo Administrador Contrato LEY o subida al sistema | M8: Administrador de Contrato
E9: Art.7 | F9: Es enfermedad profesional la causada de una manera directa por el ejercicio de la profesión o el trabajo que realice una persona y que le produzca incapacidad o muerte | G9: No realizar evaluación cualitativa con el OAL | H9: 4600029025 CC-101 | I9: Programa de Salud Ocupacional | J9: SI | K9: 1 | L9: Mantener vigente al Grupo de exposición similar | M9: Administrador de Contrato
E10: Art.15 | F10: El seguro de Accidentes del Trabajo y Enfermedades Profesionales se financiará con los siguientes recursos: a) Con una cotización básica general del 0,90% de las remuneraciones imponibles, de cargo del empleador; b) Con una cotización adicional diferenciada en función de la actividad y riesgo de la empresa o entidad empleadora, la que será determinada por el Presidente de la República y no podrá exceder de un 3,4% de las remuneraciones imponibles, que también será de cargo del empleador, y que se fijará sin perjuicio de los dispuesto en el artículo 16 c) Con el producto de las multas que cada organismo Administrador Contrato aplique en conformidad a la presente ley; d) Con las utilidades o rentas que produzca la inversión de los fondos de reserva, y e) Con las cantidades que les corresponda por el ejercicio del derecho de repetir de acuerdo con los artículos 56 y 69. | G10: No realizar pago de cotización básica | H10: 4600029025 CC-101 | I10: Pago de 0,95% de la planilla total de trabajadores + Cotización adicional | J10: SI | K10: 1 | L10: Pagos de Mutualidad | M10: Administrador de Contrato
A11: LEY 16.744 | B11: 24869 | C11: MINISTERIO DEL TRABAJO Y PREVISION SOCIAL | D11: ESTABLECE NORMAS SOBRE ACCIDENTES DEL TRABAJO Y ENFERMEDADES PROFESIONALES | E11: Art.16 | F11: Artículo 16º Las empresas o entidades que implanten o hayan implantado medidas de prevención que rebajen apreciablemente los riesgos de accidentes del trabajo o de enfermedades profesionales, podrán solicitar que se les reduzca la tasa de cotización adicional o que se les exima de ella si alcanzan un nivel óptimo de seguridad. Las empresas o entidades que no ofrezcan condiciones satisfactorias de seguridad y/o higiene, o que no implanten las medidas de seguridad que el organismo competente les ordene, deberán cancelar la cotización adicional con recargo de hasta el 100% sin perjuicio de las demás sanciones que les correspondan. | G11: No realizar actividades de Prevención de Riesgos. | H11: 4600029025 CC-101 | I11: Se cuenta con un Departamento de Prevención de Riesgos y con Programas Personalizados para la línea de Mando | J11: SI | K11: 1 | L11: Informes de Gestión HSEC | M11: Administrador de Contrato
E12: Art.66 | F12: En toda industria o faena en que trabajen más de 25 personas deberán funcionar uno o más Comités Paritarios de Higiene y Seguridad, que tendrán las siguientes funciones: 1.- Asesorar e instruir a los trabajadores para la correcta utilización de los instrumentos de protección; 2.- Vigilar el cumplimiento, tanto por parte de las empresas como de los trabajadores, de las medidas de prevención, higiene y seguridad. 3.- Investigar las causas de los accidentes del trabajo y enfermedades profesionales, que se produzcan en la empresa y de cualquiera otra afección que afecte en forma reiterada o general a los trabajadores y sea presumible que tenga su origen en la utilización de productos fitosanitarios, químicos o nocivos para la salud; 4.- Indicar la adopción de todas las medidas de higiene y seguridad, que sirvan para la prevención de los riesgos profesionales; 5.- Cumplir las demás funciones o misiones que le encomiende el organismo Administrador Contrato respectivo. | G12: No constituir Comité Paritario de Higiene y Seguridad | H12: 4600029025 CC-101 | I12: Constitución y funcionamiento de Comité Paritario | J12: SI | K12: 1 | L12: Acta de constitución de Comité Paritario Registro de reuniones mensuales C.P.H.S. Programa de Trabajo | M12: Administrador de Contrato
E13: Art.66 | F13: En aquellas empresas mineras, industriales o comerciales que ocupen a más de 100 trabajadores será obligatoria la existencia de un Departamento de Prevención de Riesgos Profesionales, el que será dirigido por un experto en prevención, en el cual formará parte. | G13: No conformar departamento de prevención de riesgos | H13: 4600029025 CC-101 | I13: Contratación profesional calificado | J13: SI | K13: 1 | L13: Contrato de trabajo del profesional | M13: Administrador de Contrato
E14: Art.66 BIS | F14: Los empleadores que contraten o subcontraten con otros la realización de una obra, faena o servicios propios de su giro, deberán vigilar el cumplimiento por parte de dichos contratistas o subcontratistas de la normativa relativa a higiene y seguridad, debiendo para ello implementar un sistema de gestión de la seguridad y salud en el trabajo para todos los trabajadores involucrados, cualquiera que sea su dependencia, cuando en su conjunto agrupen a más de 50 trabajadores. | G14: No incluir al personal subcontratista en el Programa personalizado | H14: 4600029025 CC-101 | I14: Entrega de programa personalizado | J14: N/A | K14: N/A | L14: Registro entrega de programa personalizado Registro de cumplimiento de programa | M14: Administrador de Contrato
E15: Art.67 | F15: Las empresas o entidades estarán obligadas a mantener al día los reglamentos internos de higiene y seguridad en el trabajo y los trabajadores a cumplir con las exigencias que dichos reglamentos les impongan. Los reglamentos deberán consultar la aplicación de multas a los trabajadores que no utilicen los elementos de protección personal que se les haya proporcionado o que no cumplan las obligaciones que les impongan las normas, reglamentaciones o instrucciones sobre higiene y seguridad en el trabajo. La aplicación de tales multas se regirá por lo dispuesto en el Párrafo I del Título III del Libro I del Código del Trabajo. | G15: No contar con RIOHS | H15: 4600029025 CC-101 | I15: Mantener vigente RIOHS | J15: SI | K15: 1 | L15: Cartas de presentación en DT y Seremi Salud | M15: Administrador de Contrato
A16: LEY 16.744 | B16: 24869 | C16: MINISTERIO DEL TRABAJO Y PREVISION SOCIAL | D16: ESTABLECE NORMAS SOBRE ACCIDENTES DEL TRABAJO Y ENFERMEDADES PROFESIONALES | E16: Art.68 | F16: Las empresas o entidades deberán implantar todas las medidas de higiene y seguridad en el trabajo que les prescriban directamente el Servicio Nacional de Salud o, en su caso, el respectivo organismo Administrador Contrato a que se encuentren afectas, el que deberá indicarlas de acuerdo con las normas y reglamentaciones vigentes. | G16: No cumplir con la medidas indicadas por el Servicio Nacional de Salud | H16: 4600029025 CC-101 | I16: Cierre de informe emitido por el SNS | J16: SI | K16: 1 | L16: Informe de cierre timbrado por el SNS | M16: Administrador de Contrato
E17: Art.71 | F17: Los afiliados afectados de alguna enfermedad profesional deberán ser trasladados, por la empresa donde presten sus servicios, a otras faenas donde no estén expuestos al agente causante de la enfermedad. Los trabajadores que sean citados para exámenes de control por los servicios médicos de los organismos administradores, deberán ser autorizados por su empleador para su asistencia, y el tiempo que en ello utilicen será considerado como trabajado para todos los efectos legales. Las empresas que exploten faenas en que trabajadores suyos puedan estar expuestos al riesgo de neumoconiosis, deberán realizar un control radiográfico semestral de tales trabajadores. | G17: No implantar las medidas de higiene y seguridad que prescriba el organismo administrador No proporcionar gratuitamente los Equipos de Protección Personal adecuados a los trabajadores | H17: 4600029025 CC-101 | I17: Informe de mutualidad respecto a las medidas a implantar Entrega de Equipos de protección personal en forma gratuita a trabajadores | J17: SI | K17: 1 | L17: Cuando corresponda Registro de entrega de Equipos de Protección Personal a trabajadores | M17: Administrador de Contrato
E18: Art.76 | F18: La entidad empleadora deberá denunciar al organismo Administrador Contrato respectivo, inmediatamente de producido, todo accidente o enfermedad que pueda ocasionar incapacidad para el trabajo o la muerte de la víctima. El accidentado o enfermo, o sus derecho-habientes, o el médico que trató o diagnosticó la lesión o enfermedad, como igualmente el Comité Paritario de Seguridad, tendrán también, la obligación de denunciar el hecho en dicho organismo administrador, en el caso de que la entidad empleadora no hubiere realizado la denuncia. Las denuncias mencionadas en el inciso anterior deberán contener todos los datos que hayan sido indicados por el Servicio Nacional de Salud. | G18: No controlar los peligros adecuadamente | H18: 4600029025 CC-101 | I18: Responsabilidad establecida en Investigación de Incidentes | J18: SI | K18: 1 | L18: Registros de Investigación de Incidentes (Cuando Corresponda) | M18: Administrador de Contrato
K19: 1
C20: ELABORÓ | F20: REVISÓ | G20: APROBÓ
C21: Claudio Rojas / Jefe Dpto. HSEC | F21: Mauricio Araya / Presidente CPHS | G21: José Maira / Administrador de Contrato
C22: FIRMA: FECHA : 18-02-2026 | F22: FIRMA: FECHA : 18-02-2026 | G22: FIRMA: FECHA : 18-02-2026

Sheet Ley 18.290
D1: Lista de Verificación de Cumplimiento Requisitos Legales y Otros Aplicable a Seguridad, Salud Ocupacional, Medioambiente y Comunidad Contrato 4600029025 - SKIC CC-101 | M1: Código | N1: ='Planilla Global - Cumplim (%)'!I2 -> MTRSE-00002
M2: Revisión | N2: 2
M3: Fecha | N3: 46272
A5: Nº Cuerpo Legal | B5: Fecha de Publicación | C5: Organismo | D5: Nombre del Cuerpo Legal | E5: Artículo | F5: Descripción del Contenido (Breve) | G5: Peligro o Aspecto | H5: Nº Contrato | I5: Modo de Cumplimiento | J5: ¿Cumple? | K5: Porcentaje Cumplimiento | L5: Evidencia del Cumplimiento | M5: Responsable | N5: Fecha de cumplimiento
A6: Ley 18.290 | B6: 30719 | C6: MINISTERIO DE JUSTICIA | D6: LEY DEL TRANSITO | E6: Art.5 | F6: Ninguna persona podrá conducir un vehículo motorizado o a tracción animal, sin poseer una licencia expedida por el Director del Departamento del Tránsito y Transporte Público Municipal de una Municipalidad autorizada al efecto; o un permiso provisional que los Tribunales podrán otorgar sólo a los conductores que tengan su licencia retenida por proceso pendiente; o una boleta de citación al Juzgado, dada por los funcionarios a que se refiere el artículo 4º en reemplazo de la licencia o del permiso referido; o algún documento extendido en el extranjero y con validez en Chile en virtud de tratados o acuerdos internacionales. Los documentos antes indicados otorgados en el país, son instrumentos públicos. Se exceptúa de la exigencia establecida en el inciso primero de este artículo a los alumnos en práctica de las escuelas de conductores que, acompañados de un instructor habilitado, lo hagan en vehículos de la escuela. | G6: Conducir, operar vehículos y/o maquinarias sin autorización por organismo competente | H6: 4600029025 CC-101 | I6: Listado actualizado de Conductores | J6: SI | K6: 1 | L6: Registro de conductores que indique tipo licencia y fecha de vencimientos | M6: Jefe Equipos/ Base Deysu
E7: Art.6 | F7: Los conductores de vehículos motorizados o a tracción animal, salvo la excepción del artículo anterior, deberán llevar consigo su licencia, permiso o boleta de citación y, requeridos por la autoridad competente, acreditar su identidad y entregar los documentos que los habilitan para conducir. Asimismo, tratándose de vehículos motorizados, deberán portar y entregar el certificado vigente de póliza de un seguro obligatorio de accidentes, el que deberá ser devuelto, siempre y en el acto, al conductor. | G7: Conducir, operar vehículos y/o maquinarias sin el documento que acredite la autorización mas documentación del vehículo o maquinaria. | H7: 4600029025 CC-101 | I7: Listado actualizado de Conductores | J7: SI | K7: 1 | L7: carpeta de documentación del vehículo con todos los documentos vigentes | M7: Jefe Equipos/ Base Deysu
E8: Art.7 | F8: Se prohíbe al propietario o encargado de un vehículo facilitarlo a una persona que no posea licencia para conducirlo. Si se sorprendiere conduciendo un vehículo a quien no porte los documentos a que se refiere el artículo anterior. | G8: Conducir, operar vehículos y/o maquinarias sin el documento que acredite la autorización | H8: 4600029025 CC-101 | I8: Listado de personas autorizadas | J8: SI | K8: 1 | L8: carta compromiso conducir firmada | M8: Jefe Equipos/ Base Deysu
A9: Ley 18.290 | B9: 30719 | C9: MINISTERIO DE JUSTICIA | D9: LEY DEL TRANSITO | E9: Art.12 | F9: Existirán licencias de conductor profesionales, Clase A; no profesionales, Clase B y C; y especiales, Clase D, E y F. | G9: Conducir, operar vehículos y/o maquinarias sin el documento que acredite la autorización | H9: 4600029025 CC-101 | I9: Listado de personas autorizadas | J9: SI | K9: 1 | L9: carta compromiso conducir firmada | M9: Jefe Equipos/ Base Deysu
E10: Art.60 | F10: No se podrá transportar materias peligrosas en vehículos de alquiler ni en los destinados al transporte colectivo de personas | G10: Transportar sustancias peligrosas en vehículos de transporte de personas | H10: 4600029025 CC-101 | I10: Charla ODI medioambiente | J10: SI | K10: 1 | L10: Charla ODI medioambiente firmada | M10: Jefe Equipos/ Base Deysu
E11: Art.63 | F11: Los vehículos motorizados deberán estar equipados con neumáticos en buen estado. No podrán circular aquellos cuyos neumáticos tengan sus bandas de rodadura desgastadas o hayan perdido sus condiciones de adherencia al pavimento, ni con repara | G11: Circular en vehículo con neumáticos desgastados o en malas condiciones | H11: 4600029025 CC-101 | I11: Lista de chequeo diario de vehículos | J11: SI | K11: 1 | L11: Registro de listas de chequeo | M11: Jefe Equipos/ Base Deysu
E12: Art.101 | F12: Los conductores y los peatones están obligados a obedecer y respetar las señales del tránsito, salvo que reciban instrucciones en contrario de un carabinero o que se trate de las excepciones contempladas en esta ley para vehículos de emerge | G12: No respetar señalización de transito | H12: 4600029025 CC-101 | I12: Realización de Curso de manejo defensivo a conductores online o presencial | J12: SI | K12: 1 | L12: Certificado aprobación curso manejo defensivo | M12: Jefe Equipos/ Base Deysu
E13: Art.148 | F13: Ninguna persona podrá conducir un vehículo a una velocidad mayor de la que sea razonable y prudente, bajo las condiciones existentes, debiendo considerar los riesgos y peligros presentes y los posibles. | G13: Conducir vehículo a velocidad inadecuada | H13: 4600029025 CC-101 | I13: Control GPS | J13: SI | K13: 1 | L13: Reporte semanal GPS | M13: Jefe Equipos/ Base Deysu
K14: 1
C15: ELABORÓ | F15: REVISÓ | G15: APROBÓ
C16: Claudio Rojas / Jefe Dpto. HSEC | F16: Mauricio Araya / Presidente CPHS | G16: José Maira / Administrador de Contrato
C17: FIRMA: FECHA : 18-02-2026 | F17: FIRMA: FECHA : 18-02-2026 | G17: FIRMA: FECHA : 18-02-2026

Sheet Ley 19.303
D1: Lista de Verificación de Cumplimiento Requisitos Legales y Otros Aplicable a Seguridad, Salud Ocupacional, Medioambiente y Comunidad Contrato 4600029025 - SKIC CC-101 | M1: Código | N1: ='Planilla Global - Cumplim (%)'!I2 -> MTRSE-00002
M2: Revisión | N2: 2
M3: Fecha | N3: 46272
A5: Nº Cuerpo Legal | B5: Fecha de Publicación | C5: Organismo | D5: Nombre del Cuerpo Legal | E5: Artículo | F5: Descripción del Contenido (Breve) | G5: Peligro o Aspecto | H5: Nº Contrato | I5: Modo de Cumplimiento | J5: ¿Cumple? | K5: Porcentaje Cumplimiento | L5: Evidencia del Cumplimiento | M5: Responsable | N5: Fecha de cumplimiento
A6: Ley 19303 | B6: 34437 | C6: MINISTERIO DEL INTERIOR | D6: ESTABLECE OBLIGACIONES A ENTIDADES QUE INDICA, EN MATERIA DE SEGURIDAD DE LAS PERSONAS | E6: Art. 14 | F6: Los daños físicos o síquicos que sufran los trabajadores de las empresas, entidades o establecimientos que sean objeto de robo, asalto u otra forma de violencia delictual, a causa o con ocasión del trabajo, son accidentes del trabajo, sujetos a las normas de la ley N° 16.744. | G6: ROBO/ASALTO | H6: 4600029025 CC-101 | I6: Emisión de DIAT | J6: SI | K6: 1 | L6: DIAT timbrada o subida al sistema del OAL | M6: Administrador de Contrato
K7: 1
C8: ELABORÓ | F8: REVISÓ | G8: APROBÓ
C9: Claudio Rojas / Jefe Dpto. HSEC | F9: Mauricio Araya / Presidente CPHS | G9: José Maira / Administrador de Contrato
C10: FIRMA: FECHA : 18-02-2026 | F10: FIRMA: FECHA : 18-02-2026 | G10: FIRMA: FECHA : 18-02-2026

Sheet LEY 19.404
D1: Lista de Verificación de Cumplimiento Requisitos Legales y Otros Aplicable a Seguridad, Salud Ocupacional, Medioambiente y Comunidad Contrato 4600029025 - SKIC CC-101 | M1: Código | N1: ='Planilla Global - Cumplim (%)'!I2 -> MTRSE-00002
M2: Revisión | N2: 2
M3: Fecha | N3: 46272
A5: Nº Cuerpo Legal | B5: Fecha de Publicación | C5: Organismo | D5: Nombre del Cuerpo Legal | E5: Artículo | F5: Descripción del Contenido (Breve) | G5: Peligro o Aspecto | H5: Nº Contrato | I5: Modo de Cumplimiento | J5: ¿Cumple? | K5: Porcentaje Cumplimiento | L5: Evidencia del Cumplimiento | M5: Responsable | N5: Fecha de cumplimiento
A6: Ley 19.404 | B6: 34932 | C6: MINISTERIO DE SALUD | D6: Introduce modificación al Decreto Ley Nº 3.500, de 1980, Texto Original del 01-03-2009 y dicta normas relativas a pensiones de vejez, considerando el desempeño de trabajos pesados. | E6: Art.1 | F6: Se entenderá que constituyen trabajos pesados aquellos cuya realización acelera el desgaste físico, intelectual o psíquico en la mayoría de quienes lo realizan, provocando un envejecimiento precoz, aun cuando ellos no generen una enfermedad laboral. | G6: No identificar los puestos de trabajo | H6: 4600029025 CC-101 | I6: Realizar Evaluación del puesto de trabajo por la comisión Ergonómica | J6: NO | K6: 0 | L6: Informe ergonómico OAL y presentar a la SEREMI de la región que corresponda Enviar informe a RRHH | M6: Administrador de contrato RRLL | P6: https://www.bcn.cl/leychile/navegar?idNorma=30771
E7: Art.2 | F7: Para los efectos de calificar como trabajo pesado una labor, que se ejecuta en uno o más puestos de trabajo de una determinada entidad empleadora, las Comisiones a que se refiere el presente Reglamento, deberán establecer un instrumento guía de conocimiento público, uso obligatorio y revisión permanente, considerando a lo menos, y con independencia de las características individuales de quien la realiza, los siguientes factores: a) Factor físico: constituido por las exigencias del puesto de trabajo que demandan un esfuerzo adaptativo fisiológico, reflejado en mayor gasto energético y con modificaciones del metabolismo. b) Factor ambiental: que corresponde a la presencia, en los puestos de trabajo, de agentes ambientales que pueden afectar negativamente la salud de los trabajadores, su bienestar y su equilibrio fisiológico. c) Factor mental: es la exigencia del puesto de trabajo que demanda esfuerzos adaptativos del sistema nervioso y de la estructura psicoafectiva del trabajador. d) Factor organizacional: son las exigencias del puesto de trabajo derivadas de la organización y diseño de la labor y su entorno psicosocial. Para los efectos de lo dispuesto en la Ley Nº 19.404 y en el presente Reglamento, se entiende por puesto de trabajo el conjunto de tareas, deberes y responsabilidades que, en el marco de las condiciones de trabajo definidas por la empresa, constituyen la labor regular de una persona y que pueden ser descritas con prescindencia del trabajador que lo ocupa. | G7: No identificar los puestos de trabajo | H7: 4600029025 CC-101 | I7: Realizar Evaluación del puesto de trabajo por la comisión Ergonómica | J7: NO | K7: 0 | L7: Informe ergonómico OAL y presentar a la SEREMI de la región que corresponda Enviar informe a RRHH | M7: Administrador de contrato
E8: Art.3 | F8: La definición de trabajo pesado y los factores de carga global de trabajo señalados en los artículos anteriores, serán aplicados y ponderados, en su totalidad, por la Comisión Ergonómica Nacional para la calificación por puesto de trabajo de las labores desarrolladas por los afiliados al Sistema de Pensiones del D. L. Nº 3.500, de 1980, y por los imponentes de los regímenes previsionales administrados por el Instituto de Normalización Previsional a que se refieren los artículos 1º y 2º de la Ley Nº 19.404.6 7 El menor desgaste relativo producido por un trabajo calificado como pesado, será determinado según la ponderación asignada a cada uno de los factores señalados en el artículo anterior, conforme lo establecido en el instrumento guía a que se refiere el artículo 2º de este Reglamento. | G8: No identificar los puestos de trabajo | H8: 4600029025 CC-101 | I8: Realizar Evaluación del puesto de trabajo por la comisión Ergonómica | J8: NO | K8: 0 | L8: Informe ergonómico OAL y presentar a la SEREMI de la región que corresponda Enviar informe a RRHH | M8: Administrador de contrato
K9: 0
C10: ELABORÓ | F10: REVISÓ | G10: APROBÓ
C11: Claudio Rojas / Jefe Dpto. HSEC | F11: Mauricio Araya / Presidente CPHS | G11: José Maira / Administrador de Contrato
C12: FIRMA: FECHA : 18-02-2026 | F12: FIRMA: FECHA : 18-02-2026 | G12: FIRMA: FECHA : 18-02-2026

Sheet Ley 19.419
D1: Lista de Verificación de Cumplimiento Requisitos Legales y Otros Aplicable a Seguridad, Salud Ocupacional, Medioambiente y Comunidad Contrato 4600029025 - SKIC CC-101 | M1: Código | N1: ='Planilla Global - Cumplim (%)'!I2 -> MTRSE-00002
M2: Revisión | N2: 2
M3: Fecha | N3: 46272
A5: Nº Cuerpo Legal | B5: Fecha de Publicación | C5: Organismo | D5: Nombre del Cuerpo Legal | E5: Artículo | F5: Descripción del Contenido (Breve) | G5: Peligro o Aspecto | H5: Nº Contrato | I5: Modo de Cumplimiento | J5: ¿Cumple? | K5: Porcentaje Cumplimiento | L5: Evidencia del Cumplimiento | M5: Responsable | N5: Fecha de cumplimiento
A6: Ley 19.419 | B6: 34981 | C6: MINISTERIO DE SALUD | D6: Regula Actividades que indica Relacionadas con el Tabaco | E6: Art.11 | F6: Se prohíbe fumar en los siguientes lugares, salvo en sus patios o espacios al aire libre: a) al interior de los recintos o dependencias de los órganos del Estado. Sin embargo, en las oficinas individuales se podrá fumar sólo en el caso que cuenten con ventilación hacia el aire libre o extracción del aire hacia el exterior; b) establecimientos de educación superior, públicos y privados; c) establecimientos de salud, públicos y privados; d) aeropuertos y terrapuertos; e) teatros, cines, lugares en que se presenten espectáculos culturales y musicales, salvo que sean al aire libre; f) gimnasios y recintos deportivos; g) centros de atención o de prestación de servicios abiertos al público en general; h) supermercados, centros comerciales y demás establecimientos similares de libre acceso al público. En los lugares anteriormente enumerados, podrá existir una o más salas especialmente habilitadas para fumar, con excepción de los casos que señala la letra c). Sin perjuicio de lo dispuesto en el artículo siguiente, iguales reglas se aplicarán tratándose de empresas, establecimientos, faenas o unidades económicas obligadas a confeccionar un reglamento interno de orden, higiene y seguridad, en conformidad a las normas del Código del Trabajo. En los lugares de trabajo de propiedad de particulares no comprendidos en el artículo 10 y en los incisos precedentes, la existencia de prohibición de fumar o la determinación de sitios y condiciones en que ello se autorizará serán acordadas por los respectivos propietarios o administradores, oyendo el parecer de los empleados. | G6: Contaminación del Ambiente / Incendios | H6: 4600029025 CC-101 | I6: Prohibición de fumar en Áreas de Trabajo indicado en el RIOHS | J6: SI | K6: 1 | L6: registro de entrega de RIOHS, Definición de Zonas para Fumadores. | M6: Administrador de Contrato - HSEC
K7: 1
C8: ELABORÓ | F8: REVISÓ | G8: APROBÓ
C9: Claudio Rojas / Jefe Dpto. HSEC | F9: Mauricio Araya / Presidente CPHS | G9: José Maira / Administrador de Contrato
C10: FIRMA: FECHA : 18-02-2026 | F10: FIRMA: FECHA : 18-02-2026 | G10: FIRMA: FECHA : 18-02-2026

Sheet LEY 19.518
D1: Lista de Verificación de Cumplimiento Requisitos Legales y Otros Aplicable a Seguridad, Salud Ocupacional, Medioambiente y Comunidad Contrato 4600029025 - SKIC CC-101 | M1: Código | N1: ='Planilla Global - Cumplim (%)'!I2 -> MTRSE-00002
M2: Revisión | N2: 2
M3: Fecha | N3: 46272
A5: Nº Cuerpo Legal | B5: Fecha de Publicación | C5: Organismo | D5: Nombre del Cuerpo Legal | E5: Artículo | F5: Descripción del Contenido (Breve) | G5: Peligro o Aspecto | H5: Nº Contrato | I5: Modo de Cumplimiento | J5: ¿Cumple? | K5: Porcentaje Cumplimiento | L5: Evidencia del Cumplimiento | M5: Responsable | N5: Fecha de cumplimiento
A6: Ley 19.518 | B6: 35717 | C6: MINISTERIO DEL TRABAJO Y PREVISIÓN | D6: FIJA NUEVO ESTATUTO DE CAPACITACION Y EMPLEO | E6: Art.13 | F6: Las empresas podrán constituir un comité bipartito de capacitación. Ello será obligatorio en aquellas empresas cuya dotación de personal sea igual o superior a 15 trabajadores. Las funciones del comité serán acordar y evaluar el o los programas de capacitación ocupacional de la empresa, así como asesorar a la dirección de la misma en materias de capacitación. | G6: No contar con Comité Bipartito | H6: 4600029025 CC-101 | I6: Conformar Comité Bipartito | J6: NO | K6: 0 | L6: Acta de conformación de comité Bipartito | M6: Administrador de Contrato- RRHH | N6: 46142 | P6: https://www.bcn.cl/leychile/navegar?idNorma=76201
E7: Art. 14 | F7: Los programas acordados con el comité bipartito de la empresa, darán derecho a las empresas a acceder al beneficio adicional establecido en el artículo 39 de esta ley. | G7: No contar con Comité Bipartito | H7: 4600029025 CC-101 | I7: Conformar Comité Bipartito | J7: NO | K7: 0 | L7: Programa de Capacitación | M7: Administrador de Contrato- RRHH | N7: 46142
E8: Art.15 | F8: El programa de capacitación contendrá a lo menos las siguientes menciones: a) las áreas de la empresa para las cuales se desarrollarán actividades de capacitación, y el objetivo de dichas actividades; b) el número y características de los trabajadores que participarán en las actividades de capacitación, y c) la época del año en que se ejecutarán las referidas acciones. | G8: No contar con Comité Bipartito | H8: 4600029025 CC-101 | I8: Conformar Comité Bipartito | J8: NO | K8: 0 | L8: Programa de Capacitación | M8: Administrador de Contrato- RRHH | N8: 46142
E9: Art.16 | F9: El comité bipartito estará constituido por tres representantes del empleador y tres de los trabajadores. El comité se reunirá a requerimiento de a lo menos cuatro de sus integrantes. El comité adoptará sus decisiones con el acuerdo de la mayoría de los representantes de ambos estamentos, y se formalizarán para los efectos del artículo 14 de esta ley en un programa de capacitación. | G9: No contar con Comité Bipartito | H9: 4600029025 CC-101 | I9: Conformar Comité Bipartito | J9: NO | K9: 0 | L9: Acta de conformación de comité Bipartito | M9: Administrador de Contrato- RRHH | N9: 46142
K10: 0
C11: ELABORÓ | F11: REVISÓ | G11: APROBÓ
C12: Claudio Rojas / Jefe Dpto. HSEC | F12: Mauricio Araya / Presidente CPHS | G12: José Maira / Administrador de Contrato
C13: FIRMA: FECHA : 18-02-2026 | F13: FIRMA: FECHA : 18-02-2026 | G13: FIRMA: FECHA : 18-02-2026

Sheet Ley 19.628
D1: Lista de Verificación de Cumplimiento Requisitos Legales y Otros Aplicable a Seguridad, Salud Ocupacional, Medioambiente y Comunidad Contrato 4600029025 - SKIC CC-101 | M1: Código | N1: ='Planilla Global - Cumplim (%)'!I2 -> MTRSE-00002
M2: Revisión | N2: 2
M3: Fecha | N3: 46272
A5: Nº Cuerpo Legal | B5: Fecha de Publicación | C5: Organismo | D5: Nombre del Cuerpo Legal | E5: Artículo | F5: Descripción del Contenido (Breve) | G5: Peligro o Aspecto | H5: Nº Contrato | I5: Modo de Cumplimiento | J5: ¿Cumple? | K5: Porcentaje Cumplimiento | L5: Evidencia del Cumplimiento | M5: Responsable | N5: Fecha de cumplimiento
A6: Ley 19.628 | B6: 36400 | C6: MINISTERIO SECRETARÍA GENERAL DE LA PRESIDENCIA | D6: SOBRE PROTECCION DE LA VIDA PRIVADA | E6: Art.4 | F6: El tratamiento de los datos personales sólo puede efectuarse cuando esta ley u otras disposiciones legales lo autoricen o el titular consienta expresamente en ello. La persona que autoriza debe ser debidamente informada respecto del propósito del almacenamiento de sus datos personales y su posible comunicación al público. La autorización debe constar por escrito. La autorización puede ser revocada, aunque sin efecto retroactivo, lo que también deberá hacerse por escrito. No requiere autorización el tratamiento de datos personales que provengan o que se recolecten de fuentes accesibles al público, cuando sean de carácter económico, financiero, bancario o comercial, se contengan en listados relativos a una categoría de personas que se limiten a indicar antecedentes tales como la pertenencia del individuo a ese grupo, su profesión o actividad, sus títulos educativos, dirección o fecha de nacimiento, o sean necesarios para comunicaciones comerciales de respuesta directa o comercialización o venta directa de bienes o servicios. Tampoco requerirá de esta autorización el tratamiento de datos personales que realicen personas jurídicas privadas para el uso exclusivo suyo, de sus asociados y de las entidades a que están afiliadas, con fines estadísticos, de tarificación u otros de beneficio general de aquéllos. | G6: Mal manejo de información | H6: 4600029025 CC-101 | I6: Incorporado en RIOHS/ Ficha Personal | J6: SI | K6: 1 | L6: Incorporado en RIOHS/Ficha Personal | M6: Administrador de Contrato - RRLL
E7: Art.6 | F7: Los datos personales deberán ser eliminados o cancelados cuando su almacenamiento carezca de fundamento legal o cuando hayan caducado. Han de ser modificados cuando sean erróneos, inexactos, equívocos o incompletos. Se bloquearán los datos personales cuya exactitud no pueda ser establecida o cuya vigencia sea dudosa y respecto de los cuales no corresponda la cancelación. El responsable del banco de datos personales procederá a la eliminación, modificación o bloqueo de los datos, en su caso, sin necesidad de requerimiento del titular. | G7: Mal manejo de información | H7: 4600029025 CC-101 | I7: Tratamiento de documentos obsoletos | J7: SI | K7: 1 | L7: Tratamiento de documentos obsoletos | M7: Administrador de Contrato
E8: Art.7 | F8: Las personas que trabajan en el tratamiento de datos personales, tanto en organismos públicos como privados, están obligadas a guardar secreto sobre los mismos, cuando provengan o hayan sido recolectados de fuentes no accesibles al público, como asimismo sobre los demás datos y antecedentes relacionados con el banco de datos, obligación que no cesa por haber terminado sus actividades en ese campo. | G8: Mal manejo de información | H8: 4600029025 CC-101 | I8: Personal exclusivo de manejo de información | J8: SI | K8: 1 | L8: Personal exclusivo de manejo de información | M8: Administrador de Contrato
E9: Art.9 | F9: Los datos personales deben utilizarse sólo para los fines para los cuales hubieren sido recolectados, salvo que provengan o se hayan recolectado de fuentes accesibles al público. | G9: Mal manejo de información | H9: 4600029025 CC-101 | I9: Uso en carpetas Personales | J9: SI | K9: 1 | L9: Uso en carpetas Personales | M9: Administrador de Contrato
E10: Art.11 | F10: El responsable de los registros o bases donde se almacenen datos personales con posterioridad a su recolección deberá cuidar de ellos con la debida diligencia, haciéndose responsable de los daños. | G10: Mal manejo de información | H10: 4600029025 CC-101 | I10: Uso en carpetas Personales | J10: SI | K10: 1 | L10: Uso en carpetas Personales | M10: Administrador de Contrato
E11: Art.24 | F11: Agregase los siguientes incisos segundo y tercero, nuevos, al artículo 127 del Código Sanitario: ''Las recetas médicas y análisis o exámenes de laboratorios clínicos y servicios relacionados con la salud son reservados. Sólo podrá revelarse su contenido o darse copia de ellos con el consentimiento expreso del paciente, otorgado por escrito | G11: Mal manejo de información | H11: 4600029025 CC-101 | I11: Examen Preocupacional / Ocupacional o Especifico | J11: SI | K11: 1 | L11: Registro de Consentimiento en Organismo Administrador | M11: Administrador de Contrato
K12: 1
C13: ELABORÓ | F13: REVISÓ | G13: APROBÓ
C14: Claudio Rojas / Jefe Dpto. HSEC | F14: Mauricio Araya / Presidente CPHS | G14: José Maira / Administrador de Contrato
C15: FIRMA: FECHA : 18-02-2026 | F15: FIRMA: FECHA : 18-02-2026 | G15: FIRMA: FECHA : 18-02-2026

Sheet Ley 19.728
D1: Lista de Verificación de Cumplimiento Requisitos Legales y Otros Aplicable a Seguridad, Salud Ocupacional, Medioambiente y Comunidad Contrato 4600029025 - SKIC CC-101 | M1: Código | N1: ='Planilla Global - Cumplim (%)'!I2 -> MTRSE-00002
M2: Revisión | N2: 2
M3: Fecha | N3: 46272
A5: Nº Cuerpo Legal | B5: Fecha de Publicación | C5: Organismo | D5: Nombre del Cuerpo Legal | E5: Articulo | F5: Descripción del Contenido (Breve) | G5: Peligro o Aspecto | H5: Nº Contrato | I5: Modo de Cumplimiento | J5: ¿Cumple? | K5: Porcentaje Cumplimiento | L5: Evidencia del Cumplimiento | M5: Responsable | N5: Fecha de cumplimiento
A6: Ley 19728 | B6: 37025 | C6: MINISTERIO DEL TRABAJO Y PREVISIÓN SOCIAL; SUBSECRETARÍA DEL TRABAJO | D6: ESTABLECE UN SEGURO DE DESEMPLEO | E6: Art.1 | F6: Establece un seguro obligatorio de cesantía, en adelante "el Seguro", en favor de los trabajadores dependientes regidos por el Código del Trabajo, en las condiciones previstas en la presente ley. El Seguro será administrado por una sociedad anónima denominada Sociedad Administradora de Fondos de Cesantía, en adelante Sociedad Administradora, que se regulará conforme a las disposiciones de la presente ley. | G6: Incumplimiento Legal | H6: 4600029025 CC-101 | I6: Información en liquidación de sueldos (AFC) | J6: SI | K6: 1 | L6: Liquidación de Sueldo firmada y/o enviada por correo | M6: Administrador de Contrato
E7: Art.2 | F7: Estarán sujetos al Seguro los trabajadores dependientes que inicien o reinicien actividades laborales con posterioridad a la entrada en vigencia de la presente ley.
K8: 1
C9: ELABORÓ | F9: REVISÓ | G9: APROBÓ
C10: Claudio Rojas / Jefe Dpto. HSEC | F10: Mauricio Araya / Presidente CPHS | G10: José Maira / Administrador de Contrato
C11: FIRMA: FECHA : 18-02-2026 | F11: FIRMA: FECHA : 18-02-2026 | G11: FIRMA: FECHA : 18-02-2026

Sheet LEY 20.000
D1: Lista de Verificación de Cumplimiento Requisitos Legales y Otros Aplicable a Seguridad, Salud Ocupacional, Medioambiente y Comunidad Contrato 4600029025 - SKIC CC-101 | M1: Código | N1: ='Planilla Global - Cumplim (%)'!I2 -> MTRSE-00002
M2: Revisión | N2: 2
M3: Fecha | N3: 46272
A5: Nº Cuerpo Legal | B5: Fecha de Publicación | C5: Organismo | D5: Nombre del Cuerpo Legal | E5: Artículo | F5: Descripción del Contenido (Breve) | G5: Peligro o Aspecto | H5: Nº Contrato | I5: Modo de Cumplimiento | J5: ¿Cumple? | K5: Porcentaje Cumplimiento | L5: Evidencia del Cumplimiento | M5: Responsable | N5: Fecha de cumplimiento
A6: Ley 20.000 | B6: 38399 | C6: Ministerio del Interior | D6: SUSTITUYE LA LEY Nº 19.366, QUE SANCIONA EL TRAFICO ILICITO DE ESTUPEFACIENTES Y SUSTANCIAS SICOTROPICAS | E6: Art.1 | F6: Los que elaboren, fabriquen, transformen, preparen o extraigan sustancias o drogas estupefacientes o sicotrópicas productoras de dependencia física o síquica, capaces de provocar graves efectos tóxicos o daños considerables a la salud, sin la debida autorización, serán castigados con presidio mayor en sus grados mínimo a medio y multa de cuarenta a cuatrocientas unidades tributarias mensuales. | G6: Drogas y Alcohol | H6: 4600029025 CC-101 | I6: RIOHS / POLITICA ALCOHOL Y DROGRAS | J6: SI | K6: 1 | L6: Entrega RIOHS - Difusión política alcohol y drogas | M6: RRHH | P6: https://www.bcn.cl/leychile/navegar?idNorma=235507
E7: Art.2 | F7: La producción, fabricación, elaboración, distribución, transporte, comercialización, importación, exportación, posesión o tenencia de precursores o de sustancias químicas esenciales, con el objetivo de destinarlos a la preparación de drogas estupefacientes o sustancias sicotrópicas para perpetrar, dentro o fuera del país, alguno de los hechos considerados como delitos en esta ley, será castigado con presidio menor en su grado máximo a presidio mayor en su grado mínimo y multa de cuarenta a cuatrocientas unidades tributarias mensuales. | G7: Drogas y Alcohol | H7: 4600029025 CC-101 | I7: RIOHS / POLITICA ALCOHOL Y DROGRAS | J7: SI | K7: 1 | L7: Acta de conformación de comité Bipartito | M7: RRHH
E8: Art.3 | F8: Las penas establecidas en el artículo 1º se aplicarán también a quienes trafiquen, bajo cualquier título, con las sustancias a que dicha disposición se refiere, o con las materias primas que sirvan para obtenerlas y a quienes, por cualquier medio, induzcan, promuevan o faciliten el uso o consumo de tales sustancias. Se entenderá que trafican los que, sin contar con la autorización competente, importen, exporten, transporten, adquieran, transfieran, sustraigan, posean, suministren, guarden o porten tales sustancias o materias primas. | G8: Drogas y Alcohol | H8: 4600029025 CC-101 | I8: RIOHS / POLITICA ALCOHOL Y DROGRAS | J8: SI | K8: 1 | L8: Programa de Capacitación | M8: RRHH
E9: Art.4 | F9: El que, sin la competente autorización posea, transporte, guarde o porte consigo pequeñas cantidades de sustancias o drogas estupefacientes o sicotrópicas, productoras de dependencia física o síquica, o de materias primas que sirvan para obtenerlas, sea que se trate de las indicadas en los incisos primero o segundo del artículo 1º, será castigado con presidio menor en sus grados medio a máximo y multa de diez a cuarenta unidades tributarias mensuales, a menos que justifique que están destinadas a la atención de un tratamiento médico o a su uso o consumo personal exclusivo y próximo en el tiempo. En igual pena incurrirá el que adquiera, transfiera, suministre o facilite a cualquier título pequeñas cantidades de estas sustancias, drogas o materias primas, con el objetivo de que sean consumidas o usadas por otro. Se entenderá que no concurre la circunstancia de uso o consumo personal exclusivo y próximo en el tiempo, cuando la calidad o pureza de la droga poseída, transportada, guardada o portada no permita racionalmente suponer que está destinada al uso o consumo descrito o cuando las circunstancias de la posesión, transporte, guarda o porte sean indiciarias del propósito de traficar a cualquier título. | G9: Drogas y Alcohol | H9: 4600029025 CC-101 | I9: RIOHS / POLITICA ALCOHOL Y DROGRAS | J9: SI | K9: 1 | L9: Programa de Capacitación | M9: RRHH
E10: Art.5 | F10: El que suministre a menores de dieciocho años de edad, a cualquier título, productos que contengan hidrocarburos aromáticos, tales como benceno, tolueno u otras sustancias similares, incurrirá en la pena de presidio menor en sus grados medio a máximo y multa de cuarenta a doscientas unidades tributarias mensuales. Atendidas las circunstancias del delito, podrá imponerse, además, la clausura a que hace referencia el artículo 7º. | G10: Drogas y Alcohol | H10: 4600029025 CC-101 | I10: RIOHS / POLITICA ALCOHOL Y DROGRAS | J10: SI | K10: 1 | L10: Programa de Capacitación | M10: RRHH
E11: Art.8 | F11: El que, careciendo de la debida autorización, siembre, plante, cultive o coseche especies vegetales del género cannabis u otras productoras de sustancias estupefacientes o sicotrópicas, incurrirá en la pena de presidio menor en su grado máximo a presidio mayor en su grado mínimo y multa de cuarenta a cuatrocientas unidades tributarias mensuales, a menos que justifique que están destinadas a su uso o consumo personal exclusivo y próximo en el tiempo, caso en el cual sólo se aplicarán las sanciones de los artículos 50 y siguientes. Según la gravedad del hecho y las circunstancias personales del responsable, la pena podrá rebajarse en un grado. | G11: Drogas y Alcohol | H11: 4600029025 CC-101 | I11: RIOHS / POLITICA ALCOHOL Y DROGRAS | J11: SI | K11: 1 | L11: Programa de Capacitación | M11: RRHH
E12: Art.17 | F12: La conspiración para cometer los delitos contemplados en esta ley será sancionada con la pena asignada al delito respectivo, rebajada en un grado. | G12: Drogas y Alcohol | H12: 4600029025 CC-101 | I12: RIOHS / POLITICA ALCOHOL Y DROGRAS | J12: SI | K12: 1 | L12: Programa de Capacitación | M12: RRHH
E13: Art.26 | F13: El Ministerio Público podrá efectuar indagaciones y actuaciones en el extranjero dirigidas a recoger antecedentes acerca de hechos constitutivos de alguno de los delitos contemplados en la presente ley, pudiendo solicitar directamente asesoría a las representaciones diplomáticas y consulares chilenas. | G13: Drogas y Alcohol | H13: 4600029025 CC-101 | I13: RIOHS / POLITICA ALCOHOL Y DROGRAS | J13: SI | K13: 1 | L13: Programa de Capacitación | M13: RRHH
E14: Art.50 | F14: Los que consumieren alguna de las drogas o sustancias estupefacientes o sicotrópicas de que hace mención el artículo 1º, en lugares públicos o abiertos al público, tales como calles, caminos, plazas, teatros, cines, hoteles, cafés, restaurantes, bares, estadios, centros de baile o de música; o en establecimientos educacionales o de capacitación, serán sancionados con alguna de las siguientes penas: a) Multa de una a diez unidades tributarias mensuales. b) Asistencia obligatoria a programas de prevención hasta por sesenta días, o tratamiento o rehabilitación en su caso por un período de hasta ciento ochenta días en instituciones autorizadas por el Servicio de Salud competente. Para estos efectos, el Ministerio de Salud o el Servicio Nacional para la Prevención y Rehabilitación del Consumo de Drogas y Alcohol deberán asignar preferentemente los recursos que se requieran. c) Participación en actividades determinadas a beneficio de la comunidad, con acuerdo del infractor y a propuesta del departamento social de la municipalidad respectiva, hasta por un máximo de treinta horas, o en cursos de capacitación por un número de horas suficientes para el aprendizaje de la técnica o arte objeto del curso. Para estos efectos, cada municipalidad deberá anualmente informar a el o los juzgados de garantía correspondientes acerca de los programas en beneficio de la comunidad de que disponga. El juez deberá indicar el tipo de actividades a que se refiere esta letra, el lugar en que se desarrollarán y el organismo o autoridad encargada de su supervisión. Esta medida se cumplirá sin afectar la jornada educacional o laboral del infractor. Se aplicará como pena accesoria, en su caso, la suspensión de la licencia para conducir vehículos motorizados por un plazo máximo de seis meses. En caso de reincidencia, la suspensión será de hasta un año y, de reincidir nuevamente, podrá extenderse hasta por dos años. Esta medida no podrá ser suspendida, ni aun cuando el juez hiciere uso de la facultad contemplada en el artículo 398 del Código Procesal Penal. Idénticas penas se aplicarán a quienes tengan o porten en tales lugares las drogas o sustancias antes indicadas para su uso o consumo personal exclusivo y próximo en el tiempo. Con las mismas penas serán sancionados quienes consuman dichas drogas en lugares o recintos privados, si se hubiesen concertado para tal propósito. Se entenderá justificado el uso, consumo, porte o tenencia de alguna de dichas sustancias para la atención de un tratamiento médico. | G14: Drogas y Alcohol | H14: 4600029025 CC-101 | I14: RIOHS / POLITICA ALCOHOL Y DROGRAS | J14: SI | K14: 1 | L14: Programa de Capacitación | M14: RRHH
K15: 1
C16: ELABORÓ | F16: REVISÓ | G16: APROBÓ
C17: Claudio Rojas / Jefe Dpto. HSEC | F17: Mauricio Araya / Presidente CPHS | G17: José Maira / Administrador de Contrato
C18: FIRMA: FECHA : 18-02-2026 | F18: FIRMA: FECHA : 18-02-2026 | G18: FIRMA: FECHA : 18-02-2026

Sheet Ley 20.001
D1: Lista de Verificación de Cumplimiento Requisitos Legales y Otros Aplicable a Seguridad, Salud Ocupacional, Medioambiente y Comunidad Contrato 4600029025 - SKIC CC-101 | M1: Código | N1: ='Planilla Global - Cumplim (%)'!I2 -> MTRSE-00002
M2: Revisión | N2: 2
M3: Fecha | N3: 46272
A5: Nº Cuerpo Legal | B5: Fecha de Publicación | C5: Organismo | D5: Nombre del Cuerpo Legal | E5: Artículo | F5: Descripción del Contenido (Breve) | G5: Peligro o Aspecto | H5: Nº Contrato | I5: Modo de Cumplimiento | J5: ¿Cumple? | K5: Porcentaje Cumplimiento | L5: Evidencia del Cumplimiento | M5: Responsable | N5: Fecha de cumplimiento
A6: Ley 20.001 | B6: 38388 | C6: MINISTERIO DEL TRABAJO Y PREVISIÓN SOCIAL. SUBSECRETARIA PREVISION SOCIAL | D6: REGULA EL PESO MAXIMO DE CARGA HUMANA | E6: Art.211-H | F6: Si la manipulación manual es inevitable y las ayudas mecánicas no pueden usarse, no se permitirá que se opere con cargas superiores a 50 kilogramos. | G6: Levantamiento incorrecto de material o carga, Sobrepasar capacidad de carga y Mala manipulación de muestreador | H6: 4600029025 CC-101 | I6: RIOHS Utilizar mecanismos mecánicos, en caso que se pueda y los medios lo permitan | J6: SI | K6: 1 | L6: RIOHS vigente Charla ODI Charla difusión protocolo MMC | M6: Administrador
E7: Art.211-j | F7: Los menores de 18 años y mujeres no podrán llevar, transportar, cargar, arrastrar o empujar manualmente, y sin ayuda mecánica, cargas superiores a los 20 kilogramos.". | G7: Levantamiento incorrecto de material o carga, Sobrepasar capacidad de carga y Mala manipulación de muestreador | H7: 4600029025 CC-101 | I7: RIOHS Charla ODI indicar prohibición de Manipular cargas superiores a 25 Kg. | J7: SI | K7: 1 | L7: RIOHS vigente Charla ODI Charla difusión protocolo MMC | M7: Administrador
E8: Art.211-I | F8: Se prohíbe las operaciones de carga y descarga manual para la mujer embarazada. | G8: Levantamiento incorrecto de material o carga, Sobrepasar capacidad de carga y Mala manipulación de muestreador | H8: 4600029025 CC-101 | I8: RIOHS Charla ODI Prohibición de Manipular cargas a mujeres embarazadas | J8: SI | K8: 1 | L8: RIOHS vigente Charla ODI Charla difusión protocolo MMC | M8: Administrador
K9: 1
C10: ELABORÓ | F10: REVISÓ | G10: APROBÓ
C11: Claudio Rojas / Jefe Dpto. HSEC | F11: Mauricio Araya / Presidente CPHS | G11: José Maira / Administrador de Contrato
C12: FIRMA: FECHA : 18-02-2026 | F12: FIRMA: FECHA : 18-02-2026 | G12: FIRMA: FECHA : 18-02-2026

Sheet Ley 20.005
D1: Lista de Verificación de Cumplimiento Requisitos Legales y Otros Aplicable a Seguridad, Salud Ocupacional, Medioambiente y Comunidad Contrato 4600029025 - SKIC CC-101 | M1: Código | N1: ='Planilla Global - Cumplim (%)'!I2 -> MTRSE-00002
M2: Revisión | N2: 2
M3: Fecha | N3: 46272
A5: Nº Cuerpo Legal | B5: Fecha de Publicación | C5: Organismo | D5: Nombre del Cuerpo Legal | E5: Artículo | F5: Descripción del Contenido (Breve) | G5: Peligro o Aspecto | H5: Nº Contrato | I5: Modo de Cumplimiento | J5: ¿Cumple? | K5: Porcentaje Cumplimiento | L5: Evidencia del Cumplimiento | M5: Responsable | N5: Fecha de cumplimiento
A6: Ley 20.005 | B6: 10.03.2005 | C6: MINISTERIO DEL TRABAJO Y PREVISIÓN SOCIAL | D6: TIPIFICA Y SANCIONA EL ACOSO SEXUAL | E6: Art.2 | F6: Todo trabajador/a de la empresa que sufra o conozca de hechos ilícitos definidos como acoso sexual por la ley o este reglamento, tiene derecho a denunciarlos, por escrito, a la gerencia y/o administración superior de la empresa (o establecimiento, o servicio), o a la Inspección del Trabajo competente. | G6: No denunciarlos y permitir Agresión o Abuso Físico y/o Psicológico | H6: 4600029025 CC-101 | I6: Requisito establecido en RIOHS | J6: SI | K6: 1 | L6: Entrega de RIOHS | M6: RRHH
K7: 1
C8: ELABORÓ | F8: REVISÓ | G8: APROBÓ
C9: Claudio Rojas / Jefe Dpto. HSEC | F9: Mauricio Araya / Presidente CPHS | G9: José Maira / Administrador de Contrato
C10: FIRMA: FECHA : 18-02-2026 | F10: FIRMA: FECHA : 18-02-2026 | G10: FIRMA: FECHA : 18-02-2026

Sheet Ley 20.047
D1: Lista de Verificación de Cumplimiento Requisitos Legales y Otros Aplicable a Seguridad, Salud Ocupacional, Medioambiente y Comunidad Contrato 4600029025 - SKIC CC-101 | M1: Código | N1: ='Planilla Global - Cumplim (%)'!I2 -> MTRSE-00002
M2: Revisión | N2: 2
M3: Fecha | N3: 46272
A5: Nº Cuerpo Legal | B5: Fecha de Publicación | C5: Organismo | D5: Nombre del Cuerpo Legal | E5: Artículo | F5: Descripción del Contenido (Breve) | G5: Peligro o Aspecto | H5: Nº Contrato | I5: Modo de Cumplimiento | J5: ¿Cumple? | K5: Porcentaje Cumplimiento | L5: Evidencia del Cumplimiento | M5: Responsable | N5: Fecha de cumplimiento
A6: Ley 20.047 | B6: 38597 | C6: MINISTERIO DEL TRABAJO | D6: ESTABLECE UN PERMISO PATERNAL EN EL CODIGO DEL TRABAJO | E6: Art. ÚNICO | F6: Intercalase el siguiente inciso segundo, nuevo, en el artículo 195 del Código del Trabajo, pasando los actuales incisos segundo, tercero, cuarto y quinto, a ser incisos tercero, cuarto, quinto y sexto, respectivamente: "Sin perjuicio del permiso establecido en el artículo 66, el padre tendrá derecho a un permiso pagado de cuatro días en caso de nacimiento de un hijo, el que podrá utilizar a su elección desde el momento del parto, y en este caso será de días corridos, o distribuirlo dentro del primer mes desde la fecha del nacimiento. Este permiso también se otorgará al padre que se le conceda la adopción de un hijo, contado desde la respectiva sentencia definitiva. Este derecho es irrenunciable." | G6: No otorgar el Permiso que otorga la Ley 20.047 | H6: 4600029025 CC-101 | I6: Requisito establecido en RIOHS | J6: SI | K6: 1 | L6: Papeleta de Autorización del Permiso | M6: Administrador Contrato
K7: 1
C8: ELABORÓ | F8: REVISÓ | G8: APROBÓ
C9: Claudio Rojas / Jefe Dpto. HSEC | F9: Mauricio Araya / Presidente CPHS | G9: José Maira / Administrador de Contrato
C10: FIRMA: FECHA : 18-02-2026 | F10: FIRMA: FECHA : 18-02-2026 | G10: FIRMA: FECHA : 18-02-2026

Sheet LEY 20.068
D1: Lista de Verificación de Cumplimiento Requisitos Legales y Otros Aplicable a Seguridad, Salud Ocupacional, Medioambiente y Comunidad Contrato 4600029025 - SKIC CC-101 | M1: Código | N1: ='Planilla Global - Cumplim (%)'!I2 -> MTRSE-00002
M2: Revisión | N2: 2
M3: Fecha | N3: 46272
A5: Nº Cuerpo Legal | B5: Fecha de Publicación | C5: Organismo | D5: Nombre del Cuerpo Legal | F5: Descripción del Contenido (Breve) | G5: Peligro o Aspecto | H5: Nº Contrato | I5: Modo de Cumplimiento | J5: ¿Cumple? | K5: Porcentaje Cumplimiento | L5: Evidencia del Cumplimiento | M5: Responsable | N5: Fecha de cumplimiento
A6: Ley 20.068 | B6: 38696 | C6: Ministerio de Transporte y Telecomunicaciones | D6: INTRODUCE DIVERSAS MODIFICACIONES A LA LEY Nº 18.290, EN MATERIA DE TRANSITO TERRESTRE | E6: Art.18 | F6: La licencia de conductor será de duración indefinida y mantendrá su vigencia mientras su titular reúna los requisitos o exigencias que señale la ley. El titular de una licencia no profesional Clase B o C, o de una licencia especial, deberá acreditar cada 6 años que cumple con los requisitos de idoneidad moral, física y síquica, en la forma establecida en los artículos 14 y 21. El titular de una licencia profesional deberá acreditar, cada 4 años, que cumple con los requisitos exigidos en los números 1 y 4 del inciso primero del artículo 13. El titular de una licencia Clase A-1 o A-2, obtenidas antes del 8 de marzo de 1997 deberá acreditar, cada 4 años, que cumple con los requisitos exigidos en los números 1, 2 y 4 del inciso primero del artículo 13, con excepción de los conocimientos prácticos.". | G6: No contar con licencia de conducir Municipal e Interna | H6: 4600029025 CC-101 | I6: Licencias de conducir Municipal e Interna | J6: SI | K6: 1 | L6: Copia de Licencia de conducir Municipal e Interna en Carpeta Personal | M6: RRHH | O6: https://www.bcn.cl/leychile/navegar?idNorma=244868
E7: Art.62 | F7: "A estos vehículos les serán aplicables las normas referentes a revisión técnica y a seguridad, en lo que fueran pertinentes, según su capacidad de carga y especialidad.". | G7: No contar con la revisión técnica | H7: 4600029025 CC-101 | I7: Revisión técnica al día | J7: SI | K7: 1 | L7: Certificado en vehículo | M7: RRHH
E8: Art.64 | F8: Los vehículos deberán contar con el o los sistemas de freno, luces y elementos retro reflectantes que determine el reglamento.". | G8: No cotar con revisión técnica al día | H8: 4600029025 CC-101 | I8: Revisión técnica al día | J8: SI | K8: 1 | L8: Certificado en vehículo | M8: RRHH
E9: Art.72 | F9: Desde media hora después de la puesta de sol, hasta media hora antes de su salida y cada vez que las condiciones del tiempo lo requieran o el reglamento lo determine, los vehículos deberán llevar encendidas las luces que éste establezca. Sin embargo, las motocicletas, bici motos, motonetas y similares, deberán circular permanentemente con sus luces fijas encendidas y las bicicletas deberán contar con elementos reflectantes.". | G9: No mantener las luces encendidas de acuerdo a lo que estipula el reglamento. | H9: 4600029025 CC-101 | I9: Mantener luces encendidas de acuerdo a lo indicado en el reglamento | J9: SI | K9: 1 | L9: Conforme a lo estipulado por la ley | M9: RRHH
E10: Art.79 | F10: a) Agregase, en el inciso primero del número 1, la oración "Prohíbanse los vidrios oscuros o polarizados, salvo los que se contemplen en el Reglamento.". c) Sustituyese el número 8, por el siguiente: "8.- Rueda de repuesto en buen estado y los elementos necesarios para el reemplazo, salvo en aquellos casos que determine el reglamento;". | G10: Mantener vidrios polarizados oscuros y no contar con rueda de repuesto en buen estado | H10: 4600029025 CC-101 | I10: Mantener certificación de laminas de seguridad de vidrios y contar con rueda de repuesto en buenas condiciones | J10: SI | K10: 1 | L10: Acreditación vehículo | M10: RRHH
E11: Art.81 | F11: Eliminase, en el inciso primero del artículo 81, la siguiente frase final: "El tubo de escape no deberá sobresalir de la parte trasera de la estructura del vehículo y permitirá el escape del gas sólo en forma paralela a la calzada.". | G11: No contar con tubo de escape de acuerdo a lo establecido en el reglamento | H11: 4600029025 CC-101 | I11: Mantener tubo de escapa de acuerdo a lo indicado en el reglamento. | J11: SI | K11: 1 | L11: Conforme a los establecido por la ley y la revisión técnica del vehículo actualizada | M11: RRHH
E12: Art.114 | F12: agregase el siguiente inciso final, nuevo: "Se prohíbe llevar abiertas las puertas del vehículo, abrirlas antes de su completa detención o abrirlas, mantenerlas abiertas o descender del mismo sin haberse cerciorado previamente de que ello no implica entorpecimiento o peligro para otros usuarios.". | G12: Abrir las puertas del vehículo cuando este se encuentre en movimiento | H12: 4600029025 CC-101 | I12: Mantener puertas cerradas en todo momento en que el vehículo se encuentre en movimiento. | J12: SI | K12: 1 | L12: Conforme a lo establecido por la ley | M12: RRHH
E13: Art.124 | F13: El conductor de un vehículo que adelante o sobrepase a otro, deberá hacerlo por la izquierda y a una distancia que garantice seguridad, y no volverá a tomar la pista de la derecha hasta que tenga distancia suficiente y segura delante del vehículo que acaba de adelantar o sobrepasar. El conductor del vehículo que es adelantado o sobrepasado deberá ceder el paso en favor del que lo adelante o sobrepase y no deberá aumentar la velocidad hasta que éste complete la maniobra.". | G13: Realizar adelantamiento por el lado derecho | H13: 4600029025 CC-101 | I13: Nunca realizar adelantamiento por el lado derecho, sólo si las señales de tránsito lo indican. | J13: SI | K13: 1 | L13: Conforme a lo establecido por la ley | M13: RRHH
A14: Ley 20.068 | B14: 38696 | C14: Ministerio de Transporte y Telecomunicaciones | D14: INTRODUCE DIVERSAS MODIFICACIONES A LA LEY Nº 18.290, EN MATERIA DE TRANSITO TERRESTRE | E14: Art.127 | F14: Ningún vehículo podrá adelantar o sobrepasar a otro en un paso de peatones ni en un cruce, salvo que éstos se encuentren regulados.". | G14: Adelantar un vehículo en paso de peatones | H14: 4600029025 CC-101 | I14: Nunca adelantar un vehículo en un paso de peatones. | J14: SI | K14: 1 | L14: Conforme a lo establecido por la ley | M14: RRHH
E15: Art.151 | F15: introdúzcanse las siguientes modificaciones: b) Agregase el siguiente inciso tercero, nuevo: "En Zona de Escuela, en horarios de entrada y salida de los alumnos, los vehículos no podrán circular a más de treinta kilómetros por hora.", y c) Agregase el siguiente inciso final: "El conductor que se aproxime a un vehículo de transporte escolar detenido con su dispositivo de luz intermitente, en los lugares habilitados para ello, deberá reducir la velocidad hasta detenerse si fuera necesario, para continuar luego con la debida precaución.". | G15: No reducir velocidad al enfrentar a un vehículo escolar | H15: 4600029025 CC-101 | I15: Mantener velocidad indicada en el reglamento en sectores de escuelas. | J15: SI | K15: 1 | L15: Conforme a lo establecido por la ley | M15: RRHH
E16: Art.174 | F16: a) Reemplazase, el inciso segundo, por el siguiente: "El conductor, el propietario del vehículo y el tenedor del mismo a cualquier título, a menos que estos últimos acrediten que el vehículo fue usado contra su voluntad, son solidariamente responsables de los daños o perjuicios que se ocasionen con su uso, sin perjuicio de la responsabilidad de terceros de conformidad a la legislación vigente.". | G16: Robo de vehículos | H16: 4600029025 CC-101 | I16: Mantener vehículos de acuerdo a la normativa interna, GPS. | J16: SI | K16: 1 | L16: Conforme a los establecido por la ley. Se asegura la existencia de dispositivos de emergencias mediante el check list de pre uso de vehículos | M16: RRHH
E17: Art.189 | F17: sustitúyanse los incisos segundo, tercero, cuarto, quinto y sexto, por los siguientes: "Carabineros, asimismo, podrá practicar estos exámenes a toda persona respecto de la cual tema fundadamente que se apresta a conducir un vehículo en lugar público y que presente signos externos de no estar en plenitud de facultades para ello. Si la prueba resulta positiva, Carabineros deberá prohibirle la conducción del vehículo por un plazo no superior a 3 horas, en caso de encontrarse bajo la influencia del alcohol, ni de 12 horas, en caso de encontrarse en estado de ebriedad o bajo la influencia de sustancias estupefacientes o sicotrópicas. Durante el período de tiempo que fije Carabineros, el afectado podrá ser conducido a la Unidad Policial respectiva, a menos que se allane a inmovilizar el vehículo por el tiempo que fije Carabineros o señale a otra persona que, haciéndose responsable, se haga cargo de la conducción durante dicho plazo. Esta disposición se aplicará sin perjuicio de las demás medidas o sanciones previstas en las leyes. En el caso que la persona se apreste a conducir bajo la influencia del alcohol, en estado de ebriedad o bajo la influencia de sustancias estupefacientes o sicotrópicas, el juez aplicará la sanción indicada en el artículo 196 B o 196 E, disminuida o en grado de tentativa, según corresponda.". | G17: Alcohol y drogas | H17: 4600029025 CC-101 | I17: RIOHS - Política de alcohol y drogas. | J17: SI | K17: 1 | L17: Conforme a los establecido por la ley. En el caso de drogas y alcohol aplica reglamento interno | M17: RRHH
E18: Art.196C | F18: El que infringiendo la prohibición establecida en el inciso segundo del artículo 115 A, conduzca, opere o desempeñe las funciones bajo la influencia del alcohol, ya sea que no se ocasione daño alguno ni lesiones, o que con ello se causen daños materiales o lesiones leves, será sancionado con multa de una a cinco unidades tributarias mensuales y la suspensión de la licencia de conducir por un mes. Si, a consecuencia de esa conducción, operación o desempeño, se causaren lesiones menos graves, se impondrá la pena de prisión en su grado mínimo o multa de cuatro a diez unidades tributarias mensuales y la suspensión de la licencia de conducir de dos a cuatro meses. Si se causaren lesiones graves, la pena asignada será aquélla señalada en el artículo 490, Nº 2, del Código Penal y la suspensión de la licencia de conducir de cuatro a ocho meses. Si se causaren algunas de las lesiones indicadas en el artículo 397, Nº 1, del Código Penal o la muerte, se impondrá la pena de reclusión menor en su grado máximo, multa de ocho a quince unidades tributarias mensuales y la suspensión de la licencia para conducir por el plazo que determine el juez, el que no podrá ser inferior a doce ni superior a veinticuatro meses. Los jueces podrán siempre, aunque no medie condena por concurrir alguna circunstancia eximente de responsabilidad penal, decretar la inhabilidad temporal o perpetua para conducir vehículos motorizados, si las condiciones psíquicas y morales del autor lo aconsejan. En caso de reincidencia el infractor sufrirá, además de la pena que le corresponda, la suspensión de la licencia para conducir por el tiempo que estime el juez, el que no podrá ser inferior a veinticuatro ni superior a cuarenta y ocho meses.". | G18: Alcohol y drogas | H18: 4600029025 CC-101 | I18: RIOHS - Política de alcohol y drogas. | J18: SI | K18: 1 | L18: Conforme a los establecido por la ley. En el caso de drogas y alcohol aplica reglamento interno | M18: RRHH
E19: Art.198 | F19: Son infracciones o contravenciones graves las siguientes: 1.- Conducir un vehículo en condiciones físicas o psíquicas deficientes; 3.- Conducir un vehículo con una licencia de conductor distinta a la que corresponda, salvo lo dispuesto en el inciso primero del artículo 196 D; 4.- Sobrepasar o adelantar en la situación prevista en los números 1 y 2 del artículo 126, en un paso para peatones o en un cruce no regulado, o sobrepasar por la berma; 5.- Entregar el dueño o su tenedor un vehículo para que lo conduzca persona que no cumpla con los requisitos para conducir; 6.- Conducir un vehículo sin la placa patente; 7.- Desobedecer las señales u órdenes de tránsito de un integrante de Carabineros de Chile o las de un inspector fiscal en los procedimientos de fiscalización del transporte público y privado remunerado de pasajeros y transporte de carga; 8.- No respetar los signos y demás señales que rigen el tránsito público, que no sean las indicadas en el número 2 del artículo anterior; 10.- No cumplir con lo dispuesto en el artículo 135 o en el artículo 121; 11.- Conducir un vehículo contra el sentido del tránsito; 13.- Conducir por la izquierda del eje de la calzada en una vía que tenga tránsito en ambos sentidos, ocupando el todo o parte del ancho de dicha calzada, salvo la excepción del artículo 126; 14.- No respetar el derecho preferente de paso de un peatón o de otro conductor; 15.- Detener o estacionar un vehículo en contravención a lo establecido en los números 6, 7 u 8 del artículo 159; 16.- Infringir las normas sobre virajes contempladas en los artículos 138 y 139; 17.- Conducir un vehículo con sus sistemas de dirección o de frenos en condiciones deficientes; 18.- Conducir un vehículo sin luces en las horas y circunstancias en que las exige esta ley o sus reglamentos; 19.- Conducir un vehículo con uno o más neumáticos en mal estado; 21.- No bajar la luz en carretera al enfrentar o acercarse por detrás a otro vehículo; 22.- Conducir un vehículo sin revisión técnica de reglamento, de homologación o de emisión de contaminantes vigentes o infringiendo las normas en materia de emisiones; 24.- No detener el vehículo antes de cruzar una línea férrea; 28.- Conducir un vehículo sin tacógrafo u otro dispositivo que registre en el tiempo la velocidad y distancia recorrida, o con éste en mal estado o en condiciones deficientes, cuando su uso sea obligatorio; 29.- Conducir un vehículo sin permiso de circulación o sin certificado de un seguro obligatorio de accidentes causados por vehículos motorizados, vigentes; 32.- Usar indebidamente estacionamientos exclusivos para personas con discapacidad; 33.- Detener o estacionar un vehículo en doble fila, respecto a otro vehículo detenido o estacionado junto a la cuneta; 34.- Cruzar una vía férrea en lugar no autorizado; 36.- Conducir haciendo uso de un teléfono celular u otro aparato de telecomunicaciones, salvo que tal uso se efectúe por medio de un sistema de "manos libres", cuyas características serán determinadas por reglamento; 38.- Circular por la mitad izquierda de la calzada, salvo en las excepciones mencionadas en los artículos 120 y 129; 39.- Transitar en un área urbana con restricciones por razones de contaminación ambiental, sin estar autorizado; 40.- Usar cualquier tipo de elemento destinado a evadir la fiscalización; 41.- Arrojar desde un vehículo cigarrillos u otros elementos encendidos que puedan provocar un siniestro o un accidente; 42.- Usar los particulares, de dispositivos especiales propios de vehículos de emergencia, salvo los autorizados por el reglamento; 43.- Detenerse, tratándose de medios de locomoción pública, en la intersección de calles, a dejar o tomar pasajeros en segunda fila o en paraderos no autorizados, y 44.- Toda infracción declarada por el juez como causa principal de un accidente de tránsito que origine daño o lesiones leves. | G19: Vehículos | H19: 4600029025 CC-101 | I19: Cumplir con protocolo de fatiga y somnolencia. | J19: SI | K19: 1 | L19: Conforme a lo establecido por la ley | M19: RRHH
E20: Art.199 | F20: Son infracciones o contravenciones menos graves, las siguientes: 1.- Estacionar o detener un vehículo en lugares prohibidos sin perjuicio de lo establecido en los números 8, 33 y 43 del artículo anterior, o estacionar en un espacio destinado a vehículos para personas con discapacidad, sin derecho a ello; 2.- Infringir las normas del artículo 119; 3.- Conducir un vehículo usando indebidamente las luces, sin perjuicio de lo establecido en el número 18 del artículo anterior; 4.- Infringir, los conductores, las disposiciones del artículo 146 ó 147 sobre vehículos de emergencia; 5.- No hacer las señales debidas antes de virar; 6.- No respetar las prohibiciones establecidas en el artículo 141; 7.- Conducir un vehículo sin silenciador o con éste o el tubo de escape en malas condiciones, o con el tubo de salida antirreglamentario; 8.- No llevar los elementos señalados en los números 1, 2 y 3 del artículo 79; 9.- Detener o estacionar un vehículo en doble fila; 11.- Infringir las normas sobre transporte de pasajeros en los vehículos de carga; 14.- Infringir la prohibición de consumo de bebidas alcohólicas establecida en el inciso primero del artículo 115 A; 15.- Conducir bicicletas, motocicletas o vehículos similares, contraviniendo la norma sobre uso obligatorio de casco protector y demás elementos de seguridad; 16.- No cumplir las obligaciones que impone el artículo 183; 17.- Deteriorar o alterar cualquier señal de tránsito; 18.- Transitar un peatón por la calzada, por su derecha en los caminos o cruzar cualquier vía o calle fuera del paso para peatones o saltar vallas peatonales o pasar entre o sobre rejas u otros dispositivos existentes entre calzadas con tránsito opuesto; 19.- Infringir las normas sobre transporte terrestre dictadas por el Ministerio de Transportes y Telecomunicaciones; 20.- No cumplir el titular de una licencia de conductor con las obligaciones establecidas en los artículos 18 y 23, o no dar cumplimiento a las demás obligaciones que se le hayan impuesto en la licencia para conducir; 21.- Arrojar desde un vehículo desperdicios, residuos, objetos o sustancias; 22.- Infringir lo dispuesto en el artículo 122; 23.- Conducir un vehículo de alquiler o de transporte colectivo de personas con materias peligrosas; 24.- Infringir la obligación del propietario de dar cuenta al Registro Nacional de Vehículos Motorizados de todas las alteraciones en los vehículos que los hagan cambiar su naturaleza, sus características esenciales, o que los identifican, como asimismo su abandono, destrucción o desarmadura total o parcial; 25.- No conducir dentro de la pista de circulación demarcada o cambiar sorpresivamente de pista obstruyendo la circulación de otros vehículos; 26.- Detener o estacionar un vehículo en contravención a lo establecido en los números 6 y 7 del artículo 159 o estacionar en un paso para peatones, y 27.- Conducir un vehículo en alguna de las circunstancias a que se refiere el número 11 del artículo 172.". | G20: Conductores | H20: 4600029025 CC-101 | I20: Cumplimiento al reglamento interno de conducción . | J20: SI | K20: 1 | L20: Conforme a los establecido por la ley. En el caso de drogas y alcohol aplica reglamento interno | M20: RRHH
E21: Art.201 | F21: La pena de multa se aplicará a los infractores de los preceptos de esta ley, de acuerdo con la escala siguiente: 1.- Infracciones o contravenciones gravísimas, 1,5 a 3 unidades tributarias mensuales; 2.- Infracciones o contravenciones graves, 1 a 1,5 unidades tributarias mensuales; 3.- Infracciones o contravenciones menos graves, 0,5 a 1 unidad tributaria mensual, y 4.- Infracciones o contravenciones leves, 0,2 a 0,5 unidad tributaria mensual. A los reincidentes de infracciones gravísimas o graves, cometidas en los últimos tres y dos años, respectivamente, se les impondrá el doble de la multa establecida para cada infracción, la que se elevará al triple en caso de incurrirse nuevamente en dicha conducta. Lo anterior, sin perjuicio de las suspensiones o cancelaciones de licencias de conductor que corresponda. El adquirente de un vehículo, que no cumpla con la obligación establecida en el inciso cuarto del artículo 36, o que indique domicilio falso o inexistente, será sancionado con multa de 3 a 50 unidades tributarias mensuales. Asimismo, si no diera cumplimiento a la obligación establecida en el inciso final del mismo artículo, será sancionado con multa de 3 a 5 unidades tributarias mensuales. Al que transporte cargas peligrosas sin ajustarse a las normas reglamentarias que rigen la actividad, se le aplicará una multa de 5 a 20 unidades tributarias mensuales, respectivamente. En casos calificados, por resolución fundada, el Juez podrá imponer una multa de monto inferior a las señaladas, atendidas las condiciones en que se cometió el hecho denunciado o la capacidad económica del infractor. Si una persona, en un mismo hecho, fuera responsable de dos o más infracciones, se aplicará la multa que corresponda a la infracción de mayor grado, cualquiera que sea el número de ellas, sin perjuicio de lo dispuesto en el inciso anterior. Para la definición de las infracciones y establecimiento de penalidades sobre peso máximo de vehículos, regirán las disposiciones del Ministerio de Obras Públicas.". | G21: Conducción | H21: 4600029025 CC-101 | I21: Respetar reglamento de transito interno - RIOHS, para evitar multas. | J21: SI | K21: 1 | L21: Conforme a lo establecido por la ley | M21: RRHH
K22: 1
C23: ELABORÓ | F23: REVISÓ | G23: APROBÓ
C24: Claudio Rojas / Jefe Dpto. HSEC | F24: Mauricio Araya / Presidente CPHS | G24: José Maira / Administrador de Contrato
C25: FIRMA: FECHA : 18-02-2026 | F25: FIRMA: FECHA : 18-02-2026 | G25: FIRMA: FECHA : 18-02-2026

Sheet LEY 20096
D1: Lista de Verificación de Cumplimiento Requisitos Legales y Otros Aplicable a Seguridad, Salud Ocupacional, Medioambiente y Comunidad Contrato 4600029025 - SKIC CC-101 | M1: Código | N1: ='Planilla Global - Cumplim (%)'!I2 -> MTRSE-00002
M2: Revisión | N2: 2
M3: Fecha | N3: 46272
A5: Nº Cuerpo Legal | B5: Fecha de Publicación | C5: Organismo | D5: Nombre del Cuerpo Legal | E5: Artículo | F5: Descripción del Contenido (Breve) | G5: Peligro o Aspecto | H5: Nº Contrato | I5: Modo de Cumplimiento | J5: ¿Cumple? | K5: Porcentaje Cumplimiento | L5: Evidencia del Cumplimiento | M5: Responsable | N5: Fecha de cumplimiento
A6: Ley 20.096 | B6: 38799 | C6: Ministerio secretaria General de Presidencia | D6: Establece mecanismos de control aplicables a las sustancias agotadoras de ozono | E6: Art.4 | F6: Para el adecuado resguardo de la salud de la población frente a los efectos producidos por el deterioro de la capa de ozono, esta ley establece un conjunto de medidas de difusión, prevención y evaluación tendientes a generar y proporcionar información idónea y oportuna a los sujetos expuestos a riesgo y a estimular conductas seguras frente a éste. | G6: Exposición a radiación ultravioleta de origen solar | H6: 4600029025 CC-101 | I6: Reglamento Interno de Orden Higiene y Seguridad | J6: SI | K6: 1 | L6: Entrega del reglamento Interno | M6: Administrador de contrato RRLL
E7: Art.19 | F7: Sin perjuicio de las obligaciones establecidas en los artículos 184 del código del trabajo y 67 de la ley 16.744, los empleadores deberán adoptar todas las medidas necesarias para proteger eficazmente a los trabajadores cuando puedan estar expuestos a radiación ultravioleta. Para tales efectos los contratos de trabajos o reglamentos internos de la empresa según sea el caso, deberán especificar el uso de los protectores correspondientes, de conformidad con el reglamento sobre condiciones sanitarias y ambientales básicas en los lugares de trabajo. | G7: Exposición a radiación ultravioleta de origen solar | H7: 4600029025 CC-101 | I7: RIOHS | J7: SI | K7: 1 | L7: Comprobante de entrega de RIOHS y registro de la entrega del protector solar/ODI / Programa de Radiación UV | M7: Administrador de contrato RRLL
E8: Art.20 | F8: Los instrumentos y artefactos que emitan radiación ultravioleta, tales como lámparas o ampolletas, deberán incluir en sus especificaciones técnicas o etiquetas, una advertencia de los riesgos a la salud que su uso puede ocasionar. | G8: Exposición a radiación ultravioleta de origen solar | H8: 4600029025 CC-101 | I8: Etiquetas de especificaciones técnicas y de advertencia de riesgos | J8: SI | K8: 1 | L8: Inspecciones en Terreno | M8: Administrador de contrato RRLL
E9: Art.21 | F9: Los bloqueadores, anteojos y otros dispositivos o productos protectores de la quemadura solar, deberán llevar indicaciones que señalen el factor de protección relativo a la equivalencia del tiempo de exposición a la radiación ultravioleta sin protector, indicando su efectividad ante diferentes grados de deterioro de la capa de ozono. | G9: Exposición a radiación ultravioleta de origen solar | H9: 4600029025 CC-101 | I9: Compra de bloqueadores solar | J9: SI | K9: 1 | L9: Especificaciones técnicas del EPP con protección de radiación UV y entrega a los trabajadores | M9: Administrador de contrato RRLL
K10: =AVERAGE(K6:K9) -> 1
C11: ELABORÓ | F11: REVISÓ | G11: APROBÓ
C12: Claudio Rojas / Jefe Dpto. HSEC | F12: Mauricio Araya / Presidente CPHS | G12: José Maira / Administrador de Contrato
C13: FIRMA: FECHA : 18-02-2026 | F13: FIRMA: FECHA : 18-02-2026 | G13: FIRMA: FECHA : 18-02-2026

Sheet Ley 20.101
D1: Lista de Verificación de Cumplimiento Requisitos Legales y Otros Aplicable a Seguridad, Salud Ocupacional, Medioambiente y Comunidad Contrato 4600029025 - SKIC CC-101 | M1: Código | N1: ='Planilla Global - Cumplim (%)'!I2 -> MTRSE-00002
M2: Revisión | N2: 2
M3: Fecha | N3: 46272
A5: Nº Cuerpo Legal | B5: Fecha de Publicación | C5: Organismo | D5: Nombre del Cuerpo Legal | E5: Artículo | F5: Descripción del Contenido (Breve) | G5: Peligro o Aspecto | H5: Nº Contrato | I5: Modo de Cumplimiento | J5: ¿Cumple? | K5: Porcentaje Cumplimiento | L5: Evidencia del Cumplimiento | M5: Responsable | N5: Fecha de cumplimiento
A6: Ley 20.101 | B6: 38835 | C6: MINISTERIO DEL TRABAJO Y PREVISIÓN SOCIAL; SUBSECRETARIA DE PREVISION SOCIAL | D6: AMPLIA EL CONCEPTO DE ACCIDENTE DE TRABAJO CONTEMPLADO EN LA LEY Nº 16.744, SOBRE ACCIDENTES DEL TRABAJO Y ENFERMEDADES PROFESIONALES | E6: Art.5 | F6: Para los efectos de esta ley se entiende por accidente del trabajo toda lesión que una persona sufra a causa o con ocasión del trabajo, y que le produzca incapacidad o muerte. Son también accidentes del trabajo los ocurridos en el trayecto directo, de ida o regreso, entre la habitación y lugar del trabajo. Se considerarán también accidentes del trabajo los sufridos por dirigentes de instituciones sindicales a causa o con ocasión del desempeño de sus cometidos gremiales. ley 20.101 Y aquéllos que ocurran en el trayecto directo entre dos lugares de trabajo, aunque correspondan a distintos empleadores. En este último caso, se considerará que el accidente dice relación con el trabajo al que se dirigía el trabajador al ocurrir el siniestro". | G6: No emitir DIAT | H6: 4600029025 CC-101 | I6: Emisión de DIAT | J6: SI | K6: 1 | L6: DIAT firmada por el OAL o subida al sistema | M6: Administrador de Contrato
K7: 1
C8: ELABORÓ | F8: REVISÓ | G8: APROBÓ
C9: Claudio Rojas / Jefe Dpto. HSEC | F9: Mauricio Araya / Presidente CPHS | G9: José Maira / Administrador de Contrato
C10: FIRMA: FECHA : 18-02-2026 | F10: FIRMA: FECHA : 18-02-2026 | G10: FIRMA: FECHA : 18-02-2026

Sheet Ley 20.105
D1: Lista de Verificación de Cumplimiento Requisitos Legales y Otros Aplicable a Seguridad, Salud Ocupacional, Medioambiente y Comunidad Contrato 4600029025 - SKIC CC-101 | M1: Código | N1: ='Planilla Global - Cumplim (%)'!I2 -> MTRSE-00002
M2: Revisión | N2: 2
M3: Fecha | N3: 46272
A5: Nº Cuerpo Legal | B5: Fecha de Publicación | C5: Organismo | D5: Nombre del Cuerpo Legal | E5: Artículo | F5: Descripción del Contenido (Breve) | G5: Peligro o Aspecto | H5: Nº Contrato | I5: Modo de Cumplimiento | J5: ¿Cumple? | K5: Porcentaje Cumplimiento | L5: Evidencia del Cumplimiento | M5: Responsable | N5: Fecha de cumplimiento
A6: Ley Nº 20.105 | B6: 38853 | C6: MINISTERIO DE SALUD; SUBSECRETARÍA DE SALUD PÚBLICA | D6: MODIFICA LA LEY Nº 19.419, EN MATERIAS RELATIVAS A LA PUBLICIDAD Y EL CONSUMO DEL TABACO | E6: Art.11 | F6: Se prohíbe fumar en los siguientes lugares, salvo en sus patios o espacios al aire libre: a) al interior de los recintos o dependencias de los órganos del Estado. Sin embargo, en las oficinas individuales se podrá fumar sólo en el caso que cuenten con ventilación hacia el aire libre o extracción del aire hacia el exterior; b) establecimientos de educación superior, públicos y privados; c) establecimientos de salud, públicos y privados; d) aeropuertos y terrapuertos; e) teatros, cines, lugares en que se presenten espectáculos culturales y musicales, salvo que sean al aire libre; f) gimnasios y recintos deportivos; g) centros de atención o de prestación de servicios abiertos al público en general; h) supermercados, centros comerciales y demás establecimientos similares de libre acceso al público. En los lugares anteriormente enumerados, podrá existir una o más salas especialmente habilitadas para fumar, con excepción de los casos que señala la letra c). Sin perjuicio de lo dispuesto en el artículo siguiente, iguales reglas se aplicarán tratándose de empresas, establecimientos, faenas o unidades económicas obligadas a confeccionar un reglamento interno de orden, higiene y seguridad, en conformidad a las normas del Código del Trabajo. En los lugares de trabajo de propiedad de particulares no comprendidos en el artículo 10 y en los incisos precedentes, la existencia de prohibición de fumar o la determinación de sitios y condiciones en que ello se autorizará serán acordadas por los respectivos propietarios o administradores, oyendo el parecer de los empleados. | G6: TABACO | H6: 4600029025 CC-101 | I6: Plan de Alcohol y Drogas | J6: SI | K6: 1 | L6: Registro de Difusión | M6: HSEC - ADC CTTO
K7: 1
C8: ELABORÓ | F8: REVISÓ | G8: APROBÓ
C9: Claudio Rojas / Jefe Dpto. HSEC | F9: Mauricio Araya / Presidente CPHS | G9: José Maira / Administrador de Contrato
C10: FIRMA: FECHA : 18-02-2026 | F10: FIRMA: FECHA : 18-02-2026 | G10: FIRMA: FECHA : 18-02-2026

Sheet Ley 20.123
D1: Lista de Verificación de Cumplimiento Requisitos Legales y Otros Aplicable a Seguridad, Salud Ocupacional, Medioambiente y Comunidad Contrato 4600029025 - SKIC CC-101 | M1: Código | N1: ='Planilla Global - Cumplim (%)'!I2 -> MTRSE-00002
M2: Revisión | N2: 2
M3: Fecha | N3: 46272
A5: Nº Cuerpo Legal | B5: Fecha de Publicación | C5: Organismo | D5: Nombre del Cuerpo Legal | F5: Descripción del Contenido (Breve) | G5: Peligro o Aspecto | H5: Nº Contrato | I5: Modo de Cumplimiento | J5: ¿Cumple? | K5: Porcentaje Cumplimiento | L5: Evidencia del Cumplimiento | M5: Responsable | N5: Fecha de cumplimiento
A6: Ley 20.123 | B6: 39006 | C6: MINISTERIO DEL TRABAJO | D6: Regula trabajo en régimen de subcontratación, el funcionamiento de las empresas de servicios transitorios y el contrato de trabajo de servicios transitorios | E6: Art.183 -A | F6: Es trabajo en régimen de subcontratación, aquél realizado en virtud de un contrato de trabajo por un trabajador para un empleador, denominado contratista o subcontratista, cuando éste, en razón de un acuerdo contractual, se encarga de ejecutar obras o servicios, por su cuenta y riesgo y con trabajadores bajo su dependencia, para una tercera persona natural o jurídica dueña de la obra, empresa o faena, denominada la empresa principal, en la que se desarrollan los servicios o ejecutan las obras contratadas. Con todo, no quedarán sujetos a las normas de este Párrafo las obras o los servicios que se ejecutan o prestan de manera discontinua o esporádica. Si los servicios prestados se realizan sin sujeción a los requisitos señalados en el inciso anterior o se limitan sólo a la intermediación de trabajadores a una faena, se entenderá que el empleador es el dueño de la obra, empresa o faena, sin perjuicio de las sanciones que correspondan por aplicación del artículo 478. | G6: No Contar con Contrato con la empresa subcontratista | H6: 4600029025 CC-101 | I6: Contrato formal entre ambas partes Reglamento especial de SSO para empresas subcontratistas | J6: SI | K6: 1 | L6: Contrato firmado Registro entrega Reglamento especial de S&SO para empresas subcontratistas | M6: Administrador de contrato
E7: Art.183 - B | F7: La empresa principal será solidariamente responsable de las obligaciones laborales y previsionales de dar que afecten a los contratistas en favor de los trabajadores de éstos, incluidas las eventuales indemnizaciones legales que correspondan por término de la relación laboral. Tal responsabilidad estará limitada al tiempo o período durante el cual el o los trabajadores prestaron servicios en régimen de subcontratación para la empresa principal. | G7: No Cumplir con las obligaciones legales | H7: 4600029025 CC-101 | I7: Solicitar Informes Mensuales pagos previsionales | J7: SI | K7: 1 | L7: Planilla pago cotizaciones | M7: Administrador de contrato
E8: Art.183 - C | F8: La empresa principal, cuando así lo solicite, tendrá derecho a ser informada por los contratistas sobre el monto y estado de cumplimiento de las obligaciones laborales y previsionales que a éstos correspondan respecto a sus trabajadores, como asimismo de igual tipo de obligaciones que tengan los subcontratistas con sus trabajadores. | G8: No Cumplir con los requerimientos del cliente | H8: 4600029025 CC-101 | I8: Solicitar Informes Mensuales pagos previsionales | J8: SI | K8: 1 | L8: Planilla pago cotizaciones | M8: Administrador de contrato
E9: Art.183 - D | F9: Si la empresa principal hiciere efectivo el derecho a ser informada y el derecho de retención a que se refieren los incisos primero y tercero del artículo anterior, responderá subsidiariamente de aquellas obligaciones laborales y previsionales que afecten a los contratistas y subcontratistas en favor de los trabajadores de éstos, incluidas las eventuales indemnizaciones legales que correspondan por el término de la relación laboral. Tal responsabilidad estará limitada al tiempo o período durante el cual el o los trabajadores del contratista o subcontratista prestaron servicios en régimen de subcontratación para el dueño de la obra, empresa o faena. | G9: No Cumplir con las obligaciones legales | H9: 4600029025 CC-101 | I9: Solicitar Informes Mensuales pagos previsionales | J9: SI | K9: 1 | L9: Planilla pago cotizaciones | M9: Administrador de contrato
E10: Art.183 - E | F10: Sin perjuicio de las obligaciones de la empresa principal, contratista y subcontratista respecto de sus propios trabajadores en virtud de lo dispuesto en el artículo 184, la empresa principal deberá adoptar las medidas necesarias para proteger eficazmente la vida y salud de todos los trabajadores que laboran en su obra, empresa o faena, cualquiera sea su dependencia, en conformidad a lo dispuesto en el artículo 66 bis de la ley Nº 16.744 y el artículo 3º del decreto supremo Nº 594, de 1999, del Ministerio de Salud. | G10: No contar con Programa personalizado | H10: 4600029025 CC-101 | I10: programa personalizado | J10: SI | K10: 1 | L10: Entrega mensual de cumplimiento programas personalizados | M10: Administrador de contrato
F11: b) Agréguense en el artículo 76 los siguientes incisos cuarto, quinto y final: "Sin perjuicio de lo dispuesto en los incisos precedentes, en caso de accidentes del trabajo fatales y graves, el empleador deberá informar inmediatamente a la Inspección del Trabajo y a la Secretaría Regional Ministerial de Salud que corresponda, acerca de la ocurrencia de cualquiera de estos hechos. Corresponderá a la Superintendencia de Seguridad Social impartir las instrucciones sobre la forma en que deberá cumplirse esta obligación. En estos mismos casos el empleador deberá suspender de forma inmediata las faenas afectadas y, de ser necesario, permitir a los trabajadores la evacuación del lugar de trabajo. La reanudación de faenas sólo podrá efectuarse cuando, previa fiscalización del organismo fiscalizador, se verifique que se han subsanado las deficiencias constatadas. | G11: No contar con procedimiento de investigación de incidentes | H11: 4600029025 CC-101 | I11: Difundir procedimiento de investigación de incidentes | J11: SI | K11: 1 | L11: Registro difusión Procedimiento investigación de incidentes | M11: Administrador de contrato
K12: 1
C13: ELABORÓ | F13: REVISÓ | G13: APROBÓ
C14: Claudio Rojas / Jefe Dpto. HSEC | F14: Mauricio Araya / Presidente CPHS | G14: José Maira / Administrador de Contrato
C15: FIRMA: FECHA : 18-02-2026 | F15: FIRMA: FECHA : 18-02-2026 | G15: FIRMA: FECHA : 18-02-2026

Sheet Ley 20.137
D1: Lista de Verificación de Cumplimiento Requisitos Legales y Otros Aplicable a Seguridad, Salud Ocupacional, Medioambiente y Comunidad Contrato 4600029025 - SKIC CC-101 | M1: Código | N1: ='Planilla Global - Cumplim (%)'!I2 -> MTRSE-00002
M2: Revisión | N2: 2
M3: Fecha | N3: 46272
A5: Nº Cuerpo Legal | B5: Fecha de Publicación | C5: Organismo | D5: Nombre del Cuerpo Legal | E5: Artículo | F5: Descripción del Contenido (Breve) | G5: Peligro o Aspecto | H5: Nº Contrato | I5: Modo de Cumplimiento | J5: ¿Cumple? | K5: Porcentaje Cumplimiento | L5: Evidencia del Cumplimiento | M5: Responsable | N5: Fecha de cumplimiento
A6: Ley 20.137 | B6: 39067 | C6: MINISTERIO DEL TRABAJO | D6: OTORGA PERMISO LABORAL POR MUERTE Y NACIMIENTO DE PARIENTES QUE INDICA | E6: Art.66 | F6: En el caso de muerte de un hijo así como en el de muerte del cónyuge, todo trabajador tendrá derecho a siete días corridos de permiso pagado, adicional al feriado anual, independientemente del tiempo de servicio. Igual permiso se aplicará por tres días hábiles en el caso de muerte de un hijo en período de gestación así como en el de muerte del padre o de la madre del trabajador. Estos permisos deberán hacerse efectivos a partir del día del respectivo fallecimiento. No obstante, tratándose de una defunción fetal, el permiso se hará efectivo desde el momento de acreditarse la muerte, con el respectivo certificado de defunción fetal. El trabajador al que se refiere el inciso primero gozará de fuero laboral por un mes, a contar del respectivo fallecimiento. Sin embargo, tratándose de trabajadores cuyos contratos de trabajo sean a plazo fijo o por obra o servicio determinado, el fuero los amparará sólo durante la vigencia del respectivo contrato si éste fuera menor a un mes, sin que se requiera solicitar su desafuero al término de cada uno de ellos. Los días de permiso consagrados en este artículo no podrán ser compensados en dinero.". | G6: No otorgar los Permisos que determina la Ley | H6: 4600029025 CC-101 | I6: Requisito establecido en RIOHS | J6: SI | K6: 1 | L6: Papeleta de autorización de Permiso | M6: Administrador de Contrato
K7: 1
C8: ELABORÓ | F8: REVISÓ | G8: APROBÓ
C9: Claudio Rojas / Jefe Dpto. HSEC | F9: Mauricio Araya / Presidente CPHS | G9: José Maira / Administrador de Contrato
C10: FIRMA: FECHA : 18-02-2026 | F10: FIRMA: FECHA : 18-02-2026 | G10: FIRMA: FECHA : 18-02-2026

Sheet Ley 20.348
D1: Lista de Verificación de Cumplimiento Requisitos Legales y Otros Aplicable a Seguridad, Salud Ocupacional, Medioambiente y Comunidad Contrato 4600029025 - SKIC CC-101 | M1: Código | N1: ='Planilla Global - Cumplim (%)'!I2 -> MTRSE-00002
M2: Revisión | N2: 2
M3: Fecha | N3: 46272
A5: Nº Cuerpo Legal | B5: Fecha de Publicación | C5: Organismo | D5: Nombre del Cuerpo Legal | F5: Descripción del Contenido (Breve) | G5: Peligro o Aspecto | H5: Nº Contrato | I5: Modo de Cumplimiento | J5: ¿Cumple? | K5: Porcentaje Cumplimiento | L5: Evidencia del Cumplimiento | M5: Responsable | N5: Fecha de cumplimiento
A6: Ley 20.348 | B6: 39983 | C6: MINISTERIO DEL TRABAJO | D6: Resguarda el Derecho a la Igualdad en las Remuneraciones. | E6: Art.62 BIS | F6: El empleador deberá dar cumplimiento al principio de igualdad de remuneraciones entre hombres y mujeres que presten un mismo trabajo, no siendo consideradas arbitrarias las diferencias objetivas en las remuneraciones que se funden, entre otras razones, en las capacidades, calificaciones, idoneidad, responsabilidad o productividad. Las denuncias que se realicen invocando el presente artículo, se sustanciarán en conformidad al Párrafo 6º del Capítulo II del Título I del Libro V de este Código, una vez que se encuentre concluido el procedimiento de reclamación previsto para estos efectos en el reglamento interno de la empresa.". | G6: Discriminar Sueldos por Genero | H6: 4600029025 CC-101 | I6: Requisito establecido en RIOHS | J6: SI | K6: 1 | L6: Determinación de Sueldos de Acuerdo al Cargo | M6: RRHH
F7: Intercalase, en el artículo 10 del decreto con fuerza de ley N° 29, del Ministerio de Hacienda, de 2005, que fijó el texto refundido, coordinado y sistematizado de la ley Nº18.834, Estatuto Administrativo, el siguiente inciso cuarto, nuevo: "En los empleos a contrata la asignación a un grado será de acuerdo con la importancia de la función que se desempeñe y con la capacidad, calificación e idoneidad personal de quien sirva dicho cargo y, en consecuencia, les corresponderá el sueldo y demás remuneraciones de ese grado, excluyendo toda discriminación que pueda alterar el principio de igualdad de trato entre hombres y mujeres." | G7: Discriminar Sueldos por Genero | H7: 4600029025 CC-101 | I7: Requisito establecido en RIOHS | J7: SI | K7: 1 | L7: Determinación de Sueldos de Acuerdo al Cargo | M7: RRHH
K8: 1
C9: ELABORÓ | F9: REVISÓ | G9: APROBÓ
C10: Claudio Rojas / Jefe Dpto. HSEC | F10: Mauricio Araya / Presidente CPHS | G10: José Maira / Administrador de Contrato
C11: FIRMA: FECHA : 18-02-2026 | F11: FIRMA: FECHA : 18-02-2026 | G11: FIRMA: FECHA : 18-02-2026

Sheet Ley 20.422
D1: Lista de Verificación de Cumplimiento Requisitos Legales y Otros Aplicable a Seguridad, Salud Ocupacional, Medioambiente y Comunidad Contrato 4600029025 - SKIC CC-101 | M1: Código | N1: ='Planilla Global - Cumplim (%)'!I2 -> MTRSE-00002
M2: Revisión | N2: 2
M3: Fecha | N3: 46272
A5: Nº Cuerpo Legal | B5: Fecha de Publicación | C5: Organismo | D5: Nombre del Cuerpo Legal | F5: Descripción del Contenido (Breve) | G5: Peligro o Aspecto | H5: Nº Contrato | I5: Modo de Cumplimiento | J5: ¿Cumple? | K5: Porcentaje Cumplimiento | L5: Evidencia del Cumplimiento | M5: Responsable | N5: Fecha de cumplimiento
A6: Ley 20.422 | B6: 40219 | C6: MINISTERIO DE PLANIFICACIÓN | D6: ESTABLECE NORMAS SOBRE IGUALDAD DE OPORTUNIDADES E INCLUSIÓN SOCIAL DE PERSONAS CON DISCAPACIDAD | E6: Art.7 | F6: Se entiende por igualdad de oportunidades para las personas con discapacidad, la ausencia de discriminación por razón de discapacidad, así como la adopción de medidas de acción positiva orientadas a evitar o compensar las desventajas de una persona con discapacidad para participar plenamente en la vida política, educacional, laboral, económica, cultural y social. | G6: Discriminación | H6: 4600029025 CC-101 | I6: Requisito establecido en RIOHS | J6: SI | K6: 1 | L6: Entrega RIOHS | M6: RRHH
K7: 1
C8: ELABORÓ | F8: REVISÓ | G8: APROBÓ
C9: Claudio Rojas / Jefe Dpto. HSEC | F9: Mauricio Araya / Presidente CPHS | G9: José Maira / Administrador de Contrato
C10: FIRMA: FECHA : 18-02-2026 | F10: FIRMA: FECHA : 18-02-2026 | G10: FIRMA: FECHA : 18-02-2026

Sheet LEY 20.508
D1: Lista de Verificación de Cumplimiento Requisitos Legales y Otros Aplicable a Seguridad, Salud Ocupacional, Medioambiente y Comunidad Contrato 4600029025 - SKIC CC-101 | M1: Código | N1: ='Planilla Global - Cumplim (%)'!I2 -> MTRSE-00002
M2: Revisión | N2: 2
M3: Fecha | N3: 46272
A5: Nº Cuerpo Legal | B5: Fecha de Publicación | C5: Organismo | D5: Nombre del Cuerpo Legal | F5: Descripción del Contenido (Breve) | G5: Peligro o Aspecto | H5: Nº Contrato | I5: Modo de Cumplimiento | J5: ¿Cumple? | K5: Porcentaje Cumplimiento | L5: Evidencia del Cumplimiento | M5: Responsable | N5: Fecha de cumplimiento
A6: Ley 20.508 | B6: 40651 | C6: Ministerio de transportes y telecomunicaciones | D6: Con la finalidad de exigir cinturones de seguridad y artefactos técnicos limitadores de velocidad en los buses de transporte público | E6: Art. Único | F6: Los buses que presten servicios de transporte interurbano público o privado de pasajeros deberán estar equipados con cinturón de seguridad en todos sus asientos. Su uso será obligatorio para el pasajero, salvo que dicho elemento no funcione, en cuyo caso la infracción a esta obligación será imputable al propietario del vehículo. Esta obligación será exigible a los buses que presten servicios de transporte público interurbano de pasajeros cuyo año de fabricación sea 2008 en adelante. En los buses de transporte privado interurbano de pasajeros dichas exigencias serán aplicables en vehículos cuyo año de fabricación sea 2012 o posterior. | G6: Conducir o arrendar un vehículo que no cumpla con lo indicado en el artículo | H6: 4600029025 CC-101 | I6: Check list pre-uso de buses | J6: SI | K6: 1 | L6: Terreno | M6: Administrador de Contrato
K7: 1
C8: ELABORÓ | F8: REVISÓ | G8: APROBÓ
C9: Claudio Rojas / Jefe Dpto. HSEC | F9: Mauricio Araya / Presidente CPHS | G9: José Maira / Administrador de Contrato
C10: FIRMA: FECHA : 18-02-2026 | F10: FIRMA: FECHA : 18-02-2026 | G10: FIRMA: FECHA : 18-02-2026

Sheet Ley 20.545
D1: Lista de Verificación de Cumplimiento Requisitos Legales y Otros Aplicable a Seguridad, Salud Ocupacional, Medioambiente y Comunidad Contrato 4600029025 - SKIC CC-101 | M1: Código | N1: ='Planilla Global - Cumplim (%)'!I2 -> MTRSE-00002
M2: Revisión | N2: 2
M3: Fecha | N3: 46272
A5: Nº Cuerpo Legal | B5: Fecha de Publicación | C5: Organismo | D5: Nombre del Cuerpo Legal | F5: Descripción del Contenido (Breve) | G5: Peligro o Aspecto | H5: Nº Contrato | I5: Modo de Cumplimiento | J5: ¿Cumple? | K5: Porcentaje Cumplimiento | L5: Evidencia del Cumplimiento | M5: Responsable | N5: Fecha de cumplimiento
A6: Ley 20.545 | B6: 40833 | C6: MINISTERIO DEL TRABAJO Y PREVISIÓN SOCIAL; SUBSECRETARÍA DEL TRABAJO | D6: MODIFICA LAS NORMAS SOBRE PROTECCIÓN A LA MATERNIDAD E INCORPORA EL PERMISO POSTNATAL PARENTAL | E6: Art.195 | F6: Las trabajadoras tendrán derecho a un descanso de maternidad de seis semanas antes del parto y doce semanas después de él. El padre tendrá derecho a un permiso pagado de cinco días en caso de nacimiento de un hijo, el que podrá utilizar a su elección desde el momento del parto, y en este caso será de forma continua, excluyendo el descanso semanal, o distribuirlo dentro del primer mes desde la fecha del nacimiento. Este permiso también se otorgará al padre que se encuentre en proceso de adopción, y se contará a partir de la notificación de la resolución que otorgue el cuidado personal o acoja la adopción del menor, en conformidad a los artículos 19 y 24 de la ley Nº 19.620. Este derecho es irrenunciable. Si la madre muriera en el parto o durante el período de permiso posterior a éste, dicho permiso o el resto de él que sea destinado al cuidado del hijo corresponderá al padre o a quien le fuere otorgada la custodia del menor, quien gozará del fuero establecido en el artículo 201 de este Código y tendrá derecho al subsidio a que se refiere el artículo 198. El padre que sea privado por sentencia judicial del cuidado personal del menor perderá el derecho a fuero y subsidio establecidos en el inciso anterior. Los derechos referidos en el inciso primero no podrán renunciarse y durante los períodos de descanso queda prohibido el trabajo de las mujeres embarazadas y puérperas. Asimismo, no obstante cualquier estipulación en contrario, deberán conservárseles sus empleos o puestos durante dichos períodos, incluido el período establecido en el artículo 197 bis.". | G6: Incumplir la legislación Vigente | H6: 4600029025 CC-101 | I6: Incorporado de RIOHS | J6: SI | K6: 1 | L6: Papeleta de recepción de RIOHS | M6: RRHH
E7: Art.197bis | F7: Las trabajadoras tendrán derecho a un permiso postnatal parental de doce semanas a continuación del período postnatal, durante el cual recibirán un subsidio cuya base de cálculo será la misma del subsidio por descanso de maternidad a que se refiere el inciso primero del artículo 195. | G7: Incumplir la legislación Vigente | H7: 4600029025 CC-101 | I7: Incorporado de RIOHS | J7: SI | K7: 1 | L7: Papeleta de recepción de RIOHS | M7: RRHH
E8: Art.201 | F8: Durante el período de embarazo y hasta un año después de expirado el descanso de maternidad, excluido el permiso postnatal parental establecido en el artículo 197 bis, la trabajadora gozará de fuero laboral y estará sujeta a lo dispuesto en el artículo 174. En caso de que el padre haga uso del permiso postnatal parental del artículo 197 bis también gozará de fuero laboral, por un período equivalente al doble de la duración de su permiso, a contar de los diez días anteriores al comienzo del uso del mismo. Con todo, este fuero del padre no podrá exceder de tres meses. | G8: Incumplir la legislación Vigente | H8: 4600029025 CC-101 | I8: Incorporado de RIOHS | J8: SI | K8: 1 | L8: Papeleta de recepción de RIOHS
K9: 1
C10: ELABORÓ | F10: REVISÓ | G10: APROBÓ
C11: Claudio Rojas / Jefe Dpto. HSEC | F11: #VALUE! | G11: José Maira / Administrador de Contrato
C12: FIRMA: FECHA : 18-02-2026 | F12: FIRMA: FECHA : 18-02-2026 | G12: FIRMA: FECHA : 18-02-2026

Sheet Ley 20.580
D1: Lista de Verificación de Cumplimiento Requisitos Legales y Otros Aplicable a Seguridad, Salud Ocupacional, Medioambiente y Comunidad Contrato 4600029025 - SKIC CC-101 | M1: Código | N1: ='Planilla Global - Cumplim (%)'!I2 -> MTRSE-00002
M2: Revisión | N2: 2
M3: Fecha | N3: 46272
A5: Nº Cuerpo Legal | B5: Fecha de Publicación | C5: Organismo | D5: Nombre del Cuerpo Legal | E5: Artículo | F5: Descripción del Contenido (Breve) | G5: Peligro o Aspecto | H5: Nº Contrato | I5: Modo de Cumplimiento | J5: ¿Cumple? | K5: Porcentaje Cumplimiento | L5: Evidencia del Cumplimiento | M5: Responsable | N5: Fecha de cumplimiento
A6: Ley 20.580 | B6: 40983 | C6: MINISTERIO DE TRANSPORTES Y TELECOMUNICACIONES; SUBSECRETARÍA DE TRANSPORTES | D6: MODIFICA LEY N° 18.290, AUMENTANDO LAS SANCIONES POR MANEJO EN ESTADO DE EBRIEDAD, BAJO LA INFLUENCIA DE SUSTANCIAS ESTUPEFACIENTES O SICOTRÓPICAS, Y BAJO LA INFLUENCIA DEL ALCOHOL | E6: Art.193 | F6: El que conduzca, opere o desempeñe las funciones bajo la influencia del alcohol, será sancionado con multa de una a cinco unidades tributarias mensuales y la suspensión de la licencia de conducir por tres meses. Si a consecuencia de esa conducción, operación o desempeño, se causaren daños materiales o lesiones leves, será sancionado con una multa de una a cinco unidades tributarias mensuales y la suspensión de la licencia de conducir por seis meses. Se reputarán leves, para estos efectos, todas las lesiones que produzcan al ofendido enfermedad o incapacidad por un tiempo no mayor a siete días | G6: Conducir bajo la influencia alcohol/ sustancias psicotrópicas | H6: 4600029025 CC-101 | I6: Test de alcohol y droga aleatorio en faena Inclusión de Ley en el RIOHS | J6: SI | K6: 1 | L6: Entrega RIOHS Registro de difusión de plan de prevención y control consumo de alcohol y droga Registro de Registros de tomas de test aleatorio de alcohol y droga en faenas | M6: Administrador Contrato
K7: 1
C8: ELABORÓ | F8: REVISÓ | G8: APROBÓ
C9: Claudio Rojas / Jefe Dpto. HSEC | F9: Mauricio Araya / Presidente CPHS | G9: José Maira / Administrador de Contrato
C10: FIRMA: FECHA : 18-02-2026 | F10: FIRMA: FECHA : 18-02-2026 | G10: FIRMA: FECHA : 18-02-2026

Sheet Ley 20.607
D1: Lista de Verificación de Cumplimiento Requisitos Legales y Otros Aplicable a Seguridad, Salud Ocupacional, Medioambiente y Comunidad Contrato 4600029025 - SKIC CC-101 | M1: Código | N1: ='Planilla Global - Cumplim (%)'!I2 -> MTRSE-00002
M2: Revisión | N2: 2
M3: Fecha | N3: 46272
A5: Nº Cuerpo Legal | B5: Fecha de Publicación | C5: Organismo | D5: Nombre del Cuerpo Legal | F5: Descripción del Contenido (Breve) | G5: Peligro o Aspecto | H5: Nº Contrato | I5: Modo de Cumplimiento | J5: ¿Cumple? | K5: Porcentaje Cumplimiento | L5: Evidencia del Cumplimiento | M5: Responsable | N5: Fecha de cumplimiento
A6: Ley 20.607 | B6: 41121 | C6: MINISTERIO DEL TRABAJO Y PREVISIÓN SOCIAL; SUBSECRETARÍA DEL TRABAJO | D6: Modifica el Código del trabajo, sancionando las prácticas de acoso laboral. | E6: Art.1 | F6: Introdúcense las siguientes modificaciones en el Código del Trabajo: 1) "Asimismo, es contrario a la dignidad de la persona el acoso laboral, entendiéndose por tal toda conducta que constituya agresión u hostigamiento reiterados, ejercida por el empleador o por uno o más trabajadores, en contra de otro u otros trabajadores, por cualquier medio, y que tenga como resultado para el o los afectados su menoscabo, maltrato o humillación, o bien que amenace o perjudique su situación laboral o sus oportunidades en el empleo.". | G6: mobbing | H6: 4600029025 CC-101 | I6: Incorporado en el RIOHS | J6: SI | K6: 1 | L6: Papeleta de recepción RIOHS. Investigación en caso de presentarse la situación | M6: Administrador de Contrato
K7: 1
C8: ELABORÓ | F8: REVISÓ | G8: APROBÓ
C9: Claudio Rojas / Jefe Dpto. HSEC | F9: Mauricio Araya / Presidente CPHS | G9: José Maira / Administrador de Contrato
C10: FIRMA: FECHA : 18-02-2026 | F10: FIRMA: FECHA : 18-02-2026 | G10: FIRMA: FECHA : 18-02-2026

Sheet Ley 20.609
D1: Lista de Verificación de Cumplimiento Requisitos Legales y Otros Aplicable a Seguridad, Salud Ocupacional, Medioambiente y Comunidad Contrato 4600029025 - SKIC CC-101 | M1: Código | N1: ='Planilla Global - Cumplim (%)'!I2 -> MTRSE-00002
M2: Revisión | N2: 2
M3: Fecha | N3: 46272
A5: Nº Cuerpo Legal | B5: Fecha de Publicación | C5: Organismo | D5: Nombre del Cuerpo Legal | E5: Artículo | F5: Descripción del Contenido (Breve) | G5: Peligro o Aspecto | H5: Nº Contrato | I5: Modo de Cumplimiento | J5: ¿Cumple? | K5: Porcentaje Cumplimiento | L5: Evidencia del Cumplimiento | M5: Responsable | N5: Fecha de cumplimiento
A6: Ley 20.609 | B6: 41114 | C6: MINISTERIO SECRETARIA GENERAL DE GOBIERNO | D6: Establece medidas contra la discriminación | E6: Art.2 | F6: Definición de discriminación arbitraria. Para los efectos de esta ley, se entiende por discriminación arbitraria toda distinción, exclusión o restricción que carezca de justificación razonable, efectuada por agentes del Estado o particulares, y que cause privación, perturbación o amenaza en el ejercicio legítimo de los derechos fundamentales establecidos en la Constitución Política de la República o en los tratados internacionales sobre derechos humanos ratificados por Chile y que se encuentren vigentes, en particular cuando se funden en motivos tales como la raza o etnia, la nacionalidad, la situación socioeconómica, el idioma, la ideología u opinión política, la religión o creencia, la sindicación o participación en organizaciones gremiales o la falta de ellas, el sexo, la orientación sexual, la identidad de género, el estado civil, la edad, la filiación, la apariencia personal y la enfermedad o discapacidad. Las categorías a que se refiere el inciso anterior no podrán invocarse, en ningún caso, para justificar, validar o exculpar situaciones o conductas contrarias a las leyes o al orden público. | G6: Se presenten reclamos por discriminación | H6: 4600029025 CC-101 | I6: Requisito incorporado en RIOHS | J6: SI | K6: 1 | L6: Papeleta de recepción RIOHS. Investigación en caso de presentarse la situación | M6: Administrador de Contrato
E7: Art.3 | F7: Acción de no discriminación arbitraria. Los directamente afectados por una acción u omisión que importe discriminación arbitraria podrán interponer la acción de no discriminación arbitraria, a su elección, ante el juez de letras de su domicilio o ante el del domicilio del responsable de dicha acción u omisión. | G7: Se presenten reclamos por discriminación | H7: 4600029025 CC-101 | I7: Requisito incorporado en RIOHS | J7: SI | K7: 1 | L7: Papeleta de recepción RIOHS. Investigación en caso de presentarse la situación | M7: Administrador de Contrato
K8: 1
C9: ELABORÓ | F9: REVISÓ | G9: APROBÓ
C10: Claudio Rojas / Jefe Dpto. HSEC | F10: Mauricio Araya / Presidente CPHS | G10: José Maira / Administrador de Contrato
C11: FIRMA: FECHA : 18-02-2026 | F11: FIRMA: FECHA : 18-02-2026 | G11: FIRMA: FECHA : 18-02-2026

Sheet Ley 20.611
D1: Lista de Verificación de Cumplimiento Requisitos Legales y Otros Aplicable a Seguridad, Salud Ocupacional, Medioambiente y Comunidad Contrato 4600029025 - SKIC CC-101 | M1: Código | N1: ='Planilla Global - Cumplim (%)'!I2 -> MTRSE-00002
M2: Revisión | N2: 2
M3: Fecha | N3: 46272
A5: Nº Cuerpo Legal | B5: Fecha de Publicación | C5: Organismo | D5: Nombre del Cuerpo Legal | E5: Artículo | F5: Descripción del Contenido (Breve) | G5: Peligro o Aspecto | H5: Nº Contrato | I5: Modo de Cumplimiento | J5: ¿Cumple? | K5: Porcentaje Cumplimiento | L5: Evidencia del Cumplimiento | M5: Responsable | N5: Fecha de cumplimiento
A6: Ley 20.611 | B6: 41129 | C6: MINISTERIO DEL TRABAJO Y PREVISIÓN SOCIAL; SUBSECRETARÍA DEL TRABAJO | D6: MODIFICA EL CÓDIGO DEL TRABAJO EN MATERIA DE PROTECCIÓN DE LAS REMUNERACIONES | E6: Art.54bis | F6: Las remuneraciones devengadas se incorporan al patrimonio del trabajador, teniéndose por no escrita cualquier cláusula que implique su devolución, reintegro o compensación por parte del trabajador al empleador, ante la ocurrencia de hechos posteriores a la oportunidad en que la remuneración se devengó, salvo que dichos hechos posteriores se originen en el incumplimiento por parte del trabajador de las obligaciones contenidas en su contrato de trabajo. | G6: Incumplimiento de la legislación vigente | H6: 4600029025 CC-101 | I6: Incorporado en RIOHS | J6: Liquidación de sueldo | K6: 1 | L6: Papeleta de recepción de RIOHS | M6: RRHH
E7: Art.55 | F7: En caso que la remuneración del trabajador se componga total o parcialmente de comisiones e independientemente de las condiciones de pago que la empresa pacte con el cliente, aquéllas se entenderán devengadas y deberán ser liquidadas y pagadas conjuntamente con las demás remuneraciones ordinarias del período en que se efectuaron las operaciones u ocurrieron los hechos que les dieron origen, salvo que, por razones técnicas ello no sea posible, caso en el cual deberán ser liquidadas y pagadas conjuntamente con las remuneraciones del mes siguiente. La cláusula que difiera el pago de comisiones al trabajador, infringiendo los límites establecidos en este artículo, se tendrá por no escrita.". | G7: Incumplimiento de la legislación vigente | H7: 4600029025 CC-101 | I7: Incorporado en RIOHS | J7: Liquidación de sueldo | K7: 1 | L7: Papeleta de recepción de RIOHS | M7: RRHH
E8: Art.1 | F8: Artículos transitorios Artículo 1º.- Con excepción de lo establecido en los incisos segundo y final del artículo 54 bis que se incorpora al Código del Trabajo por esta ley, los contratos de trabajo celebrados con anterioridad a la vigencia de la presente ley deberán ajustarse a sus disposiciones, en lo relativo a las condiciones y plazos para el pago de las comisiones, en el término fatal de seis meses, a contar de su publicación en el Diario Oficial. Corresponderá al empleador efectuar dichos ajustes, sin que pueda realizar otras modificaciones que signifiquen menoscabo para el trabajador, tal como una disminución de la comisión. Para estos efectos, se entenderá que hay una disminución de la comisión cuando, una vez efectuado el ajuste, el trabajador percibiere una menor remuneración variable que la que habría percibido por las mismas operaciones que le dieron origen, antes del ajuste. | G8: Incumplimiento de la legislación vigente | H8: 4600029025 CC-101 | I8: Incorporado en RIOHS | J8: Anexo de trabajo | K8: 1 | L8: Papeleta de recepción de RIOHS | M8: RRHH
E9: Art.2 | F9: Artículo 2º.- Las condiciones y plazos previstos en esta ley para el pago de comisiones, no modificarán aquellas condiciones y plazos que se hubieren pactado en un instrumento colectivo vigente a la fecha de publicación de esta ley. Con todo, si dicho instrumento se modificare en forma anticipada, el nuevo instrumento deberá considerar el referido ajuste.". | G9: Incumplimiento de la legislación vigente | H9: 4600029025 CC-101 | I9: Incorporado en RIOHS | J9: Anexo de trabajo | K9: 1 | L9: Papeleta de recepción de RIOHS | M9: RRHH
K10: 1
C11: ELABORÓ | F11: REVISÓ | G11: APROBÓ
C12: Claudio Rojas / Jefe Dpto. HSEC | F12: Mauricio Araya / Presidente CPHS | G12: José Maira / Administrador de Contrato
C13: FIRMA: FECHA : 18-02-2026 | F13: FIRMA: FECHA : 18-02-2026 | G13: FIRMA: FECHA : 18-02-2026

Sheet Ley 20.613
D1: Lista de Verificación de Cumplimiento Requisitos Legales y Otros Aplicable a Seguridad, Salud Ocupacional, Medioambiente y Comunidad Contrato 4600029025 - SKIC CC-101 | M1: Código | N1: ='Planilla Global - Cumplim (%)'!I2 -> MTRSE-00002
M2: Revisión | N2: 2
M3: Fecha | N3: 46272
A5: Nº Cuerpo Legal | B5: Fecha de Publicación | C5: Organismo | D5: Nombre del Cuerpo Legal | E5: Artículo | F5: Descripción del Contenido (Breve) | G5: Peligro o Aspecto | H5: Nº Contrato | I5: Modo de Cumplimiento | J5: ¿Cumple? | K5: Porcentaje Cumplimiento | L5: Evidencia del Cumplimiento | M5: Responsable | N5: Fecha de cumplimiento
A6: Ley 20.613 | B6: 41129 | C6: MINISTERIO DEL TRABAJO Y PREVISIÓN SOCIAL; SUBSECRETARÍA DEL TRABAJO | D6: Modifica el Código del Trabajo, incluyendo la remuneración denominada "Semana Corrida" dentro de la base de cálculo del feriado de los trabajadores | E6: Art. Único | F6: Incorpórase en el artículo 71 del Libro I del Código del Trabajo, cuyo texto refundido, coordinado y sistematizado fue fijado por el decreto con fuerza de ley Nº 1, de 2003, del Ministerio del Trabajo y Previsión Social, el siguiente inciso quinto, nuevo, pasando su actual inciso quinto a ser inciso final: "Asimismo, la remuneración íntegra durante el feriado deberá incluir la remuneración establecida en el inciso primero del artículo 45, según corresponda.".". | G6: Incumplimiento de la legislación vigente | H6: 4600029025 CC-101 | I6: Liquidaciones de sueldo | J6: SI | K6: 1 | L6: Liquidaciones de sueldo firmadas | M6: RRHH
K7: 1
C8: ELABORÓ | F8: REVISÓ | G8: APROBÓ
C9: Claudio Rojas / Jefe Dpto. HSEC | F9: Mauricio Araya / Presidente CPHS | G9: José Maira / Administrador de Contrato
C10: FIRMA: FECHA : 18-02-2026 | F10: FIRMA: FECHA : 18-02-2026 | G10: FIRMA: FECHA : 18-02-2026

Sheet Ley 20.684
D1: Lista de Verificación de Cumplimiento Requisitos Legales y Otros Aplicable a Seguridad, Salud Ocupacional, Medioambiente y Comunidad Contrato 4600029025 - SKIC CC-101 | M1: Código | N1: ='Planilla Global - Cumplim (%)'!I2 -> MTRSE-00002
M2: Revisión | N2: 2
M3: Fecha | N3: 46272
A5: Nº Cuerpo Legal | B5: Fecha de Publicación | C5: Organismo | D5: Nombre del Cuerpo Legal | E5: Artículo | F5: Descripción del Contenido (Breve) | G5: Peligro o Aspecto | H5: Nº Contrato | I5: Modo de Cumplimiento | J5: ¿Cumple? | K5: Porcentaje Cumplimiento | L5: Evidencia del Cumplimiento | M5: Responsable | N5: Fecha de cumplimiento
A6: Ley 20.684 | B6: 41509 | C6: MINISTERIO DEL TRABAJO Y PREVISIÓN SOCIAL; SUBSECRETARÍA DEL TRABAJO | D6: ESTABLECE PLAZO PARA OTORGAMIENTO DEL FINIQUITO DEL CONTRATO DE TRABAJO | E6: Artículo Único | F6: Introdúcense las siguientes modificaciones en el Código del Trabajo, cuyo texto refundido, coordinado y sistematizado fue fijado por el decreto con fuerza de ley Nº 1, de 2003, del Ministerio del Trabajo y Previsión Social: El finiquito deberá ser otorgado por el empleador y puesto su pago a disposición del trabajador dentro de diez días hábiles, contados desde la separación del trabajador. Las partes podrán pactar el pago en cuotas de conformidad con los artículos 63 bis y 169.".". | G6: Incumplimiento Legal | H6: 4600029025 CC-101 | I6: Finiquito de trabajo | J6: SI | K6: 1 | L6: Registro Pago de Finiquito ante Notario | M6: RRHH
K7: 1
C8: ELABORÓ | F8: REVISÓ | G8: APROBÓ
C9: Claudio Rojas / Jefe Dpto. HSEC | F9: Mauricio Araya / Presidente CPHS | G9: José Maira / Administrador de Contrato
C10: FIRMA: FECHA : 18-02-2026 | F10: FIRMA: FECHA : 18-02-2026 | G10: FIRMA: FECHA : 18-02-2026

Sheet Ley 20.764
D1: Lista de Verificación de Cumplimiento Requisitos Legales y Otros Aplicable a Seguridad, Salud Ocupacional, Medioambiente y Comunidad Contrato 4600029025 - SKIC CC-101 | M1: Código | N1: ='Planilla Global - Cumplim (%)'!I2 -> MTRSE-00002
M2: Revisión | N2: 2
M3: Fecha | N3: 46272
A5: Nº Cuerpo Legal | B5: Fecha de Publicación | C5: Organismo | D5: Nombre del Cuerpo Legal | E5: Artículo | F5: Descripción del Contenido (Breve) | G5: Peligro o Aspecto | H5: Nº Contrato | I5: Modo de Cumplimiento | J5: ¿Cumple? | K5: Porcentaje Cumplimiento | L5: Evidencia del Cumplimiento | M5: Responsable | N5: Fecha de cumplimiento
A6: Ley 20.764 | B6: 41838 | C6: MINISTERIO DEL TRABAJO Y PREVISIÓN SOCIAL | D6: Modifica el código del trabajo en materia de protección a la maternidad, la paternidad y la vida familiar y estable un permiso por matrimonio del trabajador | E6: Art.207bis | F6: En el caso de contraer matrimonio, todo trabajador tendrá derecho a cinco días hábiles continuos de permiso pagado, adicional al feriado anual, independientemente del tiempo de servicio. Este permiso se podrá utilizar, a elección del trabajador, en el día del matrimonio y en los días inmediatamente anteriores o posteriores al de su celebración. El trabajador deberá dar aviso a su empleador con treinta días de anticipación y presentar dentro de los treinta días siguientes a la celebración el respectivo certificado de matrimonio del Servicio de Registro Civil e Identificación.". | G6: No otorgar el permiso indicado | H6: 4600029025 CC-101 | I6: Papeleta de permiso | J6: SI | K6: 1 | L6: Papeleta firmada por el trabajador | M6: Administrador Contrato
K7: =IFERROR(AVERAGE(K6:K6),"0") -> 1
C8: ELABORÓ | F8: REVISÓ | G8: APROBÓ
C9: Claudio Rojas / Jefe Dpto. HSEC | F9: Mauricio Araya / Presidente CPHS | G9: José Maira / Administrador de Contrato
C10: FIRMA: FECHA : 18-02-2026 | F10: FIRMA: FECHA : 18-02-2026 | G10: FIRMA: FECHA : 18-02-2026

Sheet Ley  20.769
D1: Lista de Verificación de Cumplimiento Requisitos Legales y Otros Aplicable a Seguridad, Salud Ocupacional, Medioambiente y Comunidad Contrato 4600029025 - SKIC CC-101 | M1: Código | N1: ='Planilla Global - Cumplim (%)'!I2 -> MTRSE-00002
M2: Revisión | N2: 2
M3: Fecha | N3: 46272
A5: Nº Cuerpo Legal | B5: Fecha de Publicación | C5: Organismo | D5: Nombre del Cuerpo Legal | E5: Artículo | F5: Descripción del Contenido (Breve) | G5: Peligro o Aspecto | H5: Nº Contrato | I5: Modo de Cumplimiento | J5: ¿Cumple? | K5: % Cumplimiento | L5: Evidencia del Cumplimiento | M5: Responsable | N5: Fecha de cumplimiento
A6: Ley 20.769 | B6: 41902 | C6: MINISTERIO DEL TRABAJO Y PREVISIÓN SOCIAL | D6: Modifica el Código del Trabajo otorgando permiso a trabajadoras y trabajadores para efectuarse exámenes de mamografía y de próstata, respectivamente. | E6: Art.66bis | F6: Las trabajadoras y los trabajadores, cuyos contratos de trabajo sean por un plazo superior a treinta días, tendrán derecho a medio día de permiso, una vez al año durante la vigencia de la relación laboral, para someterse a los exámenes de mamografía y próstata, respectivamente, pudiendo incluir otras prestaciones de medicina preventiva, tales como el examen de papanicolau, en las instituciones de salud públicas o privadas que corresponda. En el caso de los contratos celebrados por un plazo fijo, o para la realización de una obra o faena determinada, este derecho podrá ejercerse a partir de los treinta días de celebrado el contrato de trabajo, y en cualquier momento durante la vigencia de éste | G6: No otorgar el permiso | H6: 4600029025 CC-101 | I6: Citación a médico | J6: SI | K6: 1 | L6: Papeleta de permiso que indique el motivo | M6: Administrador Contrato
K7: 1
C8: ELABORÓ | F8: REVISÓ | G8: APROBÓ
C9: Claudio Rojas / Jefe Dpto. HSEC | F9: Mauricio Araya / Presidente CPHS | G9: José Maira / Administrador de Contrato
C10: FIRMA: FECHA : 18-02-2026 | F10: FIRMA: FECHA : 18-02-2026 | G10: FIRMA: FECHA : 18-02-2026

Sheet Ley 20.770
D1: Lista de Verificación de Cumplimiento Requisitos Legales y Otros Aplicable a Seguridad, Salud Ocupacional, Medioambiente y Comunidad Contrato 4600029025 - SKIC CC-101 | M1: Código | N1: ='Planilla Global - Cumplim (%)'!I2 -> MTRSE-00002
M2: Revisión | N2: 2
M3: Fecha | N3: 46272
A5: Nº Cuerpo Legal | B5: Fecha de Publicación | C5: Organismo | D5: Nombre del Cuerpo Legal | E5: Artículo | F5: Descripción del Contenido (Breve) | G5: Peligro o Aspecto | H5: Nº Contrato | I5: Modo de Cumplimiento | J5: ¿Cumple? | K5: Porcentaje Cumplimiento | L5: Evidencia del Cumplimiento | M5: Responsable | N5: Fecha de cumplimiento
A6: Ley 20.770 | B6: 41898 | C6: MINISTERIO DE TRANSPORTES Y TELECOMUNICACIONES; SUBSECRETARÍA DE TRANSPORTES | D6: MODIFICA LA LEY DEL TRÁNSITO, EN LO QUE SE REFIERE AL DELITO DE MANEJO EN ESTADO DE EBRIEDAD, CAUSANDO LESIONES GRAVES, GRAVÍSIMAS O, CON RESULTADO DE MUERTE | E6: Art.195 | F6: El incumplimiento de la obligación de dar cuenta a la autoridad de todo accidente en que sólo se produzcan daños, señalada en el artículo 168, será sancionado con multa de tres a siete unidades tributarias mensuales y con la suspensión de la licencia hasta por un mes. El incumplimiento de la obligación de detener la marcha, prestar la ayuda posible y dar cuenta a la autoridad de todo accidente en que se produzcan lesiones, señalada en el artículo 176, se sancionará con la pena de presidio menor en su grado medio, inhabilidad perpetua para conducir vehículos de tracción mecánica y multa de siete a diez unidades tributarias mensuales. Si en el caso previsto en el inciso anterior las lesiones producidas fuesen de las señaladas en el número 1º del artículo 397 del Código Penal o se produjese la muerte de alguna persona, el responsable será castigado con la pena de presidio menor en su grado máximo, inhabilidad perpetua para conducir vehículos de tracción mecánica, multa de once a veinte unidades tributarias mensuales y con el comiso del vehículo con que se ha cometido el delito, sin perjuicio de los derechos del tercero propietario, que podrá hacer valer conforme a las reglas generales del Código Procesal Penal. Para los efectos de determinar la pena prevista en este inciso, será aplicable lo dispuesto en los artículos 196 bis y 196 ter de esta ley. Las penas previstas en este artículo se impondrán al conductor conjuntamente con las que le correspondan por la responsabilidad que le pueda caber en el respectivo delito o cuasidelito, de conformidad con lo dispuesto en el artículo 74 del Código Penal". | G6: Conducción de vehículos en estado de Ebriedad | H6: 4600029025 CC-101 | I6: Difusión al personal sobre este requisito. | J6: SI | K6: 1 | L6: Registro de Comunicación | M6: RRHH
E7: Art.195 bis | F7: La negativa injustificada de un conductor a someterse a las pruebas respiratorias u otros exámenes científicos destinados a establecer la presencia de alcohol o de sustancias estupefacientes o psicotrópicas en el cuerpo, previstos en el artículo 182, será sancionada con multa de tres a diez unidades tributarias mensuales y con la suspensión de su licencia hasta por un mes. En caso de accidentes que produzcan lesiones de las comprendidas en el número 1º del artículo 397 del Código Penal o la muerte de alguna persona, la negativa injustificada del conductor que hubiese intervenido en ellos a someterse a las pruebas respiratorias evidenciales o a los exámenes científicos señalados en el artículo 183 de esta ley para determinar la dosificación de alcohol en la sangre o la presencia de drogas estupefacientes o sicotrópicas, o la realización de cualquier maniobra que altere sus resultados, o la dilación de su práctica con ese mismo efecto, serán castigadas con la pena de presidio menor en su grado máximo, multa de once a veinte unidades tributarias mensuales, inhabilidad perpetua para conducir vehículos de tracción mecánica y comiso del vehículo con que se ha cometido el delito, sin perjuicio de los derechos del tercero propietario, que podrá hacer valer conforme a las reglas generales del Código Procesal Penal. Para los efectos de determinar la pena prevista en este inciso, será aplicable lo dispuesto en los artículos 196 bis y 196 ter de esta ley. La pena prevista en el inciso anterior se impondrá al conductor conjuntamente con la que le corresponda por la responsabilidad que le pueda caber en el respectivo delito o cuasidelito, de conformidad con lo dispuesto en el artículo 74 del Código Penal.". | G7: Conducción de vehículos en estado de Ebriedad | H7: 4600029025 CC-101 | I7: Difusión al personal sobre este requisito. | J7: SI | K7: 1 | L7: Registro de Comunicación | M7: RRHH
K8: 1
C9: ELABORÓ | F9: REVISÓ | G9: APROBÓ
C10: Claudio Rojas / Jefe Dpto. HSEC | F10: Mauricio Araya / Presidente CPHS | G10: José Maira / Administrador de Contrato
C11: FIRMA: FECHA : 18-02-2026 | F11: FIRMA: FECHA : 18-02-2026 | G11: FIRMA: FECHA : 18-02-2026

Sheet Ley 20.879
D1: Lista de Verificación de Cumplimiento Requisitos Legales y Otros Aplicable a Seguridad, Salud Ocupacional, Medioambiente y Comunidad Contrato 4600029025 - SKIC CC-101 | M1: Código | N1: ='Planilla Global - Cumplim (%)'!I2 -> MTRSE-00002
M2: Revisión | N2: 2
M3: Fecha | N3: 46272
A5: Nº Cuerpo Legal | B5: Fecha de Publicación | C5: Organismo | D5: Nombre del Cuerpo Legal | E5: Artículo | F5: Descripción del Contenido (Breve) | G5: Peligro o Aspecto | H5: Nº Contrato | I5: Modo de Cumplimiento | J5: ¿Cumple? | K5: Porcentaje Cumplimiento | L5: Evidencia del Cumplimiento | M5: Responsable | N5: Fecha de cumplimiento
A6: Ley 20.879 | B6: 42333 | C6: MINISTERIO DE TRANSPORTE | D6: SANCIONA EL TRANSPORTE DE DESECHOS HACIA VERTEDEROS CLANDESTINOS | E6: Art. Único | F6: Introduce Art 192 bis: Sobre sanciones a quienes encarguen o realicen traslado o depósito de basuras en vía pública, vertederos clandestinos o ilegales, sitios eriazos o bienes nacionales de uso público. Las municipalidades deberán dictar ordenanzas y regulaciones para el transporte y disposición de residuos o desechos. Art 192 ter: Transporte y retiro de escombros en contenedores o sacos se realizará cubriendo la carga de forma que se impida el esparcimiento. | G6: Generación de Residuos Contaminación Suelo | H6: 4600029025 CC-101 | I6: Todo transporte y disposición final de residuos deberá ser realizado por empresas autorizadas para dicha actividad. Procedimiento Manejo de Residuos | J6: SI | K6: 1 | L6: Certificado de disposición final de residuos. Resoluciónes del transportista y de la disposición final. Registro difusión Procedimiento Manejo de Residuos | M6: Administrador Contrato
K7: 1
C8: ELABORÓ | F8: REVISÓ | G8: APROBÓ
C9: Claudio Rojas / Jefe Dpto. HSEC | F9: Mauricio Araya / Presidente CPHS | G9: José Maira / Administrador de Contrato
C10: FIRMA: FECHA : 18-02-2026 | F10: FIRMA: FECHA : 18-02-2026 | G10: FIRMA: FECHA : 18-02-2026

Sheet Ley 20.907
D1: Lista de Verificación de Cumplimiento Requisitos Legales y Otros Aplicable a Seguridad, Salud Ocupacional, Medioambiente y Comunidad Contrato 4600029025 - SKIC CC-101 | M1: Código | N1: ='Planilla Global - Cumplim (%)'!I2 -> MTRSE-00002
M2: Revisión | N2: 2
M3: Fecha | N3: 46272
A5: Nº Cuerpo Legal | B5: Fecha de Publicación | C5: Organismo | D5: Nombre del Cuerpo Legal | E5: Artículo | F5: Descripción del Contenido (Breve) | G5: Peligro o Aspecto | H5: Nº Contrato | I5: Modo de Cumplimiento | J5: ¿Cumple? | K5: Porcentaje Cumplimiento | L5: Evidencia del Cumplimiento | M5: Responsable | N5: Fecha de cumplimiento
A6: Ley 20.907 | B6: 42474 | C6: Ministerio del Trabajo y Previsión Social | D6: REGULA LA SITUACIÓN DEL TRABAJADOR DEPENDIENTE QUE SE DESEMPEÑA COMO VOLUNTARIO DEL CUERPO DE BOMBEROS | E6: Art. Único | F6: Agrégase en el Código del Trabajo el siguiente artículo 66 ter: "Art. 66 ter.- Los trabajadores dependientes regidos por el Código del Trabajo y aquellos regidos por el Estatuto Administrativo contenido en la ley Nº18.834, y por el Estatuto Administrativo para Funcionarios Municipales contenido en la ley Nº 18.883, que se desempeñen adicionalmente como voluntarios del Cuerpo de Bomberos estarán facultados para acudir a llamados de emergencia ante accidentes, incendios u otros siniestros que ocurran durante su jornada laboral. El tiempo que estos trabajadores destinen a la atención de estas emergencias será considerado como trabajado para todos los efectos legales. El empleador no podrá, en ningún caso, calificar esta salida como intempestiva e injustificada para configurar la causal de abandono de trabajo establecida en el artículo 160, número 4, letra a), de este Código, o como fundamento de una investigación sumaria o de un sumario administrativo, en su caso. El empleador podrá solicitar a la Comandancia de Bomberos respectiva la acreditación de la circunstancia señalada en este artículo.". Y por cuanto he tenido a bien aprobarlo y sancionarlo; por tanto promúlguese y llévese a efecto como Ley de la República. | G6: NA | H6: 4600029025 CC-101 | I6: Requisito establecido en RIOHS | J6: SI | K6: 1 | L6: Entrega RIOHS | M6: RRHH
K7: 1
C8: ELABORÓ | F8: REVISÓ | G8: APROBÓ
C9: Claudio Rojas / Jefe Dpto. HSEC | F9: Mauricio Araya / Presidente CPHS | G9: José Maira / Administrador de Contrato
C10: FIRMA: FECHA : 18-02-2026 | F10: FIRMA: FECHA : 18-02-2026 | G10: FIRMA: FECHA : 18-02-2026

Sheet Ley 20.920
D1: Lista de Verificación de Cumplimiento Requisitos Legales y Otros Aplicable a Seguridad, Salud Ocupacional, Medioambiente y Comunidad Contrato 4600029025 - SKIC CC-101 | M1: Código | N1: ='Planilla Global - Cumplim (%)'!I2 -> MTRSE-00002
M2: Revisión | N2: 2
M3: Fecha | N3: 46272
A5: Nº Cuerpo Legal | B5: Fecha de Publicación | C5: Organismo | D5: Nombre del Cuerpo Legal | E5: Artículo | F5: Descripción del Contenido (Breve) | G5: Peligro o Aspecto | H5: Nº Contrato | I5: Modo de Cumplimiento | J5: ¿Cumple? | K5: Porcentaje Cumplimiento | L5: Evidencia del Cumplimiento | M5: Responsable | N5: Fecha de cumplimiento
A6: Ley 20.920 | B6: 42522 | C6: MINISTERIO DEL MEDIO AMBIENTE | D6: ESTABLECE MARCO PARA LA GESTIÓN DE RESIDUOS, LA RESPONSABILIDAD EXTENDIDA DEL PRODUCTOR Y FOMENTO AL RECICLAJE | E6: Art.1 | F6: La presente ley tiene por objeto disminuir la generación de residuos y fomentar su reutilización, reciclaje y otro tipo de valorización, a través de la instauración de la responsabilidad extendida del productor y otros instrumentos de gestión de residuos, con el fin de proteger la salud de las personas y el medio ambiente. | G6: N/A | H6: 4600029025 CC-101 | I6: Registrar cantidades de elementos reciclados, en caso de residuos peligrosos contar con resolución sanitaria de la empresa que lo retira | J6: SI | K6: 1 | L6: Registros de residuos reciclados. Certificado de retiro de residuos peligrosos | M6: Administrador Contrato
K7: 1
C8: ELABORÓ | F8: REVISÓ | G8: APROBÓ
C9: Claudio Rojas / Jefe Dpto. HSEC | F9: Mauricio Araya / Presidente CPHS | G9: José Maira / Administrador de Contrato
C10: FIRMA: FECHA : 18-02-2026 | F10: FIRMA: FECHA : 18-02-2026 | G10: FIRMA: FECHA : 18-02-2026

Sheet Ley 20.940
D1: Lista de Verificación de Cumplimiento Requisitos Legales y Otros Aplicable a Seguridad, Salud Ocupacional, Medioambiente y Comunidad Contrato 4600029025 - SKIC CC-101 | M1: Código | N1: ='Planilla Global - Cumplim (%)'!I2 -> MTRSE-00002
M2: Revisión | N2: 2
M3: Fecha | N3: 46272
A5: Nº Cuerpo Legal | B5: Fecha de Publicación | C5: Organismo | D5: Nombre del Cuerpo Legal | E5: Artículo | F5: Descripción del Contenido (Breve) | G5: Peligro o Aspecto | H5: Nº Contrato | I5: Modo de Cumplimiento | J5: ¿Cumple? | K5: Porcentaje Cumplimiento | L5: Evidencia del Cumplimiento | M5: Responsable | N5: Fecha de cumplimiento
A6: Ley 20.940 | B6: 42621 | C6: MINISTERIO DEL TRABAJO Y PREVISIÓN SOCIAL | D6: MODERNIZA EL SISTEMA DE RELACIONES LABORALES | E6: Art.229 | F6: Los trabajadores de una empresa que estén afiliados a un sindicato interempresa o de trabajadores eventuales o transitorios, elegirán uno o más delegados sindicales de acuerdo a las siguientes reglas: de ocho a cincuenta trabajadores elegirán un delegado sindical; de cincuenta y uno a setenta y cinco elegirán dos delegados sindicales, y si fueran setenta y seis o más trabajadores, elegirán tres delegados. Si entre los trabajadores de la empresa se hubieren elegido uno o más directores sindicales, estos cargos se rebajarán en igual proporción del número total de delegados sindicales que corresponda elegir en la respectiva empresa. Los delegados sindicales gozarán del fuero a que se refiere el artículo 243. Las elecciones de los delegados sindicales se realizarán en presencia de un ministro de fe y respecto de ellas se deberá hacer la comunicación a que se refiere el artículo 225, con copia a la Inspección del Trabajo respectiva. | G6: NO CONSTITUIR SINDICATO | H6: 4600029025 CC-101 | I6: CONTRATO DE TRABAJO ELECCION DE ACUERDO AL NUMERO DE TRABAJADORES | J6: SINDICATO CONSTITUIDO | K6: 1 | L6: REGISTRO DE COMUNICACIÓN CON COPIA A LA INSPECCION DEL TRABAJO | M6: RRHH
E7: Art.306 | F7: Materias de la negociación colectiva. Son materia de la negociación colectiva aquellas de interés común de las partes que afecten las relaciones mutuas entre trabajadores y empleadores, especialmente las que se refieran a remuneraciones u otros beneficios en especie o en dinero y, en general, a las condiciones comunes de trabajo. Las negociaciones podrán incluir acuerdos para la conciliación del trabajo con las responsabilidades familiares, el ejercicio de la corresponsabilidad parental, planes de igualdad de oportunidades y equidad de género en la empresa, acciones positivas para corregir situaciones de desigualdad, acuerdos para la capacitación y reconversión productiva de los trabajadores, constitución y mantenimiento de servicios de bienestar, mecanismos de solución de controversias, entre otros. | G7: NO CONSTITUIR SINDICATO | H7: 4600029025 CC-101 | I7: CONTRATO DE TRABAJO ELECCION DE ACUERDO AL NUMERO DE TRABAJADORES | J7: SINDICATO CONSTITUIDO | K7: 1 | L7: REGISTRO DE COMUNICACIÓN CON COPIA A LA INSPECCION DEL TRABAJO | M7: RRHH
K8: 1
C9: ELABORÓ | F9: REVISÓ | G9: APROBÓ
C10: Claudio Rojas / Jefe Dpto. HSEC | F10: Mauricio Araya / Presidente CPHS | G10: José Maira / Administrador de Contrato
C11: FIRMA: FECHA : 18-02-2026 | F11: FIRMA: FECHA : 18-02-2026 | G11: FIRMA: FECHA : 18-02-2026

Sheet Ley 20.949
D1: Lista de Verificación de Cumplimiento Requisitos Legales y Otros Aplicable a Seguridad, Salud Ocupacional, Medioambiente y Comunidad Contrato 4600029025 - SKIC CC-101 | M1: Código | N1: ='Planilla Global - Cumplim (%)'!I2 -> MTRSE-00002
M2: Revisión | N2: 2
M3: Fecha | N3: 46272
A5: Nº Cuerpo Legal | B5: Fecha de Publicación | C5: Organismo | D5: Nombre del Cuerpo Legal | E5: Artículo | F5: Descripción del Contenido (Breve) | G5: Peligro o Aspecto | H5: Nº Contrato | I5: Modo de Cumplimiento | J5: ¿Cumple? | K5: Porcentaje Cumplimiento | L5: Evidencia del Cumplimiento | M5: Responsable | N5: Fecha de cumplimiento
A6: Ley 20.949 | B6: 42630 | C6: MINISTERIO DEL TRABAJO Y PREVISIÓN SOCIAL | D6: MODIFICA EL CÓDIGO DEL TRABAJO PARA REDUCIR EL PESO DE LAS CARGAS DE MANIPULACIÓN MANUAL | E6: Art.211-H | F6: Si la manipulación manual es inevitable y las ayudas mecánicas no pueden usarse, no se permitirá que se opere con cargas superiores a 25 kilogramos. Esta carga será modificada en la medida que existan otros factores agravantes, caso en el cual, la manipulación deberá efectuarse en conformidad a lo dispuesto en el decreto supremo Nº 63, del Ministerio del Trabajo y Previsión Social, del año 2005, que aprueba reglamento para la aplicación de la ley Nº 20.001, que regula el peso máximo de carga humana, y en la Guía Técnica para la Evaluación y Control de los Riesgos Asociados al Manejo o Manipulación Manual de Carga.". | G6: INCUMPLIMIENTO LEGAL | H6: 4600029025 CC-101 | I6: Inducción IRL RIOHS Protocolo MMC | J6: SI | K6: 1 | L6: Registro IRL Entrega RIOHS Implementación Protocolo MMC | M6: Administrador de Contrato
E7: Art.211-J | F7: 2. Reemplázase el artículo 211-J por el que sigue: "Artículo 211-J.- Los menores de 18 años y las mujeres no podrán llevar, transportar, cargar, arrastrar ni empujar manualmente, y sin ayuda mecánica, cargas superiores a 20 kilogramos. Para estos trabajadores, el empleador deberá implementar medidas de seguridad y mitigación, tales como rotación de trabajadores, disminución de las alturas de levantamiento o aumento de la frecuencia con que se manipula la carga. El detalle de la implementación de dichas medidas estará contenido en la Guía Técnica para la Evaluación y Control de los Riesgos Asociados al Manejo o Manipulación Manual de Carga." | G7: INCUMPLIMIENTO LEGAL | H7: 4600029025 CC-101 | I7: Inducción IRL RIOHS Protocolo MMC | J7: SI | K7: 100'% | L7: Registro IRL Entrega RIOHS Implementación Protocolo MMC | M7: Administrador de Contrato
K8: 1
C9: ELABORÓ | F9: REVISÓ | G9: APROBÓ
C10: Claudio Rojas / Jefe Dpto. HSEC | F10: Mauricio Araya / Presidente CPHS | G10: José Maira / Administrador de Contrato
C11: FIRMA: FECHA : 18-02-2026 | F11: FIRMA: FECHA : 18-02-2026 | G11: FIRMA: FECHA : 18-02-2026

Sheet LEY 21.010
D1: Lista de Verificación de Cumplimiento Requisitos Legales y Otros Aplicable a Seguridad, Salud Ocupacional, Medioambiente y Comunidad Contrato 4600029025 - SKIC CC-101 | M1: Código | N1: ='Planilla Global - Cumplim (%)'!I2 -> MTRSE-00002
M2: Revisión | N2: 2
M3: Fecha | N3: 46272
A5: Nº Cuerpo Legal | B5: Fecha de Publicación | C5: Organismo | D5: Nombre del Cuerpo Legal | E5: Artículo | F5: Descripción del Contenido (Breve) | G5: Peligro o Aspecto | H5: Nº Contrato | I5: Modo de Cumplimiento | J5: ¿Cumple? | K5: Porcentaje Cumplimiento | L5: Evidencia del Cumplimiento | M5: Responsable | N5: Fecha de cumplimiento
A6: Ley 21.010 | B6: 42853 | C6: Ministerio del trabajo y previsión social | D6: Extiende y modifica la cotización extraordinaria para el seguro social contra riesgos de accidentes del trabajo y enfermedades profesionales, y crea el fondo que financiará el seguro para el acomañamiento de los niños y niñas | E6: Art.3 | F6: Establécese una cotización del 0,03% de las remuneraciones imponibles de los trabajadores, de cargo del empleador, destinada a la creación de un fondo cuyo objetivo será el financiamiento de un seguro para las madres y padres trabajadores de hijos e hijas mayores de 1 año y menores de 15 o 18 años de edad, según corresponda, afectados por una condición grave de salud, para que puedan ausentarse justificadamente de su trabajo durante un tiempo determinado, con la finalidad de prestarles atención, acompañamiento o cuidado personal a sus hijos e hijas. Durante dicho período las madres y padres trabajadores tendrán derecho a una prestación económica que reemplazará total o parcialmente su remuneración mensual, la que se financiará con cargo al fondo. La recaudación de esta cotización se efectuará por las mutualidades de empleadores y el Instituto de Seguridad Laboral, conjuntamente con las demás cotizaciones que recaudan para el financiamiento del seguro de la ley N° 16.744. | G6: Factores psicosociales - Doble presencia | H6: 4600029025 CC-101 | I6: Autorización del empleador para ausencia justificada según establece el requisito legal | J6: SI | K6: 1 | L6: Certificado de pago de cotizaciones | M6: Administrador Contrato
K7: 1
C8: ELABORÓ | F8: REVISÓ | G8: APROBÓ
C9: Claudio Rojas / Jefe Dpto. HSEC | F9: Mauricio Araya / Presidente CPHS | G9: José Maira / Administrador de Contrato
C10: FIRMA: FECHA : 18-02-2026 | F10: FIRMA: FECHA : 18-02-2026 | G10: FIRMA: FECHA : 18-02-2026

Sheet LEY 21.012
D1: Lista de Verificación de Cumplimiento Requisitos Legales y Otros Aplicable a Seguridad, Salud Ocupacional, Medioambiente y Comunidad Contrato 4600029025 - SKIC CC-101 | M1: Código | N1: ='Planilla Global - Cumplim (%)'!I2 -> MTRSE-00002
M2: Revisión | N2: 2
M3: Fecha | N3: 46272
A5: Nº Cuerpo Legal | B5: Fecha de Publicación | C5: Organismo | D5: Nombre del Cuerpo Legal | E5: Artículo | F5: Descripción del Contenido (Breve) | G5: Peligro o Aspecto | H5: Nº Contrato | I5: Modo de Cumplimiento | J5: ¿Cumple? | K5: Porcentaje Cumplimiento | L5: Evidencia del Cumplimiento | M5: Responsable | N5: Fecha de cumplimiento
A6: Ley 21.012 | B6: 42895 | C6: MINISTERIO DEL TRABAJO Y PREVISIÓN SOCIAL | D6: Garantiza Seguridad de los Trabajadores en Situaciones de Riesgo y Emergencia | E6: Art.184bis | F6: Sin perjuicio de lo establecido en el artículo precedente, cuando en el lugar de trabajo sobrevenga un riesgo grave e inminente para la vida o salud de los trabajadores, el empleador deberá: a) Informar inmediatamente a todos los trabajadores afectados sobre la existencia del mencionado riesgo, así como las medidas adoptadas para eliminarlo o atenuarlo. b) Adoptar medidas para la suspensión inmediata de las faenas afectadas y la evacuación de los trabajadores, en caso que el riesgo no se pueda eliminar o atenuar. Con todo, el trabajador tendrá derecho a interrumpir sus labores y, de ser necesario, abandonar el lugar de trabajo cuando considere, por motivos razonables, que continuar con ellas implica un riesgo grave e inminente para su vida o salud. El trabajador que interrumpa sus labores deberá dar cuenta de ese hecho al empleador dentro del más breve plazo, el que deberá informar de la suspensión de las mismas a la Inspección del Trabajo respectiva. | G6: No difundir la existencia de los riesgos y las medidas de control atingentes al contrato | H6: 4600029025 CC-101 | I6: Incorporado en Inducción IRL | J6: SI | K6: 1 | L6: Registro IRL | M6: Administrador de Contrato - HSEC
K7: 1
C8: ELABORÓ | F8: REVISÓ | G8: APROBÓ
C9: Claudio Rojas / Jefe Dpto. HSEC | F9: Mauricio Araya / Presidente CPHS | G9: José Maira / Administrador de Contrato
C10: FIRMA: FECHA : 18-02-2026 | F10: FIRMA: FECHA : 18-02-2026 | G10: FIRMA: FECHA : 18-02-2026

Sheet Ley 21.015
D1: Lista de Verificación de Cumplimiento Requisitos Legales y Otros Aplicable a Seguridad, Salud Ocupacional, Medioambiente y Comunidad Contrato 4600029025 - SKIC CC-101 | M1: Código | N1: ='Planilla Global - Cumplim (%)'!I2 -> MTRSE-00002
M2: Revisión | N2: 2
M3: Fecha | N3: 46272
A5: Nº Cuerpo Legal | B5: Fecha de Publicación | C5: Organismo | D5: Nombre del Cuerpo Legal | E5: Artículo | F5: Descripción del Contenido (Breve) | G5: Peligro o Aspecto | H5: Nº Contrato | I5: Modo de Cumplimiento | J5: ¿Cumple? | K5: Porcentaje Cumplimiento | L5: Evidencia del Cumplimiento | M5: Responsable | N5: Fecha de cumplimiento
A6: Ley 21.015 | B6: 42474 | C6: Ministerio de Desarrollo Social | D6: INCENTIVA LA INCLUSIÓN DE PERSONAS CON DISCAPACIDAD AL MUNDO LABORAL | E6: Art.2 | F6: Sustitúyese el inciso tercero del artículo 17 de la ley N° 18.834, sobre Estatuto Administrativo, cuyo texto refundido, coordinado y sistematizado fue fijado por el decreto con fuerza de ley N° 29, de 2004, del Ministerio de Hacienda, por el siguiente: "Prohíbese todo acto de discriminación arbitraria que se traduzca en exclusiones o restricciones, tales como aquellas basadas en motivos de raza o etnia, situación socioeconómica, idioma, ideología u opinión política, discapacidad, religión o creencia, sindicación o participación en organizaciones gremiales o la falta de ellas, sexo, orientación sexual, identidad de género, estado civil, edad, filiación, apariencia personal o enfermedad, que tengan por objeto anular o alterar la igualdad de oportunidades o trato en el empleo.". | G6: NA | H6: 4600029025 CC-101 | I6: Incorporado en RIOHS | J6: SI | K6: 1 | L6: Registro Entrega RIOHS | M6: RRHH
E7: Art.157 bis | F7: Las empresas de 100 o más trabajadores deberán contratar o mantener contratados, según corresponda, al menos el 1% de personas con discapacidad o que sean asignatarias de una pensión de invalidez de cualquier régimen previsional, en relación al total de sus trabajadores. Las personas con discapacidad deberán contar con la calificación y certificación señaladas en el artículo 13 de la ley N° 20.422. El empleador deberá registrar los contratos de trabajo celebrados con personas con discapacidad o asignatarios de una pensión de invalidez de cualquier régimen previsional, así como sus modificaciones o términos, dentro de los quince días siguientes a su celebración a través del sitio electrónico de la Dirección del Trabajo, la que llevará un registro actualizado de lo anterior, debiendo mantener reserva de dicha información. | G7: NA | H7: 4600029025 CC-101 | I7: Contrato de Trabajo | J7: NO | K7: 1 | L7: Certificado de Discapacidad en Carpeta personal | M7: RRHH
K8: 1
C9: ELABORÓ | F9: REVISÓ | G9: APROBÓ
C10: Claudio Rojas / Jefe Dpto. HSEC | F10: Mauricio Araya / Presidente CPHS | G10: José Maira / Administrador de Contrato
C11: FIRMA: FECHA : 18-02-2026 | F11: FIRMA: FECHA : 18-02-2026 | G11: FIRMA: FECHA : 18-02-2026

Sheet LEY 21.042
D1: Lista de Verificación de Cumplimiento Requisitos Legales y Otros Aplicable a Seguridad, Salud Ocupacional, Medioambiente y Comunidad Contrato 4600029025 - SKIC CC-101 | M1: Código | N1: ='Planilla Global - Cumplim (%)'!I2 -> MTRSE-00002
M2: Revisión | N2: 2
M3: Fecha | N3: 46272
A5: Nº Cuerpo Legal | B5: Fecha de Publicación | C5: Organismo | D5: Nombre del Cuerpo Legal | E5: Artículo | F5: Descripción del Contenido (Breve) | G5: Peligro o Aspecto | H5: Nº Contrato | I5: Modo de Cumplimiento | J5: ¿Cumple? | K5: Porcentaje Cumplimiento | L5: Evidencia del Cumplimiento | M5: Responsable | N5: Fecha de cumplimiento
A6: Ley 21.042 | B6: 43047 | C6: Ministerio de Trabajo y previsión social | D6: Aplica al trabajador que celebra un acuerdo de unión civil, el permiso laboral que otorga a quien contrae matrimonio | E6: Art. Único | F6: Artículo 207 bis : En el caso de contraer matrimonio o celebrar un acuerdo de unión civil, de conformidad con lo previsto en la ley N° 20.830, todo trabajador tendrá derecho a cinco días habiles continuos de permiso pagado, adicional al feriado anual, indeendientemente del tiempo de servicio. Este permiso se podrá utilizar, a elección de trabajador, en el día del matrimonio o del acuerdo de unión civil y en los días inmediatamente anteriores o posteriores al de su celebración. El trabajador deberá dar aviso a su empleador con treinta días de anticipación y oresentar dentro de los treinta días siguientes a la celebración el respectivocertificado de matrimonio o acuerdo de unión civil | G6: No otorgar el permiso | H6: 4600029025 CC-101 | I6: Autorización del empleador para ausentarse los días indicados por el trabajador. | J6: SI | K6: 1 | L6: Formulario de permiso laboral otorgado al trabajador. Certificado de matrimonio o acuerdo de unión civil | M6: Administrador Contrato
K7: 1
C8: ELABORÓ | F8: REVISÓ | G8: APROBÓ
C9: Claudio Rojas / Jefe Dpto. HSEC | F9: Mauricio Araya / Presidente CPHS | G9: José Maira / Administrador de Contrato
C10: FIRMA: FECHA : 18-02-2026 | F10: FIRMA: FECHA : 18-02-2026 | G10: FIRMA: FECHA : 18-02-2026

Sheet LEY 21.054
D1: Lista de Verificación de Cumplimiento Requisitos Legales y Otros Aplicable a Seguridad, Salud Ocupacional, Medioambiente y Comunidad Contrato 4600029025 - SKIC CC-101 | M1: Código | N1: ='Planilla Global - Cumplim (%)'!I2 -> MTRSE-00002
M2: Revisión | N2: 2
M3: Fecha | N3: 46272
A5: Nº Cuerpo Legal | B5: Fecha de Publicación | C5: Organismo | D5: Nombre del Cuerpo Legal | E5: Artículo | F5: Descripción del Contenido (Breve) | G5: Peligro o Aspecto | H5: Nº Contrato | I5: Modo de Cumplimiento | J5: ¿Cumple? | K5: Porcentaje Cumplimiento | L5: Evidencia del Cumplimiento | M5: Responsable | N5: Fecha de cumplimiento
A6: Ley 21.054 | B6: 43092 | C6: MINISTERIO DEL TRABAJO Y PREVISIÓN SOCIAL | D6: MODIFICA LA LEY N° 16.744, QUE ESTABLECE NORMAS SOBRE ACCIDENTES DEL TRABAJO Y ENFERMEDADES PROFESIONALES, CON EL OBJETO DE ELIMINAR LA DISTINCIÓN ENTRE EMPLEADOS Y OBREROS | E6: Art. Único | F6: Modifícase la ley N° 16.744, que establece normas sobre accidentes del trabajo y enfermedades profesionales, en la forma que a continuación se indica: 1. Sustitúyese el artículo 4 por el siguiente: "Artículo 4.- Para los efectos de este seguro, todos los empleadores se entenderán afiliados al Instituto de Seguridad Laboral respecto de la totalidad de sus trabajadores, salvo que se adhieran a alguna mutualidad de empleadores. Lo dispuesto en el inciso anterior también se aplicará a los trabajadores independientes afectos al seguro de esta ley.". | G6: No afiliarse al OAL y sus trabajadores | H6: 4600029025 CC-101 | I6: Cumplir con la afiliación del OAL y de sus trabajadores. | J6: SI | K6: 1 | L6: Certificado de Adehisón OAL Pago de Cotizaciones | M6: Administrador de Contrato
K7: 1
C8: ELABORÓ | F8: REVISÓ | G8: APROBÓ
C9: Claudio Rojas / Jefe Dpto. HSEC | F9: Mauricio Araya / Presidente CPHS | G9: José Maira / Administrador de Contrato
C10: FIRMA: FECHA : 18-02-2026 | F10: FIRMA: FECHA : 18-02-2026 | G10: FIRMA: FECHA : 18-02-2026

Sheet LEY 21.103
D1: Lista de Verificación de Cumplimiento Requisitos Legales y Otros Aplicable a Seguridad, Salud Ocupacional, Medioambiente y Comunidad Contrato 4600029025 - SKIC CC-101 | M1: Código | N1: ='Planilla Global - Cumplim (%)'!I2 -> MTRSE-00002
M2: Revisión | N2: 2
M3: Fecha | N3: 46272
A5: Nº Cuerpo Legal | B5: Fecha de Publicación | C5: Organismo | D5: Nombre del Cuerpo Legal | E5: Artículo | F5: Descripción del Contenido (Breve) | G5: Peligro o Aspecto | H5: Nº Contrato | I5: Modo de Cumplimiento | J5: ¿Cumple? | K5: Porcentaje Cumplimiento | L5: Evidencia del Cumplimiento | M5: Responsable | N5: Fecha de cumplimiento
A6: Ley 21.103 | B6: 43316 | C6: MINISTERIO DE TRANSPORTES Y TELECOMUNICACIONES | D6: MODIFICA LA LEY DE TRÁNSITO, EN LO RELATIVO A LA VELOCIDAD MÁXIMA DE CIRCULACIÓN EN ZONAS URBANAS | E6: Art. Único | F6: Reemplázase, en el ordinal 1.1 del número 1 del artículo 145 del decreto con fuerza de ley N° 1, de los Ministerios de Transportes y Telecomunicaciones y de Justicia, promulgado el año 2007 y publicado el año 2009, que fija el texto refundido, coordinado y sistematizado de la ley N° 18.290, de Tránsito, la frase "60 kilómetros por hora", por la siguiente: "50 kilómetros por hora".". Y por cuanto he tenido a bien aprobarlo y sancionarlo; por tanto promúlguese y llévese a efecto como Ley de la República. Santiago, 17 de julio de 2018.- SEBASTIÁN PIÑERA ECHENIQUE, Presidente de la República.- Gloria Hutt Hesse, Ministra de Transportes y Telecomunicaciones.- Hernán Larraín Fernández, Ministro de Justicia y Derechos Humanos. Lo que transcribo a Ud. para su conocimiento.- Saluda atentamente a Ud., José Luis Domínguez Covarrubias, Subsecretario de Transportes. | G6: No informar a trabajadores que utilicen vehículos de la empresa, en ocasiones en la ciudad, sobre las velocidades estipuladas en esta ley. | H6: 4600029025 CC-101 | I6: informar a trabajadores que utilicen vehículos de la empresa, en ocasiones en la ciudad, sobre las velocidades estipuladas en esta ley. | J6: NO | K6: 1 | L6: Registro de difusión a trabajadores, que conducen vehículos empresa. | M6: Administrador de Contrato
K7: 1
C8: ELABORÓ | F8: REVISÓ | G8: APROBÓ
C9: Claudio Rojas / Jefe Dpto. HSEC | F9: Mauricio Araya / Presidente CPHS | G9: José Maira / Administrador de Contrato
C10: FIRMA: FECHA : 18-02-2026 | F10: FIRMA: FECHA : 18-02-2026 | G10: FIRMA: FECHA : 18-02-2026

Sheet LEY 21.120
D1: Lista de Verificación de Cumplimiento Requisitos Legales y Otros Aplicable a Seguridad, Salud Ocupacional, Medioambiente y Comunidad Contrato 4600029025 - SKIC CC-101 | M1: Código | N1: ='Planilla Global - Cumplim (%)'!I2 -> MTRSE-00002
M2: Revisión | N2: 2
M3: Fecha | N3: 46272
A5: Nº Cuerpo Legal | B5: Fecha de Publicación | C5: Organismo | D5: Nombre del Cuerpo Legal | E5: Artículo | F5: Descripción del Contenido (Breve) | G5: Peligro o Aspecto | H5: Nº Contrato | I5: Modo de Cumplimiento | J5: ¿Cumple? | K5: Porcentaje Cumplimiento | L5: Evidencia del Cumplimiento | M5: Responsable | N5: Fecha de cumplimiento
A6: Ley 21.120 | B6: 43444 | C6: MINISTERIO DE JUSTICIA Y DERECHOS HUMANOS | D6: RECONOCE Y DA PROTECCIÓN AL DERECHO A LA IDENTIDAD DE GÉNERO | E6: Art.5 | F6: PRINCIPIOS RELATIVOS AL DERECHO A LA IDENTIDAD DE GÉNERO. El derecho a la identidad de género reconoce, entre otros, los siguientes principios: a) Principio de la no patologización: el reconocimiento y la protección de la identidad de género considera como un aspecto primordial, el derecho de toda persona trans a no ser tratada como enferma. b) Principio de la no discriminación arbitraria: los órganos del Estado garantizarán que, en el ejercicio del derecho a la identidad de género, ninguna persona sea afectada por distinciones, exclusiones o restricciones que carezcan de justificación razonable, en los términos del artículo 2° de la ley N° 20.609, que establece medidas contra la discriminación. c) Principio de la confidencialidad: toda persona tiene derecho a que, en los procedimientos seguidos ante autoridad administrativa o jurisdiccional, se resguarde el carácter reservado de los antecedentes considerados como datos sensibles, en los términos señalados por la letra g) del artículo 2° de la ley N° 19.628, sobre protección de la vida privada. d) Principio de la dignidad en el trato: los órganos del Estado deberán respetar la dignidad intrínseca de las personas, emanada de la naturaleza humana, como un eje esencial de los derechos fundamentales reconocidos por la Constitución Política de la República y por los tratados internacionales sobre derechos humanos ratificados por Chile y que se encuentren vigentes. Toda persona tiene derecho a recibir por parte de los órganos del Estado un trato amable y respetuoso en todo momento y circunstancia. | G6: Discriminación por Identidad de Genero | H6: 4600029025 CC-101 | I6: Requisitos establecidos en RIOSH, MIPER, IRL | J6: SI | K6: 1 | L6: Entrega RIOHS | M6: RRHH
K7: 1
C8: ELABORÓ | F8: REVISÓ | G8: APROBÓ
C9: Claudio Rojas / Jefe Dpto. HSEC | F9: Mauricio Araya / Presidente CPHS | G9: José Maira / Administrador de Contrato
C10: FIRMA: FECHA : 18-02-2026 | F10: FIRMA: FECHA : 18-02-2026 | G10: FIRMA: FECHA : 18-02-2026

Sheet LEY 21.122
D1: Lista de Verificación de Cumplimiento Requisitos Legales y Otros Aplicable a Seguridad, Salud Ocupacional, Medioambiente y Comunidad Contrato 4600029025 - SKIC CC-101 | M1: Código | N1: ='Planilla Global - Cumplim (%)'!I2 -> MTRSE-00002
M2: Revisión | N2: 2
M3: Fecha | N3: 46272
A5: Nº Cuerpo Legal | B5: Fecha de Publicación | C5: Organismo | D5: Nombre del Cuerpo Legal | E5: Artículo | F5: Descripción del Contenido (Breve) | G5: Peligro o Aspecto | H5: Nº Contrato | I5: Modo de Cumplimiento | J5: ¿Cumple? | K5: Porcentaje Cumplimiento | L5: Evidencia del Cumplimiento | M5: Responsable | N5: Fecha de cumplimiento
A6: Ley 21.122 | B6: 43525 | C6: MINISTERIO DEL TRABAJO Y PREVISIÓN SOCIAL | D6: MODIFICA EL CÓDIGO DEL TRABAJO EN MATERIA DE CONTRATO DE TRABAJO POR OBRA O FAENA | E6: Art.1 | F6: Sin perjuicio de lo dispuesto en el número 6 del artículo 10, las partes podrán celebrar un contrato por una obra o faena determinada. El contrato por obra o faena es aquella convención por la que el trabajador se obliga con el respectivo empleador a ejecutar una obra material o intelectual específica y determinada, en su inicio y en su término, cuya vigencia se encuentra circunscrita o limitada a la duración de aquélla. Las diferentes tareas o etapas de una obra o faena no podrán por sí solas ser objeto de dos o más contratos de este tipo en forma sucesiva, caso en el cual se entenderá que el contrato es de plazo indefinido. | G6: No Informar sobre la ley que regula los contratos de trabajadoras y trabajadores circunscritos a una obra o faena determinada. | H6: 4600029025 CC-101 | I6: La ley se aplicará a los nuevos contratos por obra o faena determinada, que se celebren a contar del 1 de enero de 2019. El derecho a una indemnización por despido, equivalente a dos y medio días de remuneración por cada mes trabajado, se implementará gradualmente en 37 meses. | J6: SI | K6: 1 | L6: Anexo al Contrato de Trabajo | M6: RRHH | O6: https://www.bcn.cl/leychile/navegar?idNorma=1125900
E7: Art.1 | F7: 2.- Sustitúyese en el inciso segundo del artículo 41 la expresión "la indemnización por años de servicios establecida" por "las indemnizaciones establecidas". 3.- Agrégase en el artículo 67 el siguiente inciso segundo nuevo, pasando los actuales incisos segundo y tercero, a ser tercero y cuarto, respectivamente: "Igual derecho asistirá al trabajador que preste servicios continuos al mismo empleador en virtud de dos o más contratos celebrados por obra o faena determinada y que sobrepasen el año. Con todo, y sólo para estos efectos, el trabajador podrá optar por que el pago de su feriado proporcional se difiera al momento de hacerlo efectivo en las condiciones señaladas en este inciso, debiendo dejar constancia expresa de ello en el respectivo finiquito. En caso de que los contratos no sobrepasen el año y el trabajador hubiere diferido el pago de los feriados conforme lo señala este inciso, el empleador deberá pagar en el último finiquito la totalidad de los feriados adeudados.". | G7: No Informar sobre la ley que regula los contratos de trabajadoras y trabajadores circunscritos a una obra o faena determinada. | H7: 4600029025 CC-101 | I7: La ley se aplicará a los nuevos contratos por obra o faena determinada, que se celebren a contar del 1 de enero de 2019. El derecho a una indemnización por despido, equivalente a dos y medio días de remuneración por cada mes trabajado, se implementará gradualmente en 37 meses. | J7: SI | K7: 1 | L7: Anexo al Contrato de Trabajo | M7: RRHH
E8: Art.1 | F8: 4.- Agrégase en el inciso cuarto del artículo 162 la siguiente oración final: "Igual indicación deberá contener la comunicación de la terminación del contrato celebrado para una obra o faena determinada, cuando corresponda el pago de indemnización por el tiempo servido, en conformidad a lo dispuesto en el artículo 163.". 5.- Incorpórase en el artículo 163 el siguiente inciso tercero, pasando los actuales incisos tercero y cuarto a ser cuarto y quinto, respectivamente: "Si el contrato celebrado para una obra o faena determinada hubiere estado vigente por un mes o más, el empleador podrá ponerle término en forma justificada en tanto pague al trabajador, en el momento de su terminación, una indemnización equivalente a dos y medio días de remuneración por cada mes trabajado y fracción superior a quince días, en la forma y modalidad señalada en el artículo 23 transitorio de este Código. Esta indemnización será calculada en conformidad a lo establecido en el artículo 172, y le será aplicable lo dispuesto en el inciso segundo del artículo 13 de la ley N° 19.728. Sólo corresponderá el pago de la prestación antes señalada, si se pusiere término al contrato por la causal contemplada en el número 5 del artículo 159. El ejercicio del derecho establecido en este inciso por parte del trabajador es incompatible con las acciones derivadas de la aplicación del inciso primero del artículo 168, sin perjuicio de las acciones señaladas en el artículo 485 de este Código.". | G8: No Informar sobre la ley que regula los contratos de trabajadoras y trabajadores circunscritos a una obra o faena determinada. | H8: 4600029025 CC-101 | I8: La ley se aplicará a los nuevos contratos por obra o faena determinada, que se celebren a contar del 1 de enero de 2019. El derecho a una indemnización por despido, equivalente a dos y medio días de remuneración por cada mes trabajado, se implementará gradualmente en 37 meses. | J8: SI | K8: 1 | L8: Anexo al Contrato de Trabajo | M8: RRHH
A9: Ley 21.122 | B9: 43525 | C9: MINISTERIO DEL TRABAJO Y PREVISIÓN SOCIAL | D9: MODIFICA EL CÓDIGO DEL TRABAJO EN MATERIA DE CONTRATO DE TRABAJO POR OBRA O FAENA | E9: Art.1 | F9: 6.- Agrégase, en el artículo 169, el siguiente inciso final: "Lo dispuesto en la letra a) de este artículo se aplicará a la indemnización que el empleador está obligado a pagar al trabajador por causa de la terminación del contrato celebrado para una obra o faena determinada, de conformidad a lo establecido en el inciso tercero del artículo 163.". | G9: No Informar sobre la ley que regula los contratos de trabajadoras y trabajadores circunscritos a una obra o faena determinada. | H9: 4600029025 CC-101 | I9: La ley se aplicará a los nuevos contratos por obra o faena determinada, que se celebren a contar del 1 de enero de 2019. El derecho a una indemnización por despido, equivalente a dos y medio días de remuneración por cada mes trabajado, se implementará gradualmente en 37 meses. | J9: SI | K9: 1 | L9: Anexo al Contrato de Trabajo | M9: RRHH
E10: Art.1 | F10: 7.- Intercálase en el inciso primero del artículo 172, a continuación de la palabra "artículos",la expresión "163,". 8.- Intercálase en el artículo 173, a continuación de la palabra "artículos", la expresión "163,". 9.- Agrégase el siguiente artículo 23 transitorio: "Artículo 23.- La norma señalada en el inciso tercero del artículo 163 se aplicará de la siguiente manera: a) En los contratos celebrados durante los primeros dieciocho meses de vigencia de dicha norma, los trabajadores tendrán derecho al pago de una indemnización equivalente a un día de remuneración por cada mes trabajado y fracción superior a quince días. b) En los contratos celebrados a partir del primer día del decimonoveno mes de vigencia de dicha norma y por los siguientes doce meses, los trabajadores tendrán derecho al pago de una indemnización equivalente a un día y medio de remuneración por cada mes trabajado y fracción superior a quince días. c) En los contratos celebrados a partir del primer día del trigésimo primer mes de vigencia de dicha norma y por los siguientes seis meses, los trabajadores tendrán derecho al pago de una indemnización equivalente a dos días de remuneración por cada mes trabajado y fracción superior a quince días. d) En los contratos celebrados con posterioridad al último día del tramo anterior, los trabajadores tendrán derecho al pago de la indemnización en los mismos términos que se señalan en la norma permanente. Si el contrato por obra o faena determinada es celebrado durante alguno de los períodos señalados en las letras a), b) o c), y termina durante un período distinto, el trabajador tendrá derecho al pago de la indemnización que corresponde por los meses trabajados en cada uno de dichos períodos. Con todo, si en los meses de inicio y término de un contrato por obra o faena se produce el cambio de tramo, conforme a los literales del inciso primero, la indemnización corresponderá en dichos meses al tramo vigente el primer día del mes de inicio y primer día del mes de término, respectivamente.". | G10: No Informar sobre la ley que regula los contratos de trabajadoras y trabajadores circunscritos a una obra o faena determinada. | H10: 4600029025 CC-101 | I10: La ley se aplicará a los nuevos contratos por obra o faena determinada, que se celebren a contar del 1 de enero de 2019. El derecho a una indemnización por despido, equivalente a dos y medio días de remuneración por cada mes trabajado, se implementará gradualmente en 37 meses. | J10: SI | K10: 1 | L10: Anexo al Contrato de Trabajo | M10: RRHH
E11: Art.2 | F11: Tratándose de personas que hayan efectuado cotizaciones de salud al Fondo Nacional de Salud, al menos durante cuatro meses en los últimos doce meses calendario en virtud de contratos por obra o faena determinada, mantendrán la calidad de afiliados por un período de doce meses a contar del mes al que corresponde la última cotización. El Director del Fondo Nacional de Salud deberá emitir, en un lapso no superior a sesenta días contado desde la vigencia de la presente ley, una resolución que establezca un procedimiento expedito, directo y completo que garantice el derecho a cobertura de salud, a partir del término de la relación laboral de los trabajadores contratados por obra o faena determinada, en la forma establecida en el inciso primero de este artículo y el literal a) del artículo 135 del decreto con fuerza de ley N° 1, del Ministerio de Salud, promulgado el año 2005 y publicado el año 2006, que fija el texto refundido, coordinado y sistematizado del decreto ley N° 2.763, de 1979 y de las leyes números 18.933 y 18.469. | G11: No Informar sobre la ley que regula los contratos de trabajadoras y trabajadores circunscritos a una obra o faena determinada. | H11: 4600029025 CC-101 | I11: La ley se aplicará a los nuevos contratos por obra o faena determinada, que se celebren a contar del 1 de enero de 2019. El derecho a una indemnización por despido, equivalente a dos y medio días de remuneración por cada mes trabajado, se implementará gradualmente en 37 meses. | J11: SI | K11: 1 | L11: Anexo al Contrato de Trabajo | M11: RRHH
K12: 1
C13: ELABORÓ | F13: REVISÓ | G13: APROBÓ
C14: Claudio Rojas / Jefe Dpto. HSEC | F14: Mauricio Araya / Presidente CPHS | G14: José Maira / Administrador de Contrato
C15: FIRMA: FECHA : 18-02-2026 | F15: FIRMA: FECHA : 18-02-2026 | G15: FIRMA: FECHA : 18-02-2026

Sheet LEY 21.155
D1: Lista de Verificación de Cumplimiento Requisitos Legales y Otros Aplicable a Seguridad, Salud Ocupacional, Medioambiente y Comunidad Contrato 4600029025 - SKIC CC-101 | M1: Código | N1: ='Planilla Global - Cumplim (%)'!I2 -> MTRSE-00002
M2: Revisión | N2: 2
M3: Fecha | N3: 46272
A5: Nº Cuerpo Legal | B5: Fecha de Publicación | C5: Organismo | D5: Nombre del Cuerpo Legal | E5: Artículo | F5: Descripción del Contenido (Breve) | G5: Peligro o Aspecto | H5: Nº Contrato | I5: Modo de Cumplimiento | J5: ¿Cumple? | K5: Porcentaje Cumplimiento | L5: Evidencia del Cumplimiento | M5: Responsable | N5: Fecha de cumplimiento
A6: Ley 21.155 | B6: 43587 | C6: MINISTERIO DE LA MUJER Y LA EQUIDAD DE GÉNERO | D6: ESTABLECE MEDIDAS DE PROTECCIÓN A LA LACTANCIA MATERNA Y SU EJERCICIO | E6: Art.7 | F6: "Para todos los efectos se entenderá que la lactancia con leche materna o lactancia materna es el medio óptimo e ideal para asegurar la alimentación saludable de lactantes, hasta los seis meses de manera exclusiva y hasta los dos años de edad en forma complementaria, y constituye la forma más eficiente de protección integral de la salud de madres e infantes lactantes. El Estado y la sociedad civil promoverán, protegerán y apoyarán la lactancia materna de conformidad con lo dispuesto en el inciso anterior.". | G6: No cumplir con lo establecido en la Ley de amamantamiento | H6: 4600029025 CC-101 | I6: Requisito establecido en EST N°10 | J6: SI | K6: 1 | L6: Documentación RRHH Respaldo cumplimiento EST | M6: RRHH | O6: https://www.bcn.cl/leychile/navegar?idNorma=1131064
K7: 1
C8: ELABORÓ | F8: REVISÓ | G8: APROBÓ
C9: Claudio Rojas / Jefe Dpto. HSEC | F9: Mauricio Araya / Presidente CPHS | G9: José Maira / Administrador de Contrato
C10: FIRMA: FECHA : 18-02-2026 | F10: FIRMA: FECHA : 18-02-2026 | G10: FIRMA: FECHA : 18-02-2026

Sheet LEY 21.165
D1: Lista de Verificación de Cumplimiento Requisitos Legales y Otros Aplicable a Seguridad, Salud Ocupacional, Medioambiente y Comunidad Contrato 4600029025 - SKIC CC-101 | M1: Código | N1: ='Planilla Global - Cumplim (%)'!I2 -> MTRSE-00002
M2: Revisión | N2: 2
M3: Fecha | N3: 46272
